Workbook

Sheet Summary and Assumptions
B1: =D9 -> Fund Name | K1: Model Key
B2: Portfolio Model | K2: Hardcoded assumption, can edit
K3: Formula, do not edit
K4: Pull from another tab, do not edit
K5: Pull from another tab, can be updated
A6: x | B6: Fund Characteristics
C9: Name | D9: Fund Name | F9: # of target initial investments: | G9: =D102 -> 35
C10: Start Date | D10: 44197
C11: Fund Size | D11: 100000000 | F11: Deals to date: | G11: =SUM(Portfolio!R158:V158) -> 0
C12: End date of intl invt period | D12: {=INDEX(Portfolio!F7:F156,(MATCH(D102,Portfolio!C7:C156,0)+1))} -> 45422 | F12: Intl Invst. to date: | G12: =Portfolio!O158 -> 0
C13: Today's Date | D13: =TODAY() -> 43958
C15: Fund to Date | D15: Seed | E15: Ext | F15: Series A | G15: Series B | H15: Series C | I15: All Rounds
C16: Invested | D16: =Portfolio!R159 -> 0 | E16: =Portfolio!S159 -> 0 | F16: =Portfolio!T159 -> 0 | G16: =Portfolio!U159 -> 0 | H16: =Portfolio!V159 -> 0 | I16: =IFERROR(SUM(D16:H16),"NA") -> 0
C17: Returned | D17: =Portfolio!R160 -> 0 | E17: =Portfolio!S160 -> 0 | F17: =Portfolio!T160 -> 0 | G17: =Portfolio!U160 -> 0 | H17: =Portfolio!V160 -> 0 | I17: =IFERROR(SUM(D17:H17),"NA") -> 0
C18: Rate | D18: =IFERROR(D17/D16,"NA") -> NA | E18: =IFERROR(E17/E16,"NA") -> NA | F18: =IFERROR(F17/F16,"NA") -> NA | G18: =IFERROR(G17/G16,"NA") -> NA | H18: =IFERROR(H17/H16,"NA") -> NA | I18: =IFERROR(I17/I16,"NA") -> NA
C19: # of Deals | D19: =Portfolio!R158 -> 0 | E19: =Portfolio!S158 -> 0 | F19: =Portfolio!T158 -> 0 | G19: =Portfolio!U158 -> 0 | H19: =Portfolio!V158 -> 0 | I19: =IFERROR(SUM(D19:H19),"NA") -> 0
C20: Average Deal Size | D20: =Portfolio!R157 -> NA | E20: =Portfolio!S157 -> NA | F20: =Portfolio!T157 -> NA | G20: =Portfolio!U157 -> NA | H20: =Portfolio!V157 -> NA | I20: =IFERROR(SUM(D20:H20),"NA") -> 0
C21: Total Conversion Rate | E21: =IFERROR(E19/$D$19,"NA") -> NA | F21: =IFERROR(F19/$D$19,"NA") -> NA | G21: =IFERROR(G19/$D$19,"NA") -> NA | H21: =IFERROR(H19/$D$19,"NA") -> NA
C22: Conversion Rate excl deals in last 2yrs | E22: =Portfolio!R165 -> NA | F22: =Portfolio!S165 -> NA | G22: =Portfolio!T165 -> NA | H22: =Portfolio!U165 -> NA
A25: x | B25: Summary
D28: Initial Invsts | E28: Follow-On Invsts | F28: Total Investment | G28: Seed Invsts | H28: Ext Invsts | I28: Series A Invsts | J28: Series B Invsts | K28: Series C Invsts | L28: Mgmt Fees | M28: Other Expenses | N28: Total Expenses | O28: Recycled Returns | P28: Total Returns | Q28: Distributions
C29: Actual to Date | D29: =Portfolio!R159 -> 0 | E29: =SUM(Portfolio!S159:V159) -> 0 | F29: =SUM(E29,D29) -> 0 | G29: =D16 -> 0 | H29: =E16 -> 0 | I29: =F16 -> 0 | J29: =G16 -> 0 | K29: =H16 -> 0 | L29: =SUMIF(Model!D4:BS4,"<="&TODAY(),Model!D121:BS121) -> 0 | M29: =SUMPRODUCT((Model!$D$4:$BS$4<=$D$13)*(Model!D115:BS120)) -> 0 | N29: =SUM(M29,L29) -> 0 | O29: =P29-Q29 -> 0 | P29: =Portfolio!W159 -> 0 | Q29: =SUMIF(Model!D4:BS4,"<="&TODAY(),Model!D138:BS138) -> 0
C30: Forecasted | D30: =Portfolio!AC159 -> 43750000 | E30: =SUM(Portfolio!AD159:AG159) -> 63000000 | F30: =SUM(E30,D30) -> 106750000 | G30: =Portfolio!AC159 -> 43750000 | H30: =Portfolio!AD159 -> 3937500 | I30: =Portfolio!AE159 -> 32812500 | J30: =Portfolio!AF159 -> 26250000 | K30: =Portfolio!AG159 -> 0 | L30: =SUMIF(Model!D4:BS4,">"&TODAY(),Model!D121:BS121) -> 22125000 | M30: =SUMPRODUCT((Model!$D$4:$BS$4>$D$13)*(Model!D115:BS120)) -> 1100000 | N30: =SUM(M30,L30) -> 23225000 | O30: =P30-Q30 -> 0 | P30: =Portfolio!AH159 -> 0 | Q30: =SUMIF(Model!D4:BS4,">"&TODAY(),Model!D138:BS138) -> 0
C31: Total (Actual + Forecast) | D31: =SUM(D29:D30) -> 43750000 | E31: =SUM(E29:E30) -> 63000000 | F31: =SUM(E31,D31) -> 106750000 | G31: =SUM(G29:G30) -> 43750000 | H31: =SUM(H29:H30) -> 3937500 | I31: =SUM(I29:I30) -> 32812500 | J31: =SUM(J29:J30) -> 26250000 | K31: =SUM(K29:K30) -> 0 | L31: =SUM(L29:L30) -> 22125000 | M31: =SUM(M29:M30) -> 1100000 | N31: =SUM(M31,L31) -> 23225000 | O31: =SUM(O29:O30) -> 0 | P31: =SUM(P29:P30) -> 0 | Q31: =SUM(Q29:Q30) -> 0
C32: As % of Total Fund | D32: =D31/$D$11 -> 0.4375 | E32: =E31/$D$11 -> 0.63 | F32: =F31/$D$11 -> 1.0675 | G32: =G31/$D$11 -> 0.4375 | H32: =H31/$D$11 -> 0.039375 | I32: =I31/$D$11 -> 0.328125 | J32: =J31/$D$11 -> 0.2625 | K32: =K31/$D$11 -> 0 | ... Q32: =Q31/$D$11 -> 0
C33: As % of Total Invested | D33: =D31/$F$31 -> 0.40983607 | E33: =E31/$F$31 -> 0.59016393 | F33: =F31/$F$31 -> 1 | G33: =G31/$F$31 -> 0.40983607 | H33: =H31/$F$31 -> 0.036885246 | I33: =I31/$F$31 -> 0.30737705 | J33: =J31/$F$31 -> 0.24590164 | K33: =K31/$F$31 -> 0 | ... Q33: =Q31/$F$31 -> 0
D36: Cash Flow Model | K36: Investable Capital Model
D37: Max out date | E37: {=IFERROR(INDEX(Model!D4:BS4,MATCH(TRUE,Model!D140:BS140<0,0)),"No Max-out Date")} -> 45838 | K37: Max out date | L37: {=IFERROR(INDEX(Model!D4:BS4,MATCH(TRUE,Model!D142:BS142<0,0)),"No Max-out Day")} -> 45657
D38: Months remaining | E38: =IFERROR(IF($D$13>$D$10,DATEDIF($D$13,E37,"m"),DATEDIF($D$10,E37,"m")),"NA") -> 53 | K38: Months remaining | L38: =IFERROR(IF($D$13>$D$10,DATEDIF($D$13,L37,"m"),DATEDIF($D$10,L37,"m")),"NA") -> 47
D39: Qs remaining | E39: =IFERROR(IF($D$13>$D$10,FLOOR(((YEAR(E37)*12+MONTH(E37))-(YEAR($D$13)*12+MONTH($D$13)))/3,1),FLOOR(((YEAR(E37)*12+MONTH(E37))-(YEAR($D$10)*12+MONTH($D$10)))/3,1)),"NA") -> 17 | K39: Qs remaining | L39: =IFERROR(IF($D$13>$D$10,FLOOR(((YEAR(L37)*12+MONTH(L37))-(YEAR($D$13)*12+MONTH($D$13)))/3,1),FLOOR(((YEAR(L37)*12+MONTH(L37))-(YEAR($D$10)*12+MONTH($D$10)))/3,1)),"NA") -> 15
D40: Recycled at max-out | E40: {=IFERROR(INDEX(Model!$D$146:$AU$146,(MATCH(E37,Model!$D$4:$AU$4,0))),"No Max-out")} -> 0.88525 | K40: Recycled at max-out | L40: {=IFERROR(INDEX(Model!$D$146:$AU$146,(MATCH(L37,Model!$D$4:$AU$4,0))),"No Max-out")} -> 0.79525
D41: Target recycling hit | E41: =EDATE(INDEX(Model!$D$4:$AU$4,(MATCH($D$105,Model!$D$146:$AU$146))),3) -> 48304 | K41: Target recycling hit | L41: {=EDATE(INDEX(Model!$D$4:$AU$4,(MATCH($D$105,Model!$D$146:$AU$146))),3)} -> 48304
A65: x | B65: Return Scenarios
D69: Bear Case Scenario | J69: Base Case Scenario | Q69: Bull Case Scenario
D70: Max out date | E70: {=IFERROR(INDEX(Model!D4:BS4,MATCH(TRUE,Model!D173:BS173<0,0)),"No Max-out")} -> 45838 | J70: Max out date | K70: {=IFERROR(INDEX(Model!J4:BY4,MATCH(TRUE,Model!J200:BY200<0,0)),"No Max-out")} -> 45930 | Q70: Max out date | R70: {=IFERROR(INDEX(Model!Q4:CF4,MATCH(TRUE,Model!Q227:CF227<0,0)),"No Max-out")} -> No Max-out
D71: Months remaining | E71: =IFERROR(IF($D$13>$D$10,DATEDIF($D$13,E70,"m"),DATEDIF($D$10,E70,"m")),"NA") -> 53 | J71: Months remaining | K71: =IFERROR(IF($D$13>$D$10,DATEDIF($D$13,K70,"m"),DATEDIF($D$10,K70,"m")),"NA") -> 56 | Q71: Months remaining | R71: =IFERROR(IF($D$13>$D$10,DATEDIF($D$13,R70,"m"),DATEDIF($D$10,R70,"m")),"NA") -> NA
D72: Qs remaining | E72: =IFERROR(IF($D$13>$D$10,FLOOR(((YEAR(E70)*12+MONTH(E70))-(YEAR($D$13)*12+MONTH($D$13)))/3,1),FLOOR(((YEAR(E70)*12+MONTH(E70))-(YEAR($D$10)*12+MONTH($D$10)))/3,1)),"NA") -> 17 | J72: Qs remaining | K72: =IFERROR(IF($D$13>$D$10,FLOOR(((YEAR(K70)*12+MONTH(K70))-(YEAR($D$13)*12+MONTH($D$13)))/3,1),FLOOR(((YEAR(K70)*12+MONTH(K70))-(YEAR($D$10)*12+MONTH($D$10)))/3,1)),"NA") -> 18 | Q72: Qs remaining | R72: =IFERROR(IF($D$13>$D$10,FLOOR(((YEAR(R70)*12+MONTH(R70))-(YEAR($D$13)*12+MONTH($D$13)))/3,1),FLOOR(((YEAR(R70)*12+MONTH(R70))-(YEAR($D$10)*12+MONTH($D$10)))/3,1)),"NA") -> NA
D73: Recycled at max-out | E73: {=IFERROR(INDEX(Model!$D$160:$AU$160,(MATCH(E70,Model!$D$4:$AU$4,0))),"No Max-out")} -> 0.88525 | J73: Recycled at max-out | K73: {=IFERROR(INDEX(Model!$D$187:$AU$187,(MATCH(K70,Model!$D$4:$AU$4,0))),"No Max-out")} -> 0.938125 | Q73: Recycled at max-out | R73: {=IFERROR(INDEX(Model!$D$214:$AU$214,(MATCH(R70,Model!$D$4:$AU$4,0))),"No Max-out")} -> No Max-out
A98: x | B98: Investment Assumptions
C101: Avg Seed investment | D101: 1250000 | J101: Investment Size as % Seed | L101: Current Fund Avg. | N101: Avg Investment in a Company
C102: Number of initial investments | D102: 35 | J102: Ext | K102: 0.3 | L102: =Portfolio!G480 -> NA | N102: Seed | O102: =D101 -> 1250000
C103: Forecasted Returns (cash flow model) | D103: -1 | J103: A | K103: 1.25 | L103: =Portfolio!H480 -> NA | N103: Ext | O103: =K102*D101 -> 375000
C104: Recycling? (1=yes, 0=no) | D104: 1 | J104: B | K104: 1.5 | L104: =Portfolio!I480 -> NA | N104: Series A | O104: =K103*D101 -> 1562500
C105: Target Recycle Rate | D105: =F32 -> 1.0675 | J105: C | K105: 1.5 | L105: =Portfolio!J480 -> NA | N105: Series B | O105: =K104*D101 -> 1875000
N106: Total through B (excl Ext) | O106: =O105+O104+O102 -> 4687500
D107: Annualized Return Scenario (MODELED) | G107: Current year: | H107: =IFERROR(HLOOKUP((DATE(YEAR(D13),((INT((MONTH(D13)-1)/3)+1)*3)+1,1)-1),Model!D237:AU238,2,1),0) -> 0
C108: Years | D108: Bear | E108: Base | F108: Bull
C109: =YEAR(D10) -> 2021 | D109: {=IF($G124<$H$107,INDEX(Model!$D$177:$AU$177,(MATCH($G124,Model!$D$157:$AU$157,0)+3)),D124)} -> 0 | E109: {=IF($G124<$H$107,INDEX(Model!$D$205:$AU$205,(MATCH($G124,Model!$D$157:$AU$157,0)+3)),E124)} -> 0 | F109: {=IF($G124<$H$107,INDEX(Model!$D$205:$AU$205,(MATCH($G124,Model!$D$157:$AU$157,0)+3)),F124)} -> 0
C110: =C109+1 -> 2022 | D110: {=IF($G125<$H$107,INDEX(Model!$D$177:$AU$177,(MATCH($G125,Model!$D$157:$AU$157,0)+3)),D125)} -> 0 | E110: {=IF($G125<$H$107,INDEX(Model!$D$205:$AU$205,(MATCH($G125,Model!$D$157:$AU$157,0)+3)),E125)} -> 0 | F110: {=IF($G125<$H$107,INDEX(Model!$D$205:$AU$205,(MATCH($G125,Model!$D$157:$AU$157,0)+3)),F125)} -> 0 | J110: Conversion Rate from Seed | L110: Current Fund Conv | N110: Implied Deal #
C111: =C110+1 -> 2023 | D111: {=IF($G126<$H$107,INDEX(Model!$D$177:$AU$177,(MATCH($G126,Model!$D$157:$AU$157,0)+3)),D126)} -> 0 | E111: {=IF($G126<$H$107,INDEX(Model!$D$205:$AU$205,(MATCH($G126,Model!$D$157:$AU$157,0)+3)),E126)} -> 0 | F111: {=IF($G126<$H$107,INDEX(Model!$D$205:$AU$205,(MATCH($G126,Model!$D$157:$AU$157,0)+3)),F126)} -> 0.01 | J111: Ext | K111: 0.3 | L111: =E21 -> NA | N111: Ext | O111: =ROUND($G$9*K111,0) -> 11
C112: =C111+1 -> 2024 | D112: {=IF($G127<$H$107,INDEX(Model!$D$177:$AU$177,(MATCH($G127,Model!$D$157:$AU$157,0)+3)),D127)} -> 0 | E112: {=IF($G127<$H$107,INDEX(Model!$D$205:$AU$205,(MATCH($G127,Model!$D$157:$AU$157,0)+3)),E127)} -> 0.02 | F112: {=IF($G127<$H$107,INDEX(Model!$D$205:$AU$205,(MATCH($G127,Model!$D$157:$AU$157,0)+3)),F127)} -> 0.07 | J112: A | K112: 0.6 | L112: =F21 -> NA | N112: A | O112: =ROUND($G$9*K112,0) -> 21
C113: =C112+1 -> 2025 | D113: 0.025 | E113: {=IF($G128<$H$107,INDEX(Model!$D$205:$AU$205,(MATCH($G128,Model!$D$157:$AU$157,0)+3)),E128)} -> 0.06 | F113: {=IF($G128<$H$107,INDEX(Model!$D$205:$AU$205,(MATCH($G128,Model!$D$157:$AU$157,0)+3)),F128)} -> 0.15 | J113: B | K113: 0.4 | L113: =G21 -> NA | N113: B | O113: =ROUND($G$9*K113,0) -> 14
C114: =C113+1 -> 2026 | D114: 0.025 | E114: {=IF($G129<$H$107,INDEX(Model!$D$205:$AU$205,(MATCH($G129,Model!$D$157:$AU$157,0)+3)),E129)} -> 0.08 | F114: {=IF($G129<$H$107,INDEX(Model!$D$205:$AU$205,(MATCH($G129,Model!$D$157:$AU$157,0)+3)),F129)} -> 0.2 | J114: C | K114: 0 | L114: =H21 -> NA | N114: C | O114: =ROUND($G$9*K114,0) -> 0
C115: =C114+1 -> 2027 | D115: 0.05 | E115: {=IF($G130<$H$107,INDEX(Model!$D$205:$AU$205,(MATCH($G130,Model!$D$157:$AU$157,0)+3)),E130)} -> 0.1 | F115: {=IF($G130<$H$107,INDEX(Model!$D$205:$AU$205,(MATCH($G130,Model!$D$157:$AU$157,0)+3)),F130)} -> 0.25
C116: =C115+1 -> 2028 | D116: 0.075 | E116: {=IF($G131<$H$107,INDEX(Model!$D$205:$AU$205,(MATCH($G131,Model!$D$157:$AU$157,0)+3)),E131)} -> 0.25 | F116: {=IF($G131<$H$107,INDEX(Model!$D$205:$AU$205,(MATCH($G131,Model!$D$157:$AU$157,0)+3)),F131)} -> 0.35
C117: =C116+1 -> 2029 | D117: 0.15 | E117: {=IF($G132<$H$107,INDEX(Model!$D$205:$AU$205,(MATCH($G132,Model!$D$157:$AU$157,0)+3)),E132)} -> 0.5 | F117: {=IF($G132<$H$107,INDEX(Model!$D$205:$AU$205,(MATCH($G132,Model!$D$157:$AU$157,0)+3)),F132)} -> 1 | J117: Avg Time Between Deals (weeks) | L117: Time in Months | M117: Current Avg (weeks)
C118: =C117+1 -> 2030 | D118: 0.25 | E118: {=IF($G133<$H$107,INDEX(Model!$D$205:$AU$205,(MATCH($G133,Model!$D$157:$AU$157,0)+3)),E133)} -> 1 | F118: {=IF($G133<$H$107,INDEX(Model!$D$205:$AU$205,(MATCH($G133,Model!$D$157:$AU$157,0)+3)),F133)} -> 1.5 | J118: Between Seed invts. | K118: 5 | L118: =K118/4 -> 1.25 | M118: =Portfolio!R324 -> NA
C119: =C118+1 -> 2031 | D119: {=IF($G134<$H$107,INDEX(Model!$D$177:$AU$177,(MATCH($G134,Model!$D$157:$AU$157,0)+3)),D134)} -> 0.25 | E119: {=IF($G134<$H$107,INDEX(Model!$D$205:$AU$205,(MATCH($G134,Model!$D$157:$AU$157,0)+3)),E134)} -> 0.5 | F119: {=IF($G134<$H$107,INDEX(Model!$D$205:$AU$205,(MATCH($G134,Model!$D$157:$AU$157,0)+3)),F134)} -> 1 | J119: S and Ext | K119: 65 | L119: =K119/4 -> 16.25 | M119: =Portfolio!S324 -> NA
C120: =C119+1 -> 2032 | D120: 0.2 | E120: =E119 -> 0.5 | F120: =F119 -> 1 | J120: S and A | K120: 75 | L120: =K120/4 -> 18.75 | M120: =Portfolio!T324 -> NA
J121: A and B | K121: 76 | L121: =K121/4 -> 19 | M121: =Portfolio!U324 -> NA
D122: Annualized Return Scenario Assumptions | G122: Year Brackets | J122: B and C | K122: 64 | L122: =K122/4 -> 16 | M122: =Portfolio!V324 -> NA
C123: Years | D123: Bear | E123: Base | F123: Bull | G123: Lower (Y) | H123: Upper (Y) | J123: Return range (from last investment) | K123: 0 | L123: =K123/4 -> 0 | M123: =Portfolio!W324 -> NA
C124: ="Y"&G124&"-Y"&H124 -> Y0-Y0 | D124: 0 | E124: 0 | F124: 0 | G124: 0 | H124: 0
C125: ="Y"&G125&"-Y"&H125 -> Y1-Y1 | D125: 0 | E125: 0 | F125: 0 | G125: =H124+1 -> 1 | H125: 1
C126: ="Y"&G126&"-Y"&H126 -> Y2-Y2 | D126: 0 | E126: 0 | F126: 0.01 | G126: =H125+1 -> 2 | H126: 2
C127: ="Y"&G127&"-Y"&H127 -> Y3-Y3 | D127: 0 | E127: 0.02 | F127: 0.07 | G127: =H126+1 -> 3 | H127: 3
C128: ="Y"&G128&"-Y"&H128 -> Y4-Y4 | D128: 0 | E128: 0.06 | F128: 0.15 | G128: =H127+1 -> 4 | H128: 4
C129: ="Y"&G129&"-Y"&H129 -> Y5-Y5 | D129: 0 | E129: 0.08 | F129: 0.2 | G129: =H128+1 -> 5 | H129: 5
C130: ="Y"&G130&"-Y"&H130 -> Y6-Y6 | D130: 0 | E130: 0.1 | F130: 0.25 | G130: =H129+1 -> 6 | H130: 6
C131: ="Y"&G131&"-Y"&H131 -> Y7-Y7 | D131: 0.05 | E131: 0.25 | F131: 0.35 | G131: =H130+1 -> 7 | H131: 7
C132: ="Y"&G132&"-Y"&H132 -> Y8-Y8 | D132: 0.12 | E132: 0.5 | F132: 1 | G132: =H131+1 -> 8 | H132: 8
C133: ="Y"&G133&"-Y"&H133 -> Y9-Y9 | D133: 0.2 | E133: 1 | F133: 1.5 | G133: =H132+1 -> 9 | H133: 9
C134: ="Y"&G134&"-Y"&H134 -> Y10-Y10 | D134: 0.25 | E134: 0.5 | F134: 1 | G134: =H133+1 -> 10 | H134: 10
C135: ="Y"&G135&"-Y"&H135 -> Y11-Y> | D135: =D134 -> 0.25 | E135: =E134 -> 0.5 | F135: =F134 -> 1 | G135: =H134+1 -> 11 | H135: >
A138: x | B138: Fee and Expense Assumptions
C141: Expense | D141: Cost | E141: Pacing
C142: Quarterly management fee | D142: 0.00625 | E142: Quarterly
C143: Quarterly decrease in mgmt fee | D143: 0.000125 | E143: After intl invt pd.
C144: Lowest annual fee | D144: 0.015
C145: Forecasted LP Distributions | D145: 0 | E145: Quarterly
C146: Forecasted GP Distributions | D146: 0 | E146: Quarterly
C147: Expense line item #1 | D147: 5000 | E147: Quarterly
C148: Expense line item #2 | D148: 5000 | E148: Quarterly
C149: Expense line item #3 | D149: 5000 | E149: Quarterly
C150: Expense line item #4 | D150: 5000 | E150: Quarterly
C151: Expense line item #5 | D151: 5000 | E151: Quarterly

Sheet Portfolio
B1: =Model!B1 -> Fund Name
B2: Portfolio
B3: Today | D3: ='Summary and Assumptions'!D13 -> 43958 | F3: # of Invst. | H3: ='Summary and Assumptions'!D102 -> 35
B4: Start Date | D4: ='Summary and Assumptions'!D10 -> 44197 | F4: Days to add if overdue | H4: 90
O5: Executed Deals | Z5: Forecast Deals
B6: F/E? | C6: Companies | E6: Info | F6: Seed | G6: Ext. | H6: A | I6: B | J6: C | K6: Stage | L6: Returns | O6: =C6 -> Companies | Q6: Intl Inv Date | R6: =F6 -> Seed | S6: =G6 -> Ext. | T6: =H6 -> A | U6: =I6 -> B | V6: =J6 -> C | W6: Returns | X6: Stage | Z6: =O6 -> Companies | AB6: =Q6 -> Intl Inv Date | AC6: =R6 -> Seed | AD6: =S6 -> Ext. | AE6: =T6 -> A | AF6: =U6 -> B | AG6: =V6 -> C | AH6: =W6 -> Returns
B7: F | C7: =G3+1 -> 1 | D7: =IF(C7<=$H$3,"Company"&" "&C7,"") -> Company 1 | E7: FQ End Date | F7: =IFERROR(IF(F8>0,(DATE(YEAR(F8),((INT((MONTH(F8)-1)/3)+1)*3)+1,1)-1),"-"),"NA") -> 44286 | G7: =IFERROR(IF(G8>0,(DATE(YEAR(G8),((INT((MONTH(G8)-1)/3)+1)*3)+1,1)-1),"-"),"NA") -> 44742 | H7: =IFERROR(IF(H8>0,(DATE(YEAR(H8),((INT((MONTH(H8)-1)/3)+1)*3)+1,1)-1),"-"),"NA") -> 44834 | I7: =IFERROR(IF(I8>0,(DATE(YEAR(I8),((INT((MONTH(I8)-1)/3)+1)*3)+1,1)-1),"-"),"NA") -> 45291 | J7: =IFERROR(IF(J8>0,(DATE(YEAR(J8),((INT((MONTH(J8)-1)/3)+1)*3)+1,1)-1),"-"),"NA") -> 45747 | L7: =IFERROR(IF(L8>0,(DATE(YEAR(L8),((INT((MONTH(L8)-1)/3)+1)*3)+1,1)-1),"-"),"") -> 45747 | O7: =IF(F8<=TODAY(),C7,"0") -> 0 | P7: =IF(F8<=TODAY(),D7,"0") -> 0 | Q7: =IF(F8<=TODAY(),F8,"0") -> 0 | R7: =IF(F8<=TODAY(),F9,0) -> 0 | S7: =IF(G8<=TODAY(),G9,0) -> 0 | T7: =IF(H8<=TODAY(),H9,0) -> 0 | U7: =IF(I8<=TODAY(),I9,0) -> 0 | V7: =IF(J8<=TODAY(),J9,0) -> 0 | W7: =IF(L8<=TODAY(),L9,0) -> 0 | X7: =IF(K8<=TODAY(),K9,"-") -> 0 | Z7: =C7 -> 1 | AA7: =D7 -> Company 1 | AB7: =F8 -> 44232 | AC7: =IF(F8>TODAY(),F9,"0") -> 1250000 | AD7: =IF(G8>TODAY(),G9,"0") -> 112500 | AE7: =IF(H8>TODAY(),H9,"0") -> 937500 | AF7: =IF(I8>TODAY(),I9,"0") -> 750000 | AG7: =IF(J8>TODAY(),J9,"0") -> 0 | AH7: =IF(L8>TODAY(),L9,"0") -> 0
E8: Date | F8: =IF(C7<=$H$3,IF((D4+('Summary and Assumptions'!$K$118*7))>$D$3,(D4+('Summary and Assumptions'!$K$118*7)),($D$3+$H$4)),"") -> 44232 | G8: =IF($C7<=$H$3,IF((F8+('Summary and Assumptions'!$K$119*7))>$D$3,(F8+('Summary and Assumptions'!$K$119*7)),($D$3+$H$4)),"") -> 44687 | H8: =IF($C7<=$H$3,IF((F8+('Summary and Assumptions'!$K$120*7))>$D$3,(F8+('Summary and Assumptions'!$K$120*7)),($D$3+$H$4)),"") -> 44757 | I8: =IF($C7<=$H$3,IF((H8+('Summary and Assumptions'!$K$121*7))>$D$3,(H8+('Summary and Assumptions'!$K$121*7)),($D$3+$H$4)),"") -> 45289 | J8: =IF($C7<=$H$3,IF((I8+('Summary and Assumptions'!$K$122*7))>$D$3,(I8+('Summary and Assumptions'!$K$122*7)),($D$3+$H$4)),"") -> 45737 | L8: =IF($C7<=$H$3,IF((J8+('Summary and Assumptions'!$K$123*7))>$D$3,(J8+('Summary and Assumptions'!$K$123*7)),($D$3+$H$4)),"") -> 45737
E9: Amount | F9: =IF(C7<=$H$3,'Summary and Assumptions'!$D$101,"") -> 1250000 | G9: =IF(C7<=$H$3,F9*'Summary and Assumptions'!$K$111*'Summary and Assumptions'!$K$102,"") -> 112500 | H9: =IF(C7<=$H$3,$F9*'Summary and Assumptions'!$K$112*'Summary and Assumptions'!$K$103,"") -> 937500 | I9: =IF(C7<=$H$3,$F9*'Summary and Assumptions'!$K$113*'Summary and Assumptions'!$K$104,"") -> 750000 | J9: =IF(C7<=$H$3,$F9*'Summary and Assumptions'!$K$114*'Summary and Assumptions'!$K$105,"") -> 0 | K9: =IF(AND(J8<=$D$3,J9>0),$J$6,IF(AND(I8<=$D$3,I9>0),$I$6,IF(AND(H8<=$D$3,H9>0),$H$6,IF(AND(G8<=$D$3,G9>0),$G$6,IF(AND(F8<=$D$3,F9>0),$F$6,"0"))))) -> 0 | L9: =IF(C7<=$H$3,SUM($F9:$I9)*(1+'Summary and Assumptions'!$D$103),"") -> 0
B10: F | C10: =C7+1 -> 2 | D10: =IF(C10<=$H$3,"Company"&" "&C10,"") -> Company 2 | E10: FQ End Date | F10: =IFERROR(IF(F11>0,(DATE(YEAR(F11),((INT((MONTH(F11)-1)/3)+1)*3)+1,1)-1),"-"),"NA") -> 44286 | G10: =IFERROR(IF(G11>0,(DATE(YEAR(G11),((INT((MONTH(G11)-1)/3)+1)*3)+1,1)-1),"-"),"NA") -> 44742 | H10: =IFERROR(IF(H11>0,(DATE(YEAR(H11),((INT((MONTH(H11)-1)/3)+1)*3)+1,1)-1),"-"),"NA") -> 44834 | I10: =IFERROR(IF(I11>0,(DATE(YEAR(I11),((INT((MONTH(I11)-1)/3)+1)*3)+1,1)-1),"-"),"NA") -> 45382 | J10: =IFERROR(IF(J11>0,(DATE(YEAR(J11),((INT((MONTH(J11)-1)/3)+1)*3)+1,1)-1),"-"),"NA") -> 45838 | L10: =IFERROR(IF(L11>0,(DATE(YEAR(L11),((INT((MONTH(L11)-1)/3)+1)*3)+1,1)-1),"-"),"") -> 45838 | O10: =IF(F11<=TODAY(),C10,"0") -> 0 | P10: =IF(F11<=TODAY(),D10,"0") -> 0 | Q10: =IF(F11<=TODAY(),F11,"0") -> 0 | R10: =IF(F11<=TODAY(),F12,0) -> 0 | S10: =IF(G11<=TODAY(),G12,0) -> 0 | T10: =IF(H11<=TODAY(),H12,0) -> 0 | U10: =IF(I11<=TODAY(),I12,0) -> 0 | V10: =IF(J11<=TODAY(),J12,0) -> 0 | W10: =IF(L11<=TODAY(),L12,0) -> 0 | X10: =IF(K11<=TODAY(),K12,"-") -> 0 | Z10: =C10 -> 2 | AA10: =D10 -> Company 2 | AB10: =F11 -> 44267 | AC10: =IF(F11>TODAY(),F12,"0") -> 1250000 | AD10: =IF(G11>TODAY(),G12,"0") -> 112500 | AE10: =IF(H11>TODAY(),H12,"0") -> 937500 | AF10: =IF(I11>TODAY(),I12,"0") -> 750000 | AG10: =IF(J11>TODAY(),J12,"0") -> 0 | AH10: =IF(L11>TODAY(),L12,"0") -> 0
E11: Date | F11: =IF(C10<=$H$3,IF((F8+('Summary and Assumptions'!$K$118*7))>$D$3,(F8+('Summary and Assumptions'!$K$118*7)),($D$3+$H$4)),"") -> 44267 | G11: =IF($C10<=$H$3,IF((F11+('Summary and Assumptions'!$K$119*7))>$D$3,(F11+('Summary and Assumptions'!$K$119*7)),($D$3+$H$4)),"") -> 44722 | H11: =IF($C10<=$H$3,IF((F11+('Summary and Assumptions'!$K$120*7))>$D$3,(F11+('Summary and Assumptions'!$K$120*7)),($D$3+$H$4)),"") -> 44792 | I11: =IF($C10<=$H$3,IF((H11+('Summary and Assumptions'!$K$121*7))>$D$3,(H11+('Summary and Assumptions'!$K$121*7)),($D$3+$H$4)),"") -> 45324 | J11: =IF($C10<=$H$3,IF((I11+('Summary and Assumptions'!$K$122*7))>$D$3,(I11+('Summary and Assumptions'!$K$122*7)),($D$3+$H$4)),"") -> 45772 | L11: =IF($C10<=$H$3,IF((J11+('Summary and Assumptions'!$K$123*7))>$D$3,(J11+('Summary and Assumptions'!$K$123*7)),($D$3+$H$4)),"") -> 45772
E12: Amount | F12: =IF(C10<=$H$3,'Summary and Assumptions'!$D$101,"") -> 1250000 | G12: =IF(C10<=$H$3,F12*'Summary and Assumptions'!$K$111*'Summary and Assumptions'!$K$102,"") -> 112500 | H12: =IF(C10<=$H$3,$F12*'Summary and Assumptions'!$K$112*'Summary and Assumptions'!$K$103,"") -> 937500 | I12: =IF(C10<=$H$3,$F12*'Summary and Assumptions'!$K$113*'Summary and Assumptions'!$K$104,"") -> 750000 | J12: =IF(C10<=$H$3,$F12*'Summary and Assumptions'!$K$114*'Summary and Assumptions'!$K$105,"") -> 0 | K12: =IF(AND(J11<=$D$3,J12>0),$J$6,IF(AND(I11<=$D$3,I12>0),$I$6,IF(AND(H11<=$D$3,H12>0),$H$6,IF(AND(G11<=$D$3,G12>0),$G$6,IF(AND(F11<=$D$3,F12>0),$F$6,"0"))))) -> 0 | L12: =IF(C10<=$H$3,SUM($F12:$I12)*(1+'Summary and Assumptions'!$D$103),"") -> 0
B13: F | C13: =C10+1 -> 3 | D13: =IF(C13<=$H$3,"Company"&" "&C13,"") -> Company 3 | E13: FQ End Date | F13: =IFERROR(IF(F14>0,(DATE(YEAR(F14),((INT((MONTH(F14)-1)/3)+1)*3)+1,1)-1),"-"),"NA") -> 44377 | G13: =IFERROR(IF(G14>0,(DATE(YEAR(G14),((INT((MONTH(G14)-1)/3)+1)*3)+1,1)-1),"-"),"NA") -> 44834 | H13: =IFERROR(IF(H14>0,(DATE(YEAR(H14),((INT((MONTH(H14)-1)/3)+1)*3)+1,1)-1),"-"),"NA") -> 44834 | I13: =IFERROR(IF(I14>0,(DATE(YEAR(I14),((INT((MONTH(I14)-1)/3)+1)*3)+1,1)-1),"-"),"NA") -> 45382 | J13: =IFERROR(IF(J14>0,(DATE(YEAR(J14),((INT((MONTH(J14)-1)/3)+1)*3)+1,1)-1),"-"),"NA") -> 45838 | L13: =IFERROR(IF(L14>0,(DATE(YEAR(L14),((INT((MONTH(L14)-1)/3)+1)*3)+1,1)-1),"-"),"") -> 45838 | O13: =IF(F14<=TODAY(),C13,"0") -> 0 | P13: =IF(F14<=TODAY(),D13,"0") -> 0 | Q13: =IF(F14<=TODAY(),F14,"0") -> 0 | R13: =IF(F14<=TODAY(),F15,0) -> 0 | S13: =IF(G14<=TODAY(),G15,0) -> 0 | T13: =IF(H14<=TODAY(),H15,0) -> 0 | U13: =IF(I14<=TODAY(),I15,0) -> 0 | V13: =IF(J14<=TODAY(),J15,0) -> 0 | W13: =IF(L14<=TODAY(),L15,0) -> 0 | X13: =IF(K14<=TODAY(),K15,"-") -> 0 | Z13: =C13 -> 3 | AA13: =D13 -> Company 3 | AB13: =F14 -> 44302 | AC13: =IF(F14>TODAY(),F15,"0") -> 1250000 | AD13: =IF(G14>TODAY(),G15,"0") -> 112500 | AE13: =IF(H14>TODAY(),H15,"0") -> 937500 | AF13: =IF(I14>TODAY(),I15,"0") -> 750000 | AG13: =IF(J14>TODAY(),J15,"0") -> 0 | AH13: =IF(L14>TODAY(),L15,"0") -> 0
E14: Date | F14: =IF(C13<=$H$3,IF((F11+('Summary and Assumptions'!$K$118*7))>$D$3,(F11+('Summary and Assumptions'!$K$118*7)),($D$3+$H$4)),"") -> 44302 | G14: =IF($C13<=$H$3,IF((F14+('Summary and Assumptions'!$K$119*7))>$D$3,(F14+('Summary and Assumptions'!$K$119*7)),($D$3+$H$4)),"") -> 44757 | H14: =IF($C13<=$H$3,IF((F14+('Summary and Assumptions'!$K$120*7))>$D$3,(F14+('Summary and Assumptions'!$K$120*7)),($D$3+$H$4)),"") -> 44827 | I14: =IF($C13<=$H$3,IF((H14+('Summary and Assumptions'!$K$121*7))>$D$3,(H14+('Summary and Assumptions'!$K$121*7)),($D$3+$H$4)),"") -> 45359 | J14: =IF($C13<=$H$3,IF((I14+('Summary and Assumptions'!$K$122*7))>$D$3,(I14+('Summary and Assumptions'!$K$122*7)),($D$3+$H$4)),"") -> 45807 | L14: =IF($C13<=$H$3,IF((J14+('Summary and Assumptions'!$K$123*7))>$D$3,(J14+('Summary and Assumptions'!$K$123*7)),($D$3+$H$4)),"") -> 45807
E15: Amount | F15: =IF(C13<=$H$3,'Summary and Assumptions'!$D$101,"") -> 1250000 | G15: =IF(C13<=$H$3,F15*'Summary and Assumptions'!$K$111*'Summary and Assumptions'!$K$102,"") -> 112500 | H15: =IF(C13<=$H$3,$F15*'Summary and Assumptions'!$K$112*'Summary and Assumptions'!$K$103,"") -> 937500 | I15: =IF(C13<=$H$3,$F15*'Summary and Assumptions'!$K$113*'Summary and Assumptions'!$K$104,"") -> 750000 | J15: =IF(C13<=$H$3,$F15*'Summary and Assumptions'!$K$114*'Summary and Assumptions'!$K$105,"") -> 0 | K15: =IF(AND(J14<=$D$3,J15>0),$J$6,IF(AND(I14<=$D$3,I15>0),$I$6,IF(AND(H14<=$D$3,H15>0),$H$6,IF(AND(G14<=$D$3,G15>0),$G$6,IF(AND(F14<=$D$3,F15>0),$F$6,"0"))))) -> 0 | L15: =IF(C13<=$H$3,SUM($F15:$I15)*(1+'Summary and Assumptions'!$D$103),"") -> 0
B16: F | C16: =C13+1 -> 4 | D16: =IF(C16<=$H$3,"Company"&" "&C16,"") -> Company 4 | E16: FQ End Date | F16: =IFERROR(IF(F17>0,(DATE(YEAR(F17),((INT((MONTH(F17)-1)/3)+1)*3)+1,1)-1),"-"),"NA") -> 44377 | G16: =IFERROR(IF(G17>0,(DATE(YEAR(G17),((INT((MONTH(G17)-1)/3)+1)*3)+1,1)-1),"-"),"NA") -> 44834 | H16: =IFERROR(IF(H17>0,(DATE(YEAR(H17),((INT((MONTH(H17)-1)/3)+1)*3)+1,1)-1),"-"),"NA") -> 44926 | I16: =IFERROR(IF(I17>0,(DATE(YEAR(I17),((INT((MONTH(I17)-1)/3)+1)*3)+1,1)-1),"-"),"NA") -> 45473 | J16: =IFERROR(IF(J17>0,(DATE(YEAR(J17),((INT((MONTH(J17)-1)/3)+1)*3)+1,1)-1),"-"),"NA") -> 45930 | L16: =IFERROR(IF(L17>0,(DATE(YEAR(L17),((INT((MONTH(L17)-1)/3)+1)*3)+1,1)-1),"-"),"") -> 45930 | O16: =IF(F17<=TODAY(),C16,"0") -> 0 | P16: =IF(F17<=TODAY(),D16,"0") -> 0 | Q16: =IF(F17<=TODAY(),F17,"0") -> 0 | R16: =IF(F17<=TODAY(),F18,0) -> 0 | S16: =IF(G17<=TODAY(),G18,0) -> 0 | T16: =IF(H17<=TODAY(),H18,0) -> 0 | U16: =IF(I17<=TODAY(),I18,0) -> 0 | V16: =IF(J17<=TODAY(),J18,0) -> 0 | W16: =IF(L17<=TODAY(),L18,0) -> 0 | X16: =IF(K17<=TODAY(),K18,"-") -> 0 | Z16: =C16 -> 4 | AA16: =D16 -> Company 4 | AB16: =F17 -> 44337 | AC16: =IF(F17>TODAY(),F18,"0") -> 1250000 | AD16: =IF(G17>TODAY(),G18,"0") -> 112500 | AE16: =IF(H17>TODAY(),H18,"0") -> 937500 | AF16: =IF(I17>TODAY(),I18,"0") -> 750000 | AG16: =IF(J17>TODAY(),J18,"0") -> 0 | AH16: =IF(L17>TODAY(),L18,"0") -> 0
E17: Date | F17: =IF(C16<=$H$3,IF((F14+('Summary and Assumptions'!$K$118*7))>$D$3,(F14+('Summary and Assumptions'!$K$118*7)),($D$3+$H$4)),"") -> 44337 | G17: =IF($C16<=$H$3,IF((F17+('Summary and Assumptions'!$K$119*7))>$D$3,(F17+('Summary and Assumptions'!$K$119*7)),($D$3+$H$4)),"") -> 44792 | H17: =IF($C16<=$H$3,IF((F17+('Summary and Assumptions'!$K$120*7))>$D$3,(F17+('Summary and Assumptions'!$K$120*7)),($D$3+$H$4)),"") -> 44862 | I17: =IF($C16<=$H$3,IF((H17+('Summary and Assumptions'!$K$121*7))>$D$3,(H17+('Summary and Assumptions'!$K$121*7)),($D$3+$H$4)),"") -> 45394 | J17: =IF($C16<=$H$3,IF((I17+('Summary and Assumptions'!$K$122*7))>$D$3,(I17+('Summary and Assumptions'!$K$122*7)),($D$3+$H$4)),"") -> 45842 | L17: =IF($C16<=$H$3,IF((J17+('Summary and Assumptions'!$K$123*7))>$D$3,(J17+('Summary and Assumptions'!$K$123*7)),($D$3+$H$4)),"") -> 45842
E18: Amount | F18: =IF(C16<=$H$3,'Summary and Assumptions'!$D$101,"") -> 1250000 | G18: =IF(C16<=$H$3,F18*'Summary and Assumptions'!$K$111*'Summary and Assumptions'!$K$102,"") -> 112500 | H18: =IF(C16<=$H$3,$F18*'Summary and Assumptions'!$K$112*'Summary and Assumptions'!$K$103,"") -> 937500 | I18: =IF(C16<=$H$3,$F18*'Summary and Assumptions'!$K$113*'Summary and Assumptions'!$K$104,"") -> 750000 | J18: =IF(C16<=$H$3,$F18*'Summary and Assumptions'!$K$114*'Summary and Assumptions'!$K$105,"") -> 0 | K18: =IF(AND(J17<=$D$3,J18>0),$J$6,IF(AND(I17<=$D$3,I18>0),$I$6,IF(AND(H17<=$D$3,H18>0),$H$6,IF(AND(G17<=$D$3,G18>0),$G$6,IF(AND(F17<=$D$3,F18>0),$F$6,"0"))))) -> 0 | L18: =IF(C16<=$H$3,SUM($F18:$I18)*(1+'Summary and Assumptions'!$D$103),"") -> 0
B19: F | C19: =C16+1 -> 5 | D19: =IF(C19<=$H$3,"Company"&" "&C19,"") -> Company 5 | E19: FQ End Date | F19: =IFERROR(IF(F20>0,(DATE(YEAR(F20),((INT((MONTH(F20)-1)/3)+1)*3)+1,1)-1),"-"),"NA") -> 44377 | G19: =IFERROR(IF(G20>0,(DATE(YEAR(G20),((INT((MONTH(G20)-1)/3)+1)*3)+1,1)-1),"-"),"NA") -> 44834 | H19: =IFERROR(IF(H20>0,(DATE(YEAR(H20),((INT((MONTH(H20)-1)/3)+1)*3)+1,1)-1),"-"),"NA") -> 44926 | I19: =IFERROR(IF(I20>0,(DATE(YEAR(I20),((INT((MONTH(I20)-1)/3)+1)*3)+1,1)-1),"-"),"NA") -> 45473 | J19: =IFERROR(IF(J20>0,(DATE(YEAR(J20),((INT((MONTH(J20)-1)/3)+1)*3)+1,1)-1),"-"),"NA") -> 45930 | L19: =IFERROR(IF(L20>0,(DATE(YEAR(L20),((INT((MONTH(L20)-1)/3)+1)*3)+1,1)-1),"-"),"") -> 45930 | O19: =IF(F20<=TODAY(),C19,"0") -> 0 | P19: =IF(F20<=TODAY(),D19,"0") -> 0 | Q19: =IF(F20<=TODAY(),F20,"0") -> 0 | R19: =IF(F20<=TODAY(),F21,0) -> 0 | S19: =IF(G20<=TODAY(),G21,0) -> 0 | T19: =IF(H20<=TODAY(),H21,0) -> 0 | U19: =IF(I20<=TODAY(),I21,0) -> 0 | V19: =IF(J20<=TODAY(),J21,0) -> 0 | W19: =IF(L20<=TODAY(),L21,0) -> 0 | X19: =IF(K20<=TODAY(),K21,"-") -> 0 | Z19: =C19 -> 5 | AA19: =D19 -> Company 5 | AB19: =F20 -> 44372 | AC19: =IF(F20>TODAY(),F21,"0") -> 1250000 | AD19: =IF(G20>TODAY(),G21,"0") -> 112500 | AE19: =IF(H20>TODAY(),H21,"0") -> 937500 | AF19: =IF(I20>TODAY(),I21,"0") -> 750000 | AG19: =IF(J20>TODAY(),J21,"0") -> 0 | AH19: =IF(L20>TODAY(),L21,"0") -> 0
E20: Date | F20: =IF(C19<=$H$3,IF((F17+('Summary and Assumptions'!$K$118*7))>$D$3,(F17+('Summary and Assumptions'!$K$118*7)),($D$3+$H$4)),"") -> 44372 | G20: =IF($C19<=$H$3,IF((F20+('Summary and Assumptions'!$K$119*7))>$D$3,(F20+('Summary and Assumptions'!$K$119*7)),($D$3+$H$4)),"") -> 44827 | H20: =IF($C19<=$H$3,IF((F20+('Summary and Assumptions'!$K$120*7))>$D$3,(F20+('Summary and Assumptions'!$K$120*7)),($D$3+$H$4)),"") -> 44897 | I20: =IF($C19<=$H$3,IF((H20+('Summary and Assumptions'!$K$121*7))>$D$3,(H20+('Summary and Assumptions'!$K$121*7)),($D$3+$H$4)),"") -> 45429 | J20: =IF($C19<=$H$3,IF((I20+('Summary and Assumptions'!$K$122*7))>$D$3,(I20+('Summary and Assumptions'!$K$122*7)),($D$3+$H$4)),"") -> 45877 | L20: =IF($C19<=$H$3,IF((J20+('Summary and Assumptions'!$K$123*7))>$D$3,(J20+('Summary and Assumptions'!$K$123*7)),($D$3+$H$4)),"") -> 45877
E21: Amount | F21: =IF(C19<=$H$3,'Summary and Assumptions'!$D$101,"") -> 1250000 | G21: =IF(C19<=$H$3,F21*'Summary and Assumptions'!$K$111*'Summary and Assumptions'!$K$102,"") -> 112500 | H21: =IF(C19<=$H$3,$F21*'Summary and Assumptions'!$K$112*'Summary and Assumptions'!$K$103,"") -> 937500 | I21: =IF(C19<=$H$3,$F21*'Summary and Assumptions'!$K$113*'Summary and Assumptions'!$K$104,"") -> 750000 | J21: =IF(C19<=$H$3,$F21*'Summary and Assumptions'!$K$114*'Summary and Assumptions'!$K$105,"") -> 0 | K21: =IF(AND(J20<=$D$3,J21>0),$J$6,IF(AND(I20<=$D$3,I21>0),$I$6,IF(AND(H20<=$D$3,H21>0),$H$6,IF(AND(G20<=$D$3,G21>0),$G$6,IF(AND(F20<=$D$3,F21>0),$F$6,"0"))))) -> 0 | L21: =IF(C19<=$H$3,SUM($F21:$I21)*(1+'Summary and Assumptions'!$D$103),"") -> 0
B22: F | C22: =C19+1 -> 6 | D22: =IF(C22<=$H$3,"Company"&" "&C22,"") -> Company 6 | E22: FQ End Date | F22: =IFERROR(IF(F23>0,(DATE(YEAR(F23),((INT((MONTH(F23)-1)/3)+1)*3)+1,1)-1),"-"),"NA") -> 44469 | G22: =IFERROR(IF(G23>0,(DATE(YEAR(G23),((INT((MONTH(G23)-1)/3)+1)*3)+1,1)-1),"-"),"NA") -> 44926 | H22: =IFERROR(IF(H23>0,(DATE(YEAR(H23),((INT((MONTH(H23)-1)/3)+1)*3)+1,1)-1),"-"),"NA") -> 45016 | I22: =IFERROR(IF(I23>0,(DATE(YEAR(I23),((INT((MONTH(I23)-1)/3)+1)*3)+1,1)-1),"-"),"NA") -> 45473 | J22: =IFERROR(IF(J23>0,(DATE(YEAR(J23),((INT((MONTH(J23)-1)/3)+1)*3)+1,1)-1),"-"),"NA") -> 45930 | L22: =IFERROR(IF(L23>0,(DATE(YEAR(L23),((INT((MONTH(L23)-1)/3)+1)*3)+1,1)-1),"-"),"") -> 45930 | O22: =IF(F23<=TODAY(),C22,"0") -> 0 | P22: =IF(F23<=TODAY(),D22,"0") -> 0 | Q22: =IF(F23<=TODAY(),F23,"0") -> 0 | R22: =IF(F23<=TODAY(),F24,0) -> 0 | S22: =IF(G23<=TODAY(),G24,0) -> 0 | T22: =IF(H23<=TODAY(),H24,0) -> 0 | U22: =IF(I23<=TODAY(),I24,0) -> 0 | V22: =IF(J23<=TODAY(),J24,0) -> 0 | W22: =IF(L23<=TODAY(),L24,0) -> 0 | X22: =IF(K23<=TODAY(),K24,"-") -> 0 | Z22: =C22 -> 6 | AA22: =D22 -> Company 6 | AB22: =F23 -> 44407 | AC22: =IF(F23>TODAY(),F24,"0") -> 1250000 | AD22: =IF(G23>TODAY(),G24,"0") -> 112500 | AE22: =IF(H23>TODAY(),H24,"0") -> 937500 | AF22: =IF(I23>TODAY(),I24,"0") -> 750000 | AG22: =IF(J23>TODAY(),J24,"0") -> 0 | AH22: =IF(L23>TODAY(),L24,"0") -> 0
E23: Date | F23: =IF(C22<=$H$3,IF((F20+('Summary and Assumptions'!$K$118*7))>$D$3,(F20+('Summary and Assumptions'!$K$118*7)),($D$3+$H$4)),"") -> 44407 | G23: =IF($C22<=$H$3,IF((F23+('Summary and Assumptions'!$K$119*7))>$D$3,(F23+('Summary and Assumptions'!$K$119*7)),($D$3+$H$4)),"") -> 44862 | H23: =IF($C22<=$H$3,IF((F23+('Summary and Assumptions'!$K$120*7))>$D$3,(F23+('Summary and Assumptions'!$K$120*7)),($D$3+$H$4)),"") -> 44932 | I23: =IF($C22<=$H$3,IF((H23+('Summary and Assumptions'!$K$121*7))>$D$3,(H23+('Summary and Assumptions'!$K$121*7)),($D$3+$H$4)),"") -> 45464 | J23: =IF($C22<=$H$3,IF((I23+('Summary and Assumptions'!$K$122*7))>$D$3,(I23+('Summary and Assumptions'!$K$122*7)),($D$3+$H$4)),"") -> 45912 | L23: =IF($C22<=$H$3,IF((J23+('Summary and Assumptions'!$K$123*7))>$D$3,(J23+('Summary and Assumptions'!$K$123*7)),($D$3+$H$4)),"") -> 45912
E24: Amount | F24: =IF(C22<=$H$3,'Summary and Assumptions'!$D$101,"") -> 1250000 | G24: =IF(C22<=$H$3,F24*'Summary and Assumptions'!$K$111*'Summary and Assumptions'!$K$102,"") -> 112500 | H24: =IF(C22<=$H$3,$F24*'Summary and Assumptions'!$K$112*'Summary and Assumptions'!$K$103,"") -> 937500 | I24: =IF(C22<=$H$3,$F24*'Summary and Assumptions'!$K$113*'Summary and Assumptions'!$K$104,"") -> 750000 | J24: =IF(C22<=$H$3,$F24*'Summary and Assumptions'!$K$114*'Summary and Assumptions'!$K$105,"") -> 0 | K24: =IF(AND(J23<=$D$3,J24>0),$J$6,IF(AND(I23<=$D$3,I24>0),$I$6,IF(AND(H23<=$D$3,H24>0),$H$6,IF(AND(G23<=$D$3,G24>0),$G$6,IF(AND(F23<=$D$3,F24>0),$F$6,"0"))))) -> 0 | L24: =IF(C22<=$H$3,SUM($F24:$I24)*(1+'Summary and Assumptions'!$D$103),"") -> 0
B25: F | C25: =C22+1 -> 7 | D25: =IF(C25<=$H$3,"Company"&" "&C25,"") -> Company 7 | E25: FQ End Date | F25: =IFERROR(IF(F26>0,(DATE(YEAR(F26),((INT((MONTH(F26)-1)/3)+1)*3)+1,1)-1),"-"),"NA") -> 44469 | G25: =IFERROR(IF(G26>0,(DATE(YEAR(G26),((INT((MONTH(G26)-1)/3)+1)*3)+1,1)-1),"-"),"NA") -> 44926 | H25: =IFERROR(IF(H26>0,(DATE(YEAR(H26),((INT((MONTH(H26)-1)/3)+1)*3)+1,1)-1),"-"),"NA") -> 45016 | I25: =IFERROR(IF(I26>0,(DATE(YEAR(I26),((INT((MONTH(I26)-1)/3)+1)*3)+1,1)-1),"-"),"NA") -> 45565 | J25: =IFERROR(IF(J26>0,(DATE(YEAR(J26),((INT((MONTH(J26)-1)/3)+1)*3)+1,1)-1),"-"),"NA") -> 46022 | L25: =IFERROR(IF(L26>0,(DATE(YEAR(L26),((INT((MONTH(L26)-1)/3)+1)*3)+1,1)-1),"-"),"") -> 46022 | O25: =IF(F26<=TODAY(),C25,"0") -> 0 | P25: =IF(F26<=TODAY(),D25,"0") -> 0 | Q25: =IF(F26<=TODAY(),F26,"0") -> 0 | R25: =IF(F26<=TODAY(),F27,0) -> 0 | S25: =IF(G26<=TODAY(),G27,0) -> 0 | T25: =IF(H26<=TODAY(),H27,0) -> 0 | U25: =IF(I26<=TODAY(),I27,0) -> 0 | V25: =IF(J26<=TODAY(),J27,0) -> 0 | W25: =IF(L26<=TODAY(),L27,0) -> 0 | X25: =IF(K26<=TODAY(),K27,"-") -> 0 | Z25: =C25 -> 7 | AA25: =D25 -> Company 7 | AB25: =F26 -> 44442 | AC25: =IF(F26>TODAY(),F27,"0") -> 1250000 | AD25: =IF(G26>TODAY(),G27,"0") -> 112500 | AE25: =IF(H26>TODAY(),H27,"0") -> 937500 | AF25: =IF(I26>TODAY(),I27,"0") -> 750000 | AG25: =IF(J26>TODAY(),J27,"0") -> 0 | AH25: =IF(L26>TODAY(),L27,"0") -> 0
E26: Date | F26: =IF(C25<=$H$3,IF((F23+('Summary and Assumptions'!$K$118*7))>$D$3,(F23+('Summary and Assumptions'!$K$118*7)),($D$3+$H$4)),"") -> 44442 | G26: =IF($C25<=$H$3,IF((F26+('Summary and Assumptions'!$K$119*7))>$D$3,(F26+('Summary and Assumptions'!$K$119*7)),($D$3+$H$4)),"") -> 44897 | H26: =IF($C25<=$H$3,IF((F26+('Summary and Assumptions'!$K$120*7))>$D$3,(F26+('Summary and Assumptions'!$K$120*7)),($D$3+$H$4)),"") -> 44967 | I26: =IF($C25<=$H$3,IF((H26+('Summary and Assumptions'!$K$121*7))>$D$3,(H26+('Summary and Assumptions'!$K$121*7)),($D$3+$H$4)),"") -> 45499 | J26: =IF($C25<=$H$3,IF((I26+('Summary and Assumptions'!$K$122*7))>$D$3,(I26+('Summary and Assumptions'!$K$122*7)),($D$3+$H$4)),"") -> 45947 | L26: =IF($C25<=$H$3,IF((J26+('Summary and Assumptions'!$K$123*7))>$D$3,(J26+('Summary and Assumptions'!$K$123*7)),($D$3+$H$4)),"") -> 45947
E27: Amount | F27: =IF(C25<=$H$3,'Summary and Assumptions'!$D$101,"") -> 1250000 | G27: =IF(C25<=$H$3,F27*'Summary and Assumptions'!$K$111*'Summary and Assumptions'!$K$102,"") -> 112500 | H27: =IF(C25<=$H$3,$F27*'Summary and Assumptions'!$K$112*'Summary and Assumptions'!$K$103,"") -> 937500 | I27: =IF(C25<=$H$3,$F27*'Summary and Assumptions'!$K$113*'Summary and Assumptions'!$K$104,"") -> 750000 | J27: =IF(C25<=$H$3,$F27*'Summary and Assumptions'!$K$114*'Summary and Assumptions'!$K$105,"") -> 0 | K27: =IF(AND(J26<=$D$3,J27>0),$J$6,IF(AND(I26<=$D$3,I27>0),$I$6,IF(AND(H26<=$D$3,H27>0),$H$6,IF(AND(G26<=$D$3,G27>0),$G$6,IF(AND(F26<=$D$3,F27>0),$F$6,"0"))))) -> 0 | L27: =IF(C25<=$H$3,SUM($F27:$I27)*(1+'Summary and Assumptions'!$D$103),"") -> 0
B28: F | C28: =C25+1 -> 8 | D28: =IF(C28<=$H$3,"Company"&" "&C28,"") -> Company 8 | E28: FQ End Date | F28: =IFERROR(IF(F29>0,(DATE(YEAR(F29),((INT((MONTH(F29)-1)/3)+1)*3)+1,1)-1),"-"),"NA") -> 44561 | G28: =IFERROR(IF(G29>0,(DATE(YEAR(G29),((INT((MONTH(G29)-1)/3)+1)*3)+1,1)-1),"-"),"NA") -> 45016 | H28: =IFERROR(IF(H29>0,(DATE(YEAR(H29),((INT((MONTH(H29)-1)/3)+1)*3)+1,1)-1),"-"),"NA") -> 45016 | I28: =IFERROR(IF(I29>0,(DATE(YEAR(I29),((INT((MONTH(I29)-1)/3)+1)*3)+1,1)-1),"-"),"NA") -> 45565 | J28: =IFERROR(IF(J29>0,(DATE(YEAR(J29),((INT((MONTH(J29)-1)/3)+1)*3)+1,1)-1),"-"),"NA") -> 46022 | L28: =IFERROR(IF(L29>0,(DATE(YEAR(L29),((INT((MONTH(L29)-1)/3)+1)*3)+1,1)-1),"-"),"") -> 46022 | O28: =IF(F29<=TODAY(),C28,"0") -> 0 | P28: =IF(F29<=TODAY(),D28,"0") -> 0 | Q28: =IF(F29<=TODAY(),F29,"0") -> 0 | R28: =IF(F29<=TODAY(),F30,0) -> 0 | S28: =IF(G29<=TODAY(),G30,0) -> 0 | T28: =IF(H29<=TODAY(),H30,0) -> 0 | U28: =IF(I29<=TODAY(),I30,0) -> 0 | V28: =IF(J29<=TODAY(),J30,0) -> 0 | W28: =IF(L29<=TODAY(),L30,0) -> 0 | X28: =IF(K29<=TODAY(),K30,"-") -> 0 | Z28: =C28 -> 8 | AA28: =D28 -> Company 8 | AB28: =F29 -> 44477 | AC28: =IF(F29>TODAY(),F30,"0") -> 1250000 | AD28: =IF(G29>TODAY(),G30,"0") -> 112500 | AE28: =IF(H29>TODAY(),H30,"0") -> 937500 | AF28: =IF(I29>TODAY(),I30,"0") -> 750000 | AG28: =IF(J29>TODAY(),J30,"0") -> 0 | AH28: =IF(L29>TODAY(),L30,"0") -> 0
E29: Date | F29: =IF(C28<=$H$3,IF((F26+('Summary and Assumptions'!$K$118*7))>$D$3,(F26+('Summary and Assumptions'!$K$118*7)),($D$3+$H$4)),"") -> 44477 | G29: =IF($C28<=$H$3,IF((F29+('Summary and Assumptions'!$K$119*7))>$D$3,(F29+('Summary and Assumptions'!$K$119*7)),($D$3+$H$4)),"") -> 44932 | H29: =IF($C28<=$H$3,IF((F29+('Summary and Assumptions'!$K$120*7))>$D$3,(F29+('Summary and Assumptions'!$K$120*7)),($D$3+$H$4)),"") -> 45002 | I29: =IF($C28<=$H$3,IF((H29+('Summary and Assumptions'!$K$121*7))>$D$3,(H29+('Summary and Assumptions'!$K$121*7)),($D$3+$H$4)),"") -> 45534 | J29: =IF($C28<=$H$3,IF((I29+('Summary and Assumptions'!$K$122*7))>$D$3,(I29+('Summary and Assumptions'!$K$122*7)),($D$3+$H$4)),"") -> 45982 | L29: =IF($C28<=$H$3,IF((J29+('Summary and Assumptions'!$K$123*7))>$D$3,(J29+('Summary and Assumptions'!$K$123*7)),($D$3+$H$4)),"") -> 45982
E30: Amount | F30: =IF(C28<=$H$3,'Summary and Assumptions'!$D$101,"") -> 1250000 | G30: =IF(C28<=$H$3,F30*'Summary and Assumptions'!$K$111*'Summary and Assumptions'!$K$102,"") -> 112500 | H30: =IF(C28<=$H$3,$F30*'Summary and Assumptions'!$K$112*'Summary and Assumptions'!$K$103,"") -> 937500 | I30: =IF(C28<=$H$3,$F30*'Summary and Assumptions'!$K$113*'Summary and Assumptions'!$K$104,"") -> 750000 | J30: =IF(C28<=$H$3,$F30*'Summary and Assumptions'!$K$114*'Summary and Assumptions'!$K$105,"") -> 0 | K30: =IF(AND(J29<=$D$3,J30>0),$J$6,IF(AND(I29<=$D$3,I30>0),$I$6,IF(AND(H29<=$D$3,H30>0),$H$6,IF(AND(G29<=$D$3,G30>0),$G$6,IF(AND(F29<=$D$3,F30>0),$F$6,"0"))))) -> 0 | L30: =IF(C28<=$H$3,SUM($F30:$I30)*(1+'Summary and Assumptions'!$D$103),"") -> 0
B31: F | C31: =C28+1 -> 9 | D31: =IF(C31<=$H$3,"Company"&" "&C31,"") -> Company 9 | E31: FQ End Date | F31: =IFERROR(IF(F32>0,(DATE(YEAR(F32),((INT((MONTH(F32)-1)/3)+1)*3)+1,1)-1),"-"),"NA") -> 44561 | G31: =IFERROR(IF(G32>0,(DATE(YEAR(G32),((INT((MONTH(G32)-1)/3)+1)*3)+1,1)-1),"-"),"NA") -> 45016 | H31: =IFERROR(IF(H32>0,(DATE(YEAR(H32),((INT((MONTH(H32)-1)/3)+1)*3)+1,1)-1),"-"),"NA") -> 45107 | I31: =IFERROR(IF(I32>0,(DATE(YEAR(I32),((INT((MONTH(I32)-1)/3)+1)*3)+1,1)-1),"-"),"NA") -> 45657 | J31: =IFERROR(IF(J32>0,(DATE(YEAR(J32),((INT((MONTH(J32)-1)/3)+1)*3)+1,1)-1),"-"),"NA") -> 46022 | L31: =IFERROR(IF(L32>0,(DATE(YEAR(L32),((INT((MONTH(L32)-1)/3)+1)*3)+1,1)-1),"-"),"") -> 46022 | O31: =IF(F32<=TODAY(),C31,"0") -> 0 | P31: =IF(F32<=TODAY(),D31,"0") -> 0 | Q31: =IF(F32<=TODAY(),F32,"0") -> 0 | R31: =IF(F32<=TODAY(),F33,0) -> 0 | S31: =IF(G32<=TODAY(),G33,0) -> 0 | T31: =IF(H32<=TODAY(),H33,0) -> 0 | U31: =IF(I32<=TODAY(),I33,0) -> 0 | V31: =IF(J32<=TODAY(),J33,0) -> 0 | W31: =IF(L32<=TODAY(),L33,0) -> 0 | X31: =IF(K32<=TODAY(),K33,"-") -> 0 | Z31: =C31 -> 9 | AA31: =D31 -> Company 9 | AB31: =F32 -> 44512 | AC31: =IF(F32>TODAY(),F33,"0") -> 1250000 | AD31: =IF(G32>TODAY(),G33,"0") -> 112500 | AE31: =IF(H32>TODAY(),H33,"0") -> 937500 | AF31: =IF(I32>TODAY(),I33,"0") -> 750000 | AG31: =IF(J32>TODAY(),J33,"0") -> 0 | AH31: =IF(L32>TODAY(),L33,"0") -> 0
E32: Date | F32: =IF(C31<=$H$3,IF((F29+('Summary and Assumptions'!$K$118*7))>$D$3,(F29+('Summary and Assumptions'!$K$118*7)),($D$3+$H$4)),"") -> 44512 | G32: =IF($C31<=$H$3,IF((F32+('Summary and Assumptions'!$K$119*7))>$D$3,(F32+('Summary and Assumptions'!$K$119*7)),($D$3+$H$4)),"") -> 44967 | H32: =IF($C31<=$H$3,IF((F32+('Summary and Assumptions'!$K$120*7))>$D$3,(F32+('Summary and Assumptions'!$K$120*7)),($D$3+$H$4)),"") -> 45037 | I32: =IF($C31<=$H$3,IF((H32+('Summary and Assumptions'!$K$121*7))>$D$3,(H32+('Summary and Assumptions'!$K$121*7)),($D$3+$H$4)),"") -> 45569 | J32: =IF($C31<=$H$3,IF((I32+('Summary and Assumptions'!$K$122*7))>$D$3,(I32+('Summary and Assumptions'!$K$122*7)),($D$3+$H$4)),"") -> 46017 | L32: =IF($C31<=$H$3,IF((J32+('Summary and Assumptions'!$K$123*7))>$D$3,(J32+('Summary and Assumptions'!$K$123*7)),($D$3+$H$4)),"") -> 46017
E33: Amount | F33: =IF(C31<=$H$3,'Summary and Assumptions'!$D$101,"") -> 1250000 | G33: =IF(C31<=$H$3,F33*'Summary and Assumptions'!$K$111*'Summary and Assumptions'!$K$102,"") -> 112500 | H33: =IF(C31<=$H$3,$F33*'Summary and Assumptions'!$K$112*'Summary and Assumptions'!$K$103,"") -> 937500 | I33: =IF(C31<=$H$3,$F33*'Summary and Assumptions'!$K$113*'Summary and Assumptions'!$K$104,"") -> 750000 | J33: =IF(C31<=$H$3,$F33*'Summary and Assumptions'!$K$114*'Summary and Assumptions'!$K$105,"") -> 0 | K33: =IF(AND(J32<=$D$3,J33>0),$J$6,IF(AND(I32<=$D$3,I33>0),$I$6,IF(AND(H32<=$D$3,H33>0),$H$6,IF(AND(G32<=$D$3,G33>0),$G$6,IF(AND(F32<=$D$3,F33>0),$F$6,"0"))))) -> 0 | L33: =IF(C31<=$H$3,SUM($F33:$I33)*(1+'Summary and Assumptions'!$D$103),"") -> 0
B34: F | C34: =C31+1 -> 10 | D34: =IF(C34<=$H$3,"Company"&" "&C34,"") -> Company 10 | E34: FQ End Date | F34: =IFERROR(IF(F35>0,(DATE(YEAR(F35),((INT((MONTH(F35)-1)/3)+1)*3)+1,1)-1),"-"),"NA") -> 44561 | G34: =IFERROR(IF(G35>0,(DATE(YEAR(G35),((INT((MONTH(G35)-1)/3)+1)*3)+1,1)-1),"-"),"NA") -> 45016 | H34: =IFERROR(IF(H35>0,(DATE(YEAR(H35),((INT((MONTH(H35)-1)/3)+1)*3)+1,1)-1),"-"),"NA") -> 45107 | I34: =IFERROR(IF(I35>0,(DATE(YEAR(I35),((INT((MONTH(I35)-1)/3)+1)*3)+1,1)-1),"-"),"NA") -> 45657 | J34: =IFERROR(IF(J35>0,(DATE(YEAR(J35),((INT((MONTH(J35)-1)/3)+1)*3)+1,1)-1),"-"),"NA") -> 46112 | L34: =IFERROR(IF(L35>0,(DATE(YEAR(L35),((INT((MONTH(L35)-1)/3)+1)*3)+1,1)-1),"-"),"") -> 46112 | O34: =IF(F35<=TODAY(),C34,"0") -> 0 | P34: =IF(F35<=TODAY(),D34,"0") -> 0 | Q34: =IF(F35<=TODAY(),F35,"0") -> 0 | R34: =IF(F35<=TODAY(),F36,0) -> 0 | S34: =IF(G35<=TODAY(),G36,0) -> 0 | T34: =IF(H35<=TODAY(),H36,0) -> 0 | U34: =IF(I35<=TODAY(),I36,0) -> 0 | V34: =IF(J35<=TODAY(),J36,0) -> 0 | W34: =IF(L35<=TODAY(),L36,0) -> 0 | X34: =IF(K35<=TODAY(),K36,"-") -> 0 | Z34: =C34 -> 10 | AA34: =D34 -> Company 10 | AB34: =F35 -> 44547 | AC34: =IF(F35>TODAY(),F36,"0") -> 1250000 | AD34: =IF(G35>TODAY(),G36,"0") -> 112500 | AE34: =IF(H35>TODAY(),H36,"0") -> 937500 | AF34: =IF(I35>TODAY(),I36,"0") -> 750000 | AG34: =IF(J35>TODAY(),J36,"0") -> 0 | AH34: =IF(L35>TODAY(),L36,"0") -> 0
E35: Date | F35: =IF(C34<=$H$3,IF((F32+('Summary and Assumptions'!$K$118*7))>$D$3,(F32+('Summary and Assumptions'!$K$118*7)),($D$3+$H$4)),"") -> 44547 | G35: =IF($C34<=$H$3,IF((F35+('Summary and Assumptions'!$K$119*7))>$D$3,(F35+('Summary and Assumptions'!$K$119*7)),($D$3+$H$4)),"") -> 45002 | H35: =IF($C34<=$H$3,IF((F35+('Summary and Assumptions'!$K$120*7))>$D$3,(F35+('Summary and Assumptions'!$K$120*7)),($D$3+$H$4)),"") -> 45072 | I35: =IF($C34<=$H$3,IF((H35+('Summary and Assumptions'!$K$121*7))>$D$3,(H35+('Summary and Assumptions'!$K$121*7)),($D$3+$H$4)),"") -> 45604 | J35: =IF($C34<=$H$3,IF((I35+('Summary and Assumptions'!$K$122*7))>$D$3,(I35+('Summary and Assumptions'!$K$122*7)),($D$3+$H$4)),"") -> 46052 | L35: =IF($C34<=$H$3,IF((J35+('Summary and Assumptions'!$K$123*7))>$D$3,(J35+('Summary and Assumptions'!$K$123*7)),($D$3+$H$4)),"") -> 46052
E36: Amount | F36: =IF(C34<=$H$3,'Summary and Assumptions'!$D$101,"") -> 1250000 | G36: =IF(C34<=$H$3,F36*'Summary and Assumptions'!$K$111*'Summary and Assumptions'!$K$102,"") -> 112500 | H36: =IF(C34<=$H$3,$F36*'Summary and Assumptions'!$K$112*'Summary and Assumptions'!$K$103,"") -> 937500 | I36: =IF(C34<=$H$3,$F36*'Summary and Assumptions'!$K$113*'Summary and Assumptions'!$K$104,"") -> 750000 | J36: =IF(C34<=$H$3,$F36*'Summary and Assumptions'!$K$114*'Summary and Assumptions'!$K$105,"") -> 0 | K36: =IF(AND(J35<=$D$3,J36>0),$J$6,IF(AND(I35<=$D$3,I36>0),$I$6,IF(AND(H35<=$D$3,H36>0),$H$6,IF(AND(G35<=$D$3,G36>0),$G$6,IF(AND(F35<=$D$3,F36>0),$F$6,"0"))))) -> 0 | L36: =IF(C34<=$H$3,SUM($F36:$I36)*(1+'Summary and Assumptions'!$D$103),"") -> 0
B37: F | C37: =C34+1 -> 11 | D37: =IF(C37<=$H$3,"Company"&" "&C37,"") -> Company 11 | E37: FQ End Date | F37: =IFERROR(IF(F38>0,(DATE(YEAR(F38),((INT((MONTH(F38)-1)/3)+1)*3)+1,1)-1),"-"),"NA") -> 44651 | G37: =IFERROR(IF(G38>0,(DATE(YEAR(G38),((INT((MONTH(G38)-1)/3)+1)*3)+1,1)-1),"-"),"NA") -> 45107 | H37: =IFERROR(IF(H38>0,(DATE(YEAR(H38),((INT((MONTH(H38)-1)/3)+1)*3)+1,1)-1),"-"),"NA") -> 45107 | I37: =IFERROR(IF(I38>0,(DATE(YEAR(I38),((INT((MONTH(I38)-1)/3)+1)*3)+1,1)-1),"-"),"NA") -> 45657 | J37: =IFERROR(IF(J38>0,(DATE(YEAR(J38),((INT((MONTH(J38)-1)/3)+1)*3)+1,1)-1),"-"),"NA") -> 46112 | L37: =IFERROR(IF(L38>0,(DATE(YEAR(L38),((INT((MONTH(L38)-1)/3)+1)*3)+1,1)-1),"-"),"") -> 46112 | O37: =IF(F38<=TODAY(),C37,"0") -> 0 | P37: =IF(F38<=TODAY(),D37,"0") -> 0 | Q37: =IF(F38<=TODAY(),F38,"0") -> 0 | R37: =IF(F38<=TODAY(),F39,0) -> 0 | S37: =IF(G38<=TODAY(),G39,0) -> 0 | T37: =IF(H38<=TODAY(),H39,0) -> 0 | U37: =IF(I38<=TODAY(),I39,0) -> 0 | V37: =IF(J38<=TODAY(),J39,0) -> 0 | W37: =IF(L38<=TODAY(),L39,0) -> 0 | X37: =IF(K38<=TODAY(),K39,"-") -> 0 | Z37: =C37 -> 11 | AA37: =D37 -> Company 11 | AB37: =F38 -> 44582 | AC37: =IF(F38>TODAY(),F39,"0") -> 1250000 | AD37: =IF(G38>TODAY(),G39,"0") -> 112500 | AE37: =IF(H38>TODAY(),H39,"0") -> 937500 | AF37: =IF(I38>TODAY(),I39,"0") -> 750000 | AG37: =IF(J38>TODAY(),J39,"0") -> 0 | AH37: =IF(L38>TODAY(),L39,"0") -> 0
E38: Date | F38: =IF(C37<=$H$3,IF((F35+('Summary and Assumptions'!$K$118*7))>$D$3,(F35+('Summary and Assumptions'!$K$118*7)),($D$3+$H$4)),"") -> 44582 | G38: =IF($C37<=$H$3,IF((F38+('Summary and Assumptions'!$K$119*7))>$D$3,(F38+('Summary and Assumptions'!$K$119*7)),($D$3+$H$4)),"") -> 45037 | H38: =IF($C37<=$H$3,IF((F38+('Summary and Assumptions'!$K$120*7))>$D$3,(F38+('Summary and Assumptions'!$K$120*7)),($D$3+$H$4)),"") -> 45107 | I38: =IF($C37<=$H$3,IF((H38+('Summary and Assumptions'!$K$121*7))>$D$3,(H38+('Summary and Assumptions'!$K$121*7)),($D$3+$H$4)),"") -> 45639 | J38: =IF($C37<=$H$3,IF((I38+('Summary and Assumptions'!$K$122*7))>$D$3,(I38+('Summary and Assumptions'!$K$122*7)),($D$3+$H$4)),"") -> 46087 | L38: =IF($C37<=$H$3,IF((J38+('Summary and Assumptions'!$K$123*7))>$D$3,(J38+('Summary and Assumptions'!$K$123*7)),($D$3+$H$4)),"") -> 46087
E39: Amount | F39: =IF(C37<=$H$3,'Summary and Assumptions'!$D$101,"") -> 1250000 | G39: =IF(C37<=$H$3,F39*'Summary and Assumptions'!$K$111*'Summary and Assumptions'!$K$102,"") -> 112500 | H39: =IF(C37<=$H$3,$F39*'Summary and Assumptions'!$K$112*'Summary and Assumptions'!$K$103,"") -> 937500 | I39: =IF(C37<=$H$3,$F39*'Summary and Assumptions'!$K$113*'Summary and Assumptions'!$K$104,"") -> 750000 | J39: =IF(C37<=$H$3,$F39*'Summary and Assumptions'!$K$114*'Summary and Assumptions'!$K$105,"") -> 0 | K39: =IF(AND(J38<=$D$3,J39>0),$J$6,IF(AND(I38<=$D$3,I39>0),$I$6,IF(AND(H38<=$D$3,H39>0),$H$6,IF(AND(G38<=$D$3,G39>0),$G$6,IF(AND(F38<=$D$3,F39>0),$F$6,"0"))))) -> 0 | L39: =IF(C37<=$H$3,SUM($F39:$I39)*(1+'Summary and Assumptions'!$D$103),"") -> 0
B40: F | C40: =C37+1 -> 12 | D40: =IF(C40<=$H$3,"Company"&" "&C40,"") -> Company 12 | E40: FQ End Date | F40: =IFERROR(IF(F41>0,(DATE(YEAR(F41),((INT((MONTH(F41)-1)/3)+1)*3)+1,1)-1),"-"),"NA") -> 44651 | G40: =IFERROR(IF(G41>0,(DATE(YEAR(G41),((INT((MONTH(G41)-1)/3)+1)*3)+1,1)-1),"-"),"NA") -> 45107 | H40: =IFERROR(IF(H41>0,(DATE(YEAR(H41),((INT((MONTH(H41)-1)/3)+1)*3)+1,1)-1),"-"),"NA") -> 45199 | I40: =IFERROR(IF(I41>0,(DATE(YEAR(I41),((INT((MONTH(I41)-1)/3)+1)*3)+1,1)-1),"-"),"NA") -> 45747 | J40: =IFERROR(IF(J41>0,(DATE(YEAR(J41),((INT((MONTH(J41)-1)/3)+1)*3)+1,1)-1),"-"),"NA") -> 46203 | L40: =IFERROR(IF(L41>0,(DATE(YEAR(L41),((INT((MONTH(L41)-1)/3)+1)*3)+1,1)-1),"-"),"") -> 46203 | O40: =IF(F41<=TODAY(),C40,"0") -> 0 | P40: =IF(F41<=TODAY(),D40,"0") -> 0 | Q40: =IF(F41<=TODAY(),F41,"0") -> 0 | R40: =IF(F41<=TODAY(),F42,0) -> 0 | S40: =IF(G41<=TODAY(),G42,0) -> 0 | T40: =IF(H41<=TODAY(),H42,0) -> 0 | U40: =IF(I41<=TODAY(),I42,0) -> 0 | V40: =IF(J41<=TODAY(),J42,0) -> 0 | W40: =IF(L41<=TODAY(),L42,0) -> 0 | X40: =IF(K41<=TODAY(),K42,"-") -> 0 | Z40: =C40 -> 12 | AA40: =D40 -> Company 12 | AB40: =F41 -> 44617 | AC40: =IF(F41>TODAY(),F42,"0") -> 1250000 | AD40: =IF(G41>TODAY(),G42,"0") -> 112500 | AE40: =IF(H41>TODAY(),H42,"0") -> 937500 | AF40: =IF(I41>TODAY(),I42,"0") -> 750000 | AG40: =IF(J41>TODAY(),J42,"0") -> 0 | AH40: =IF(L41>TODAY(),L42,"0") -> 0
E41: Date | F41: =IF(C40<=$H$3,IF((F38+('Summary and Assumptions'!$K$118*7))>$D$3,(F38+('Summary and Assumptions'!$K$118*7)),($D$3+$H$4)),"") -> 44617 | G41: =IF($C40<=$H$3,IF((F41+('Summary and Assumptions'!$K$119*7))>$D$3,(F41+('Summary and Assumptions'!$K$119*7)),($D$3+$H$4)),"") -> 45072 | H41: =IF($C40<=$H$3,IF((F41+('Summary and Assumptions'!$K$120*7))>$D$3,(F41+('Summary and Assumptions'!$K$120*7)),($D$3+$H$4)),"") -> 45142 | I41: =IF($C40<=$H$3,IF((H41+('Summary and Assumptions'!$K$121*7))>$D$3,(H41+('Summary and Assumptions'!$K$121*7)),($D$3+$H$4)),"") -> 45674 | J41: =IF($C40<=$H$3,IF((I41+('Summary and Assumptions'!$K$122*7))>$D$3,(I41+('Summary and Assumptions'!$K$122*7)),($D$3+$H$4)),"") -> 46122 | L41: =IF($C40<=$H$3,IF((J41+('Summary and Assumptions'!$K$123*7))>$D$3,(J41+('Summary and Assumptions'!$K$123*7)),($D$3+$H$4)),"") -> 46122
E42: Amount | F42: =IF(C40<=$H$3,'Summary and Assumptions'!$D$101,"") -> 1250000 | G42: =IF(C40<=$H$3,F42*'Summary and Assumptions'!$K$111*'Summary and Assumptions'!$K$102,"") -> 112500 | H42: =IF(C40<=$H$3,$F42*'Summary and Assumptions'!$K$112*'Summary and Assumptions'!$K$103,"") -> 937500 | I42: =IF(C40<=$H$3,$F42*'Summary and Assumptions'!$K$113*'Summary and Assumptions'!$K$104,"") -> 750000 | J42: =IF(C40<=$H$3,$F42*'Summary and Assumptions'!$K$114*'Summary and Assumptions'!$K$105,"") -> 0 | K42: =IF(AND(J41<=$D$3,J42>0),$J$6,IF(AND(I41<=$D$3,I42>0),$I$6,IF(AND(H41<=$D$3,H42>0),$H$6,IF(AND(G41<=$D$3,G42>0),$G$6,IF(AND(F41<=$D$3,F42>0),$F$6,"0"))))) -> 0 | L42: =IF(C40<=$H$3,SUM($F42:$I42)*(1+'Summary and Assumptions'!$D$103),"") -> 0
B43: F | C43: =C40+1 -> 13 | D43: =IF(C43<=$H$3,"Company"&" "&C43,"") -> Company 13 | E43: FQ End Date | F43: =IFERROR(IF(F44>0,(DATE(YEAR(F44),((INT((MONTH(F44)-1)/3)+1)*3)+1,1)-1),"-"),"NA") -> 44742 | G43: =IFERROR(IF(G44>0,(DATE(YEAR(G44),((INT((MONTH(G44)-1)/3)+1)*3)+1,1)-1),"-"),"NA") -> 45107 | H43: =IFERROR(IF(H44>0,(DATE(YEAR(H44),((INT((MONTH(H44)-1)/3)+1)*3)+1,1)-1),"-"),"NA") -> 45199 | I43: =IFERROR(IF(I44>0,(DATE(YEAR(I44),((INT((MONTH(I44)-1)/3)+1)*3)+1,1)-1),"-"),"NA") -> 45747 | J43: =IFERROR(IF(J44>0,(DATE(YEAR(J44),((INT((MONTH(J44)-1)/3)+1)*3)+1,1)-1),"-"),"NA") -> 46203 | L43: =IFERROR(IF(L44>0,(DATE(YEAR(L44),((INT((MONTH(L44)-1)/3)+1)*3)+1,1)-1),"-"),"") -> 46203 | O43: =IF(F44<=TODAY(),C43,"0") -> 0 | P43: =IF(F44<=TODAY(),D43,"0") -> 0 | Q43: =IF(F44<=TODAY(),F44,"0") -> 0 | R43: =IF(F44<=TODAY(),F45,0) -> 0 | S43: =IF(G44<=TODAY(),G45,0) -> 0 | T43: =IF(H44<=TODAY(),H45,0) -> 0 | U43: =IF(I44<=TODAY(),I45,0) -> 0 | V43: =IF(J44<=TODAY(),J45,0) -> 0 | W43: =IF(L44<=TODAY(),L45,0) -> 0 | X43: =IF(K44<=TODAY(),K45,"-") -> 0 | Z43: =C43 -> 13 | AA43: =D43 -> Company 13 | AB43: =F44 -> 44652 | AC43: =IF(F44>TODAY(),F45,"0") -> 1250000 | AD43: =IF(G44>TODAY(),G45,"0") -> 112500 | AE43: =IF(H44>TODAY(),H45,"0") -> 937500 | AF43: =IF(I44>TODAY(),I45,"0") -> 750000 | AG43: =IF(J44>TODAY(),J45,"0") -> 0 | AH43: =IF(L44>TODAY(),L45,"0") -> 0
E44: Date | F44: =IF(C43<=$H$3,IF((F41+('Summary and Assumptions'!$K$118*7))>$D$3,(F41+('Summary and Assumptions'!$K$118*7)),($D$3+$H$4)),"") -> 44652 | G44: =IF($C43<=$H$3,IF((F44+('Summary and Assumptions'!$K$119*7))>$D$3,(F44+('Summary and Assumptions'!$K$119*7)),($D$3+$H$4)),"") -> 45107 | H44: =IF($C43<=$H$3,IF((F44+('Summary and Assumptions'!$K$120*7))>$D$3,(F44+('Summary and Assumptions'!$K$120*7)),($D$3+$H$4)),"") -> 45177 | I44: =IF($C43<=$H$3,IF((H44+('Summary and Assumptions'!$K$121*7))>$D$3,(H44+('Summary and Assumptions'!$K$121*7)),($D$3+$H$4)),"") -> 45709 | J44: =IF($C43<=$H$3,IF((I44+('Summary and Assumptions'!$K$122*7))>$D$3,(I44+('Summary and Assumptions'!$K$122*7)),($D$3+$H$4)),"") -> 46157 | L44: =IF($C43<=$H$3,IF((J44+('Summary and Assumptions'!$K$123*7))>$D$3,(J44+('Summary and Assumptions'!$K$123*7)),($D$3+$H$4)),"") -> 46157
E45: Amount | F45: =IF(C43<=$H$3,'Summary and Assumptions'!$D$101,"") -> 1250000 | G45: =IF(C43<=$H$3,F45*'Summary and Assumptions'!$K$111*'Summary and Assumptions'!$K$102,"") -> 112500 | H45: =IF(C43<=$H$3,$F45*'Summary and Assumptions'!$K$112*'Summary and Assumptions'!$K$103,"") -> 937500 | I45: =IF(C43<=$H$3,$F45*'Summary and Assumptions'!$K$113*'Summary and Assumptions'!$K$104,"") -> 750000 | J45: =IF(C43<=$H$3,$F45*'Summary and Assumptions'!$K$114*'Summary and Assumptions'!$K$105,"") -> 0 | K45: =IF(AND(J44<=$D$3,J45>0),$J$6,IF(AND(I44<=$D$3,I45>0),$I$6,IF(AND(H44<=$D$3,H45>0),$H$6,IF(AND(G44<=$D$3,G45>0),$G$6,IF(AND(F44<=$D$3,F45>0),$F$6,"0"))))) -> 0 | L45: =IF(C43<=$H$3,SUM($F45:$I45)*(1+'Summary and Assumptions'!$D$103),"") -> 0
B46: F | C46: =C43+1 -> 14 | D46: =IF(C46<=$H$3,"Company"&" "&C46,"") -> Company 14 | E46: FQ End Date | F46: =IFERROR(IF(F47>0,(DATE(YEAR(F47),((INT((MONTH(F47)-1)/3)+1)*3)+1,1)-1),"-"),"NA") -> 44742 | G46: =IFERROR(IF(G47>0,(DATE(YEAR(G47),((INT((MONTH(G47)-1)/3)+1)*3)+1,1)-1),"-"),"NA") -> 45199 | H46: =IFERROR(IF(H47>0,(DATE(YEAR(H47),((INT((MONTH(H47)-1)/3)+1)*3)+1,1)-1),"-"),"NA") -> 45291 | I46: =IFERROR(IF(I47>0,(DATE(YEAR(I47),((INT((MONTH(I47)-1)/3)+1)*3)+1,1)-1),"-"),"NA") -> 45747 | J46: =IFERROR(IF(J47>0,(DATE(YEAR(J47),((INT((MONTH(J47)-1)/3)+1)*3)+1,1)-1),"-"),"NA") -> 46203 | L46: =IFERROR(IF(L47>0,(DATE(YEAR(L47),((INT((MONTH(L47)-1)/3)+1)*3)+1,1)-1),"-"),"") -> 46203 | O46: =IF(F47<=TODAY(),C46,"0") -> 0 | P46: =IF(F47<=TODAY(),D46,"0") -> 0 | Q46: =IF(F47<=TODAY(),F47,"0") -> 0 | R46: =IF(F47<=TODAY(),F48,0) -> 0 | S46: =IF(G47<=TODAY(),G48,0) -> 0 | T46: =IF(H47<=TODAY(),H48,0) -> 0 | U46: =IF(I47<=TODAY(),I48,0) -> 0 | V46: =IF(J47<=TODAY(),J48,0) -> 0 | W46: =IF(L47<=TODAY(),L48,0) -> 0 | X46: =IF(K47<=TODAY(),K48,"-") -> 0 | Z46: =C46 -> 14 | AA46: =D46 -> Company 14 | AB46: =F47 -> 44687 | AC46: =IF(F47>TODAY(),F48,"0") -> 1250000 | AD46: =IF(G47>TODAY(),G48,"0") -> 112500 | AE46: =IF(H47>TODAY(),H48,"0") -> 937500 | AF46: =IF(I47>TODAY(),I48,"0") -> 750000 | AG46: =IF(J47>TODAY(),J48,"0") -> 0 | AH46: =IF(L47>TODAY(),L48,"0") -> 0
E47: Date | F47: =IF(C46<=$H$3,IF((F44+('Summary and Assumptions'!$K$118*7))>$D$3,(F44+('Summary and Assumptions'!$K$118*7)),($D$3+$H$4)),"") -> 44687 | G47: =IF($C46<=$H$3,IF((F47+('Summary and Assumptions'!$K$119*7))>$D$3,(F47+('Summary and Assumptions'!$K$119*7)),($D$3+$H$4)),"") -> 45142 | H47: =IF($C46<=$H$3,IF((F47+('Summary and Assumptions'!$K$120*7))>$D$3,(F47+('Summary and Assumptions'!$K$120*7)),($D$3+$H$4)),"") -> 45212 | I47: =IF($C46<=$H$3,IF((H47+('Summary and Assumptions'!$K$121*7))>$D$3,(H47+('Summary and Assumptions'!$K$121*7)),($D$3+$H$4)),"") -> 45744 | J47: =IF($C46<=$H$3,IF((I47+('Summary and Assumptions'!$K$122*7))>$D$3,(I47+('Summary and Assumptions'!$K$122*7)),($D$3+$H$4)),"") -> 46192 | L47: =IF($C46<=$H$3,IF((J47+('Summary and Assumptions'!$K$123*7))>$D$3,(J47+('Summary and Assumptions'!$K$123*7)),($D$3+$H$4)),"") -> 46192
E48: Amount | F48: =IF(C46<=$H$3,'Summary and Assumptions'!$D$101,"") -> 1250000 | G48: =IF(C46<=$H$3,F48*'Summary and Assumptions'!$K$111*'Summary and Assumptions'!$K$102,"") -> 112500 | H48: =IF(C46<=$H$3,$F48*'Summary and Assumptions'!$K$112*'Summary and Assumptions'!$K$103,"") -> 937500 | I48: =IF(C46<=$H$3,$F48*'Summary and Assumptions'!$K$113*'Summary and Assumptions'!$K$104,"") -> 750000 | J48: =IF(C46<=$H$3,$F48*'Summary and Assumptions'!$K$114*'Summary and Assumptions'!$K$105,"") -> 0 | K48: =IF(AND(J47<=$D$3,J48>0),$J$6,IF(AND(I47<=$D$3,I48>0),$I$6,IF(AND(H47<=$D$3,H48>0),$H$6,IF(AND(G47<=$D$3,G48>0),$G$6,IF(AND(F47<=$D$3,F48>0),$F$6,"0"))))) -> 0 | L48: =IF(C46<=$H$3,SUM($F48:$I48)*(1+'Summary and Assumptions'!$D$103),"") -> 0
B49: F | C49: =C46+1 -> 15 | D49: =IF(C49<=$H$3,"Company"&" "&C49,"") -> Company 15 | E49: FQ End Date | F49: =IFERROR(IF(F50>0,(DATE(YEAR(F50),((INT((MONTH(F50)-1)/3)+1)*3)+1,1)-1),"-"),"NA") -> 44742 | G49: =IFERROR(IF(G50>0,(DATE(YEAR(G50),((INT((MONTH(G50)-1)/3)+1)*3)+1,1)-1),"-"),"NA") -> 45199 | H49: =IFERROR(IF(H50>0,(DATE(YEAR(H50),((INT((MONTH(H50)-1)/3)+1)*3)+1,1)-1),"-"),"NA") -> 45291 | I49: =IFERROR(IF(I50>0,(DATE(YEAR(I50),((INT((MONTH(I50)-1)/3)+1)*3)+1,1)-1),"-"),"NA") -> 45838 | J49: =IFERROR(IF(J50>0,(DATE(YEAR(J50),((INT((MONTH(J50)-1)/3)+1)*3)+1,1)-1),"-"),"NA") -> 46295 | L49: =IFERROR(IF(L50>0,(DATE(YEAR(L50),((INT((MONTH(L50)-1)/3)+1)*3)+1,1)-1),"-"),"") -> 46295 | O49: =IF(F50<=TODAY(),C49,"0") -> 0 | P49: =IF(F50<=TODAY(),D49,"0") -> 0 | Q49: =IF(F50<=TODAY(),F50,"0") -> 0 | R49: =IF(F50<=TODAY(),F51,0) -> 0 | S49: =IF(G50<=TODAY(),G51,0) -> 0 | T49: =IF(H50<=TODAY(),H51,0) -> 0 | U49: =IF(I50<=TODAY(),I51,0) -> 0 | V49: =IF(J50<=TODAY(),J51,0) -> 0 | W49: =IF(L50<=TODAY(),L51,0) -> 0 | X49: =IF(K50<=TODAY(),K51,"-") -> 0 | Z49: =C49 -> 15 | AA49: =D49 -> Company 15 | AB49: =F50 -> 44722 | AC49: =IF(F50>TODAY(),F51,"0") -> 1250000 | AD49: =IF(G50>TODAY(),G51,"0") -> 112500 | AE49: =IF(H50>TODAY(),H51,"0") -> 937500 | AF49: =IF(I50>TODAY(),I51,"0") -> 750000 | AG49: =IF(J50>TODAY(),J51,"0") -> 0 | AH49: =IF(L50>TODAY(),L51,"0") -> 0
E50: Date | F50: =IF(C49<=$H$3,IF((F47+('Summary and Assumptions'!$K$118*7))>$D$3,(F47+('Summary and Assumptions'!$K$118*7)),($D$3+$H$4)),"") -> 44722 | G50: =IF($C49<=$H$3,IF((F50+('Summary and Assumptions'!$K$119*7))>$D$3,(F50+('Summary and Assumptions'!$K$119*7)),($D$3+$H$4)),"") -> 45177 | H50: =IF($C49<=$H$3,IF((F50+('Summary and Assumptions'!$K$120*7))>$D$3,(F50+('Summary and Assumptions'!$K$120*7)),($D$3+$H$4)),"") -> 45247 | I50: =IF($C49<=$H$3,IF((H50+('Summary and Assumptions'!$K$121*7))>$D$3,(H50+('Summary and Assumptions'!$K$121*7)),($D$3+$H$4)),"") -> 45779 | J50: =IF($C49<=$H$3,IF((I50+('Summary and Assumptions'!$K$122*7))>$D$3,(I50+('Summary and Assumptions'!$K$122*7)),($D$3+$H$4)),"") -> 46227 | L50: =IF($C49<=$H$3,IF((J50+('Summary and Assumptions'!$K$123*7))>$D$3,(J50+('Summary and Assumptions'!$K$123*7)),($D$3+$H$4)),"") -> 46227
E51: Amount | F51: =IF(C49<=$H$3,'Summary and Assumptions'!$D$101,"") -> 1250000 | G51: =IF(C49<=$H$3,F51*'Summary and Assumptions'!$K$111*'Summary and Assumptions'!$K$102,"") -> 112500 | H51: =IF(C49<=$H$3,$F51*'Summary and Assumptions'!$K$112*'Summary and Assumptions'!$K$103,"") -> 937500 | I51: =IF(C49<=$H$3,$F51*'Summary and Assumptions'!$K$113*'Summary and Assumptions'!$K$104,"") -> 750000 | J51: =IF(C49<=$H$3,$F51*'Summary and Assumptions'!$K$114*'Summary and Assumptions'!$K$105,"") -> 0 | K51: =IF(AND(J50<=$D$3,J51>0),$J$6,IF(AND(I50<=$D$3,I51>0),$I$6,IF(AND(H50<=$D$3,H51>0),$H$6,IF(AND(G50<=$D$3,G51>0),$G$6,IF(AND(F50<=$D$3,F51>0),$F$6,"0"))))) -> 0 | L51: =IF(C49<=$H$3,SUM($F51:$I51)*(1+'Summary and Assumptions'!$D$103),"") -> 0
B52: F | C52: =C49+1 -> 16 | D52: =IF(C52<=$H$3,"Company"&" "&C52,"") -> Company 16 | E52: FQ End Date | F52: =IFERROR(IF(F53>0,(DATE(YEAR(F53),((INT((MONTH(F53)-1)/3)+1)*3)+1,1)-1),"-"),"NA") -> 44834 | G52: =IFERROR(IF(G53>0,(DATE(YEAR(G53),((INT((MONTH(G53)-1)/3)+1)*3)+1,1)-1),"-"),"NA") -> 45291 | H52: =IFERROR(IF(H53>0,(DATE(YEAR(H53),((INT((MONTH(H53)-1)/3)+1)*3)+1,1)-1),"-"),"NA") -> 45291 | I52: =IFERROR(IF(I53>0,(DATE(YEAR(I53),((INT((MONTH(I53)-1)/3)+1)*3)+1,1)-1),"-"),"NA") -> 45838 | J52: =IFERROR(IF(J53>0,(DATE(YEAR(J53),((INT((MONTH(J53)-1)/3)+1)*3)+1,1)-1),"-"),"NA") -> 46295 | L52: =IFERROR(IF(L53>0,(DATE(YEAR(L53),((INT((MONTH(L53)-1)/3)+1)*3)+1,1)-1),"-"),"") -> 46295 | O52: =IF(F53<=TODAY(),C52,"0") -> 0 | P52: =IF(F53<=TODAY(),D52,"0") -> 0 | Q52: =IF(F53<=TODAY(),F53,"0") -> 0 | R52: =IF(F53<=TODAY(),F54,0) -> 0 | S52: =IF(G53<=TODAY(),G54,0) -> 0 | T52: =IF(H53<=TODAY(),H54,0) -> 0 | U52: =IF(I53<=TODAY(),I54,0) -> 0 | V52: =IF(J53<=TODAY(),J54,0) -> 0 | W52: =IF(L53<=TODAY(),L54,0) -> 0 | X52: =IF(K53<=TODAY(),K54,"-") -> 0 | Z52: =C52 -> 16 | AA52: =D52 -> Company 16 | AB52: =F53 -> 44757 | AC52: =IF(F53>TODAY(),F54,"0") -> 1250000 | AD52: =IF(G53>TODAY(),G54,"0") -> 112500 | AE52: =IF(H53>TODAY(),H54,"0") -> 937500 | AF52: =IF(I53>TODAY(),I54,"0") -> 750000 | AG52: =IF(J53>TODAY(),J54,"0") -> 0 | AH52: =IF(L53>TODAY(),L54,"0") -> 0
E53: Date | F53: =IF(C52<=$H$3,IF((F50+('Summary and Assumptions'!$K$118*7))>$D$3,(F50+('Summary and Assumptions'!$K$118*7)),($D$3+$H$4)),"") -> 44757 | G53: =IF($C52<=$H$3,IF((F53+('Summary and Assumptions'!$K$119*7))>$D$3,(F53+('Summary and Assumptions'!$K$119*7)),($D$3+$H$4)),"") -> 45212 | H53: =IF($C52<=$H$3,IF((F53+('Summary and Assumptions'!$K$120*7))>$D$3,(F53+('Summary and Assumptions'!$K$120*7)),($D$3+$H$4)),"") -> 45282 | I53: =IF($C52<=$H$3,IF((H53+('Summary and Assumptions'!$K$121*7))>$D$3,(H53+('Summary and Assumptions'!$K$121*7)),($D$3+$H$4)),"") -> 45814 | J53: =IF($C52<=$H$3,IF((I53+('Summary and Assumptions'!$K$122*7))>$D$3,(I53+('Summary and Assumptions'!$K$122*7)),($D$3+$H$4)),"") -> 46262 | L53: =IF($C52<=$H$3,IF((J53+('Summary and Assumptions'!$K$123*7))>$D$3,(J53+('Summary and Assumptions'!$K$123*7)),($D$3+$H$4)),"") -> 46262
E54: Amount | F54: =IF(C52<=$H$3,'Summary and Assumptions'!$D$101,"") -> 1250000 | G54: =IF(C52<=$H$3,F54*'Summary and Assumptions'!$K$111*'Summary and Assumptions'!$K$102,"") -> 112500 | H54: =IF(C52<=$H$3,$F54*'Summary and Assumptions'!$K$112*'Summary and Assumptions'!$K$103,"") -> 937500 | I54: =IF(C52<=$H$3,$F54*'Summary and Assumptions'!$K$113*'Summary and Assumptions'!$K$104,"") -> 750000 | J54: =IF(C52<=$H$3,$F54*'Summary and Assumptions'!$K$114*'Summary and Assumptions'!$K$105,"") -> 0 | K54: =IF(AND(J53<=$D$3,J54>0),$J$6,IF(AND(I53<=$D$3,I54>0),$I$6,IF(AND(H53<=$D$3,H54>0),$H$6,IF(AND(G53<=$D$3,G54>0),$G$6,IF(AND(F53<=$D$3,F54>0),$F$6,"0"))))) -> 0 | L54: =IF(C52<=$H$3,SUM($F54:$I54)*(1+'Summary and Assumptions'!$D$103),"") -> 0
B55: F | C55: =C52+1 -> 17 | D55: =IF(C55<=$H$3,"Company"&" "&C55,"") -> Company 17 | E55: FQ End Date | F55: =IFERROR(IF(F56>0,(DATE(YEAR(F56),((INT((MONTH(F56)-1)/3)+1)*3)+1,1)-1),"-"),"NA") -> 44834 | G55: =IFERROR(IF(G56>0,(DATE(YEAR(G56),((INT((MONTH(G56)-1)/3)+1)*3)+1,1)-1),"-"),"NA") -> 45291 | H55: =IFERROR(IF(H56>0,(DATE(YEAR(H56),((INT((MONTH(H56)-1)/3)+1)*3)+1,1)-1),"-"),"NA") -> 45382 | I55: =IFERROR(IF(I56>0,(DATE(YEAR(I56),((INT((MONTH(I56)-1)/3)+1)*3)+1,1)-1),"-"),"NA") -> 45930 | J55: =IFERROR(IF(J56>0,(DATE(YEAR(J56),((INT((MONTH(J56)-1)/3)+1)*3)+1,1)-1),"-"),"NA") -> 46387 | L55: =IFERROR(IF(L56>0,(DATE(YEAR(L56),((INT((MONTH(L56)-1)/3)+1)*3)+1,1)-1),"-"),"") -> 46387 | O55: =IF(F56<=TODAY(),C55,"0") -> 0 | P55: =IF(F56<=TODAY(),D55,"0") -> 0 | Q55: =IF(F56<=TODAY(),F56,"0") -> 0 | R55: =IF(F56<=TODAY(),F57,0) -> 0 | S55: =IF(G56<=TODAY(),G57,0) -> 0 | T55: =IF(H56<=TODAY(),H57,0) -> 0 | U55: =IF(I56<=TODAY(),I57,0) -> 0 | V55: =IF(J56<=TODAY(),J57,0) -> 0 | W55: =IF(L56<=TODAY(),L57,0) -> 0 | X55: =IF(K56<=TODAY(),K57,"-") -> 0 | Z55: =C55 -> 17 | AA55: =D55 -> Company 17 | AB55: =F56 -> 44792 | AC55: =IF(F56>TODAY(),F57,"0") -> 1250000 | AD55: =IF(G56>TODAY(),G57,"0") -> 112500 | AE55: =IF(H56>TODAY(),H57,"0") -> 937500 | AF55: =IF(I56>TODAY(),I57,"0") -> 750000 | AG55: =IF(J56>TODAY(),J57,"0") -> 0 | AH55: =IF(L56>TODAY(),L57,"0") -> 0
E56: Date | F56: =IF(C55<=$H$3,IF((F53+('Summary and Assumptions'!$K$118*7))>$D$3,(F53+('Summary and Assumptions'!$K$118*7)),($D$3+$H$4)),"") -> 44792 | G56: =IF($C55<=$H$3,IF((F56+('Summary and Assumptions'!$K$119*7))>$D$3,(F56+('Summary and Assumptions'!$K$119*7)),($D$3+$H$4)),"") -> 45247 | H56: =IF($C55<=$H$3,IF((F56+('Summary and Assumptions'!$K$120*7))>$D$3,(F56+('Summary and Assumptions'!$K$120*7)),($D$3+$H$4)),"") -> 45317 | I56: =IF($C55<=$H$3,IF((H56+('Summary and Assumptions'!$K$121*7))>$D$3,(H56+('Summary and Assumptions'!$K$121*7)),($D$3+$H$4)),"") -> 45849 | J56: =IF($C55<=$H$3,IF((I56+('Summary and Assumptions'!$K$122*7))>$D$3,(I56+('Summary and Assumptions'!$K$122*7)),($D$3+$H$4)),"") -> 46297 | L56: =IF($C55<=$H$3,IF((J56+('Summary and Assumptions'!$K$123*7))>$D$3,(J56+('Summary and Assumptions'!$K$123*7)),($D$3+$H$4)),"") -> 46297
E57: Amount | F57: =IF(C55<=$H$3,'Summary and Assumptions'!$D$101,"") -> 1250000 | G57: =IF(C55<=$H$3,F57*'Summary and Assumptions'!$K$111*'Summary and Assumptions'!$K$102,"") -> 112500 | H57: =IF(C55<=$H$3,$F57*'Summary and Assumptions'!$K$112*'Summary and Assumptions'!$K$103,"") -> 937500 | I57: =IF(C55<=$H$3,$F57*'Summary and Assumptions'!$K$113*'Summary and Assumptions'!$K$104,"") -> 750000 | J57: =IF(C55<=$H$3,$F57*'Summary and Assumptions'!$K$114*'Summary and Assumptions'!$K$105,"") -> 0 | K57: =IF(AND(J56<=$D$3,J57>0),$J$6,IF(AND(I56<=$D$3,I57>0),$I$6,IF(AND(H56<=$D$3,H57>0),$H$6,IF(AND(G56<=$D$3,G57>0),$G$6,IF(AND(F56<=$D$3,F57>0),$F$6,"0"))))) -> 0 | L57: =IF(C55<=$H$3,SUM($F57:$I57)*(1+'Summary and Assumptions'!$D$103),"") -> 0
B58: F | C58: =C55+1 -> 18 | D58: =IF(C58<=$H$3,"Company"&" "&C58,"") -> Company 18 | E58: FQ End Date | F58: =IFERROR(IF(F59>0,(DATE(YEAR(F59),((INT((MONTH(F59)-1)/3)+1)*3)+1,1)-1),"-"),"NA") -> 44834 | G58: =IFERROR(IF(G59>0,(DATE(YEAR(G59),((INT((MONTH(G59)-1)/3)+1)*3)+1,1)-1),"-"),"NA") -> 45291 | H58: =IFERROR(IF(H59>0,(DATE(YEAR(H59),((INT((MONTH(H59)-1)/3)+1)*3)+1,1)-1),"-"),"NA") -> 45382 | I58: =IFERROR(IF(I59>0,(DATE(YEAR(I59),((INT((MONTH(I59)-1)/3)+1)*3)+1,1)-1),"-"),"NA") -> 45930 | J58: =IFERROR(IF(J59>0,(DATE(YEAR(J59),((INT((MONTH(J59)-1)/3)+1)*3)+1,1)-1),"-"),"NA") -> 46387 | L58: =IFERROR(IF(L59>0,(DATE(YEAR(L59),((INT((MONTH(L59)-1)/3)+1)*3)+1,1)-1),"-"),"") -> 46387 | O58: =IF(F59<=TODAY(),C58,"0") -> 0 | P58: =IF(F59<=TODAY(),D58,"0") -> 0 | Q58: =IF(F59<=TODAY(),F59,"0") -> 0 | R58: =IF(F59<=TODAY(),F60,0) -> 0 | S58: =IF(G59<=TODAY(),G60,0) -> 0 | T58: =IF(H59<=TODAY(),H60,0) -> 0 | U58: =IF(I59<=TODAY(),I60,0) -> 0 | V58: =IF(J59<=TODAY(),J60,0) -> 0 | W58: =IF(L59<=TODAY(),L60,0) -> 0 | X58: =IF(K59<=TODAY(),K60,"-") -> 0 | Z58: =C58 -> 18 | AA58: =D58 -> Company 18 | AB58: =F59 -> 44827 | AC58: =IF(F59>TODAY(),F60,"0") -> 1250000 | AD58: =IF(G59>TODAY(),G60,"0") -> 112500 | AE58: =IF(H59>TODAY(),H60,"0") -> 937500 | AF58: =IF(I59>TODAY(),I60,"0") -> 750000 | AG58: =IF(J59>TODAY(),J60,"0") -> 0 | AH58: =IF(L59>TODAY(),L60,"0") -> 0
E59: Date | F59: =IF(C58<=$H$3,IF((F56+('Summary and Assumptions'!$K$118*7))>$D$3,(F56+('Summary and Assumptions'!$K$118*7)),($D$3+$H$4)),"") -> 44827 | G59: =IF($C58<=$H$3,IF((F59+('Summary and Assumptions'!$K$119*7))>$D$3,(F59+('Summary and Assumptions'!$K$119*7)),($D$3+$H$4)),"") -> 45282 | H59: =IF($C58<=$H$3,IF((F59+('Summary and Assumptions'!$K$120*7))>$D$3,(F59+('Summary and Assumptions'!$K$120*7)),($D$3+$H$4)),"") -> 45352 | I59: =IF($C58<=$H$3,IF((H59+('Summary and Assumptions'!$K$121*7))>$D$3,(H59+('Summary and Assumptions'!$K$121*7)),($D$3+$H$4)),"") -> 45884 | J59: =IF($C58<=$H$3,IF((I59+('Summary and Assumptions'!$K$122*7))>$D$3,(I59+('Summary and Assumptions'!$K$122*7)),($D$3+$H$4)),"") -> 46332 | L59: =IF($C58<=$H$3,IF((J59+('Summary and Assumptions'!$K$123*7))>$D$3,(J59+('Summary and Assumptions'!$K$123*7)),($D$3+$H$4)),"") -> 46332
E60: Amount | F60: =IF(C58<=$H$3,'Summary and Assumptions'!$D$101,"") -> 1250000 | G60: =IF(C58<=$H$3,F60*'Summary and Assumptions'!$K$111*'Summary and Assumptions'!$K$102,"") -> 112500 | H60: =IF(C58<=$H$3,$F60*'Summary and Assumptions'!$K$112*'Summary and Assumptions'!$K$103,"") -> 937500 | I60: =IF(C58<=$H$3,$F60*'Summary and Assumptions'!$K$113*'Summary and Assumptions'!$K$104,"") -> 750000 | J60: =IF(C58<=$H$3,$F60*'Summary and Assumptions'!$K$114*'Summary and Assumptions'!$K$105,"") -> 0 | K60: =IF(AND(J59<=$D$3,J60>0),$J$6,IF(AND(I59<=$D$3,I60>0),$I$6,IF(AND(H59<=$D$3,H60>0),$H$6,IF(AND(G59<=$D$3,G60>0),$G$6,IF(AND(F59<=$D$3,F60>0),$F$6,"0"))))) -> 0 | L60: =IF(C58<=$H$3,SUM($F60:$I60)*(1+'Summary and Assumptions'!$D$103),"") -> 0
B61: F | C61: =C58+1 -> 19 | D61: =IF(C61<=$H$3,"Company"&" "&C61,"") -> Company 19 | E61: FQ End Date | F61: =IFERROR(IF(F62>0,(DATE(YEAR(F62),((INT((MONTH(F62)-1)/3)+1)*3)+1,1)-1),"-"),"NA") -> 44926 | G61: =IFERROR(IF(G62>0,(DATE(YEAR(G62),((INT((MONTH(G62)-1)/3)+1)*3)+1,1)-1),"-"),"NA") -> 45382 | H61: =IFERROR(IF(H62>0,(DATE(YEAR(H62),((INT((MONTH(H62)-1)/3)+1)*3)+1,1)-1),"-"),"NA") -> 45473 | I61: =IFERROR(IF(I62>0,(DATE(YEAR(I62),((INT((MONTH(I62)-1)/3)+1)*3)+1,1)-1),"-"),"NA") -> 45930 | J61: =IFERROR(IF(J62>0,(DATE(YEAR(J62),((INT((MONTH(J62)-1)/3)+1)*3)+1,1)-1),"-"),"NA") -> 46387 | L61: =IFERROR(IF(L62>0,(DATE(YEAR(L62),((INT((MONTH(L62)-1)/3)+1)*3)+1,1)-1),"-"),"") -> 46387 | O61: =IF(F62<=TODAY(),C61,"0") -> 0 | P61: =IF(F62<=TODAY(),D61,"0") -> 0 | Q61: =IF(F62<=TODAY(),F62,"0") -> 0 | R61: =IF(F62<=TODAY(),F63,0) -> 0 | S61: =IF(G62<=TODAY(),G63,0) -> 0 | T61: =IF(H62<=TODAY(),H63,0) -> 0 | U61: =IF(I62<=TODAY(),I63,0) -> 0 | V61: =IF(J62<=TODAY(),J63,0) -> 0 | W61: =IF(L62<=TODAY(),L63,0) -> 0 | X61: =IF(K62<=TODAY(),K63,"-") -> 0 | Z61: =C61 -> 19 | AA61: =D61 -> Company 19 | AB61: =F62 -> 44862 | AC61: =IF(F62>TODAY(),F63,"0") -> 1250000 | AD61: =IF(G62>TODAY(),G63,"0") -> 112500 | AE61: =IF(H62>TODAY(),H63,"0") -> 937500 | AF61: =IF(I62>TODAY(),I63,"0") -> 750000 | AG61: =IF(J62>TODAY(),J63,"0") -> 0 | AH61: =IF(L62>TODAY(),L63,"0") -> 0
E62: Date | F62: =IF(C61<=$H$3,IF((F59+('Summary and Assumptions'!$K$118*7))>$D$3,(F59+('Summary and Assumptions'!$K$118*7)),($D$3+$H$4)),"") -> 44862 | G62: =IF($C61<=$H$3,IF((F62+('Summary and Assumptions'!$K$119*7))>$D$3,(F62+('Summary and Assumptions'!$K$119*7)),($D$3+$H$4)),"") -> 45317 | H62: =IF($C61<=$H$3,IF((F62+('Summary and Assumptions'!$K$120*7))>$D$3,(F62+('Summary and Assumptions'!$K$120*7)),($D$3+$H$4)),"") -> 45387 | I62: =IF($C61<=$H$3,IF((H62+('Summary and Assumptions'!$K$121*7))>$D$3,(H62+('Summary and Assumptions'!$K$121*7)),($D$3+$H$4)),"") -> 45919 | J62: =IF($C61<=$H$3,IF((I62+('Summary and Assumptions'!$K$122*7))>$D$3,(I62+('Summary and Assumptions'!$K$122*7)),($D$3+$H$4)),"") -> 46367 | L62: =IF($C61<=$H$3,IF((J62+('Summary and Assumptions'!$K$123*7))>$D$3,(J62+('Summary and Assumptions'!$K$123*7)),($D$3+$H$4)),"") -> 46367
E63: Amount | F63: =IF(C61<=$H$3,'Summary and Assumptions'!$D$101,"") -> 1250000 | G63: =IF(C61<=$H$3,F63*'Summary and Assumptions'!$K$111*'Summary and Assumptions'!$K$102,"") -> 112500 | H63: =IF(C61<=$H$3,$F63*'Summary and Assumptions'!$K$112*'Summary and Assumptions'!$K$103,"") -> 937500 | I63: =IF(C61<=$H$3,$F63*'Summary and Assumptions'!$K$113*'Summary and Assumptions'!$K$104,"") -> 750000 | J63: =IF(C61<=$H$3,$F63*'Summary and Assumptions'!$K$114*'Summary and Assumptions'!$K$105,"") -> 0 | K63: =IF(AND(J62<=$D$3,J63>0),$J$6,IF(AND(I62<=$D$3,I63>0),$I$6,IF(AND(H62<=$D$3,H63>0),$H$6,IF(AND(G62<=$D$3,G63>0),$G$6,IF(AND(F62<=$D$3,F63>0),$F$6,"0"))))) -> 0 | L63: =IF(C61<=$H$3,SUM($F63:$I63)*(1+'Summary and Assumptions'!$D$103),"") -> 0
B64: F | C64: =C61+1 -> 20 | D64: =IF(C64<=$H$3,"Company"&" "&C64,"") -> Company 20 | E64: FQ End Date | F64: =IFERROR(IF(F65>0,(DATE(YEAR(F65),((INT((MONTH(F65)-1)/3)+1)*3)+1,1)-1),"-"),"NA") -> 44926 | G64: =IFERROR(IF(G65>0,(DATE(YEAR(G65),((INT((MONTH(G65)-1)/3)+1)*3)+1,1)-1),"-"),"NA") -> 45382 | H64: =IFERROR(IF(H65>0,(DATE(YEAR(H65),((INT((MONTH(H65)-1)/3)+1)*3)+1,1)-1),"-"),"NA") -> 45473 | I64: =IFERROR(IF(I65>0,(DATE(YEAR(I65),((INT((MONTH(I65)-1)/3)+1)*3)+1,1)-1),"-"),"NA") -> 46022 | J64: =IFERROR(IF(J65>0,(DATE(YEAR(J65),((INT((MONTH(J65)-1)/3)+1)*3)+1,1)-1),"-"),"NA") -> 46477 | L64: =IFERROR(IF(L65>0,(DATE(YEAR(L65),((INT((MONTH(L65)-1)/3)+1)*3)+1,1)-1),"-"),"") -> 46477 | O64: =IF(F65<=TODAY(),C64,"0") -> 0 | P64: =IF(F65<=TODAY(),D64,"0") -> 0 | Q64: =IF(F65<=TODAY(),F65,"0") -> 0 | R64: =IF(F65<=TODAY(),F66,0) -> 0 | S64: =IF(G65<=TODAY(),G66,0) -> 0 | T64: =IF(H65<=TODAY(),H66,0) -> 0 | U64: =IF(I65<=TODAY(),I66,0) -> 0 | V64: =IF(J65<=TODAY(),J66,0) -> 0 | W64: =IF(L65<=TODAY(),L66,0) -> 0 | X64: =IF(K65<=TODAY(),K66,"-") -> 0 | Z64: =C64 -> 20 | AA64: =D64 -> Company 20 | AB64: =F65 -> 44897 | AC64: =IF(F65>TODAY(),F66,"0") -> 1250000 | AD64: =IF(G65>TODAY(),G66,"0") -> 112500 | AE64: =IF(H65>TODAY(),H66,"0") -> 937500 | AF64: =IF(I65>TODAY(),I66,"0") -> 750000 | AG64: =IF(J65>TODAY(),J66,"0") -> 0 | AH64: =IF(L65>TODAY(),L66,"0") -> 0
E65: Date | F65: =IF(C64<=$H$3,IF((F62+('Summary and Assumptions'!$K$118*7))>$D$3,(F62+('Summary and Assumptions'!$K$118*7)),($D$3+$H$4)),"") -> 44897 | G65: =IF($C64<=$H$3,IF((F65+('Summary and Assumptions'!$K$119*7))>$D$3,(F65+('Summary and Assumptions'!$K$119*7)),($D$3+$H$4)),"") -> 45352 | H65: =IF($C64<=$H$3,IF((F65+('Summary and Assumptions'!$K$120*7))>$D$3,(F65+('Summary and Assumptions'!$K$120*7)),($D$3+$H$4)),"") -> 45422 | I65: =IF($C64<=$H$3,IF((H65+('Summary and Assumptions'!$K$121*7))>$D$3,(H65+('Summary and Assumptions'!$K$121*7)),($D$3+$H$4)),"") -> 45954 | J65: =IF($C64<=$H$3,IF((I65+('Summary and Assumptions'!$K$122*7))>$D$3,(I65+('Summary and Assumptions'!$K$122*7)),($D$3+$H$4)),"") -> 46402 | L65: =IF($C64<=$H$3,IF((J65+('Summary and Assumptions'!$K$123*7))>$D$3,(J65+('Summary and Assumptions'!$K$123*7)),($D$3+$H$4)),"") -> 46402
E66: Amount | F66: =IF(C64<=$H$3,'Summary and Assumptions'!$D$101,"") -> 1250000 | G66: =IF(C64<=$H$3,F66*'Summary and Assumptions'!$K$111*'Summary and Assumptions'!$K$102,"") -> 112500 | H66: =IF(C64<=$H$3,$F66*'Summary and Assumptions'!$K$112*'Summary and Assumptions'!$K$103,"") -> 937500 | I66: =IF(C64<=$H$3,$F66*'Summary and Assumptions'!$K$113*'Summary and Assumptions'!$K$104,"") -> 750000 | J66: =IF(C64<=$H$3,$F66*'Summary and Assumptions'!$K$114*'Summary and Assumptions'!$K$105,"") -> 0 | K66: =IF(AND(J65<=$D$3,J66>0),$J$6,IF(AND(I65<=$D$3,I66>0),$I$6,IF(AND(H65<=$D$3,H66>0),$H$6,IF(AND(G65<=$D$3,G66>0),$G$6,IF(AND(F65<=$D$3,F66>0),$F$6,"0"))))) -> 0 | L66: =IF(C64<=$H$3,SUM($F66:$I66)*(1+'Summary and Assumptions'!$D$103),"") -> 0
B67: F | C67: =C64+1 -> 21 | D67: =IF(C67<=$H$3,"Company"&" "&C67,"") -> Company 21 | E67: FQ End Date | F67: =IFERROR(IF(F68>0,(DATE(YEAR(F68),((INT((MONTH(F68)-1)/3)+1)*3)+1,1)-1),"-"),"NA") -> 45016 | G67: =IFERROR(IF(G68>0,(DATE(YEAR(G68),((INT((MONTH(G68)-1)/3)+1)*3)+1,1)-1),"-"),"NA") -> 45473 | H67: =IFERROR(IF(H68>0,(DATE(YEAR(H68),((INT((MONTH(H68)-1)/3)+1)*3)+1,1)-1),"-"),"NA") -> 45473 | I67: =IFERROR(IF(I68>0,(DATE(YEAR(I68),((INT((MONTH(I68)-1)/3)+1)*3)+1,1)-1),"-"),"NA") -> 46022 | J67: =IFERROR(IF(J68>0,(DATE(YEAR(J68),((INT((MONTH(J68)-1)/3)+1)*3)+1,1)-1),"-"),"NA") -> 46477 | L67: =IFERROR(IF(L68>0,(DATE(YEAR(L68),((INT((MONTH(L68)-1)/3)+1)*3)+1,1)-1),"-"),"") -> 46477 | O67: =IF(F68<=TODAY(),C67,"0") -> 0 | P67: =IF(F68<=TODAY(),D67,"0") -> 0 | Q67: =IF(F68<=TODAY(),F68,"0") -> 0 | R67: =IF(F68<=TODAY(),F69,0) -> 0 | S67: =IF(G68<=TODAY(),G69,0) -> 0 | T67: =IF(H68<=TODAY(),H69,0) -> 0 | U67: =IF(I68<=TODAY(),I69,0) -> 0 | V67: =IF(J68<=TODAY(),J69,0) -> 0 | W67: =IF(L68<=TODAY(),L69,0) -> 0 | X67: =IF(K68<=TODAY(),K69,"-") -> 0 | Z67: =IF(F68>TODAY(),C67,"0") -> 21 | AA67: =IF(F68>TODAY(),D67,"0") -> Company 21 | AB67: =IF(F68>TODAY(),F68,"0") -> 44932 | AC67: =IF(F68>TODAY(),F69,"0") -> 1250000 | AD67: =IF(G68>TODAY(),G69,"0") -> 112500 | AE67: =IF(H68>TODAY(),H69,"0") -> 937500 | AF67: =IF(I68>TODAY(),I69,"0") -> 750000 | AG67: =IF(J68>TODAY(),J69,"0") -> 0 | AH67: =IF(L68>TODAY(),L69,"0") -> 0
E68: Date | F68: =IF(C67<=$H$3,IF((F65+('Summary and Assumptions'!$K$118*7))>$D$3,(F65+('Summary and Assumptions'!$K$118*7)),($D$3+$H$4)),"") -> 44932 | G68: =IF($C67<=$H$3,IF((F68+('Summary and Assumptions'!$K$119*7))>$D$3,(F68+('Summary and Assumptions'!$K$119*7)),($D$3+$H$4)),"") -> 45387 | H68: =IF($C67<=$H$3,IF((F68+('Summary and Assumptions'!$K$120*7))>$D$3,(F68+('Summary and Assumptions'!$K$120*7)),($D$3+$H$4)),"") -> 45457 | I68: =IF($C67<=$H$3,IF((H68+('Summary and Assumptions'!$K$121*7))>$D$3,(H68+('Summary and Assumptions'!$K$121*7)),($D$3+$H$4)),"") -> 45989 | J68: =IF($C67<=$H$3,IF((I68+('Summary and Assumptions'!$K$122*7))>$D$3,(I68+('Summary and Assumptions'!$K$122*7)),($D$3+$H$4)),"") -> 46437 | L68: =IF($C67<=$H$3,IF((J68+('Summary and Assumptions'!$K$123*7))>$D$3,(J68+('Summary and Assumptions'!$K$123*7)),($D$3+$H$4)),"") -> 46437
E69: Amount | F69: =IF(C67<=$H$3,'Summary and Assumptions'!$D$101,"") -> 1250000 | G69: =IF(C67<=$H$3,F69*'Summary and Assumptions'!$K$111*'Summary and Assumptions'!$K$102,"") -> 112500 | H69: =IF(C67<=$H$3,$F69*'Summary and Assumptions'!$K$112*'Summary and Assumptions'!$K$103,"") -> 937500 | I69: =IF(C67<=$H$3,$F69*'Summary and Assumptions'!$K$113*'Summary and Assumptions'!$K$104,"") -> 750000 | J69: =IF(C67<=$H$3,$F69*'Summary and Assumptions'!$K$114*'Summary and Assumptions'!$K$105,"") -> 0 | K69: =IF(AND(J68<=$D$3,J69>0),$J$6,IF(AND(I68<=$D$3,I69>0),$I$6,IF(AND(H68<=$D$3,H69>0),$H$6,IF(AND(G68<=$D$3,G69>0),$G$6,IF(AND(F68<=$D$3,F69>0),$F$6,"0"))))) -> 0 | L69: =IF(C67<=$H$3,SUM($F69:$I69)*(1+'Summary and Assumptions'!$D$103),"") -> 0
B70: F | C70: =C67+1 -> 22 | D70: =IF(C70<=$H$3,"Company"&" "&C70,"") -> Company 22 | E70: FQ End Date | F70: =IFERROR(IF(F71>0,(DATE(YEAR(F71),((INT((MONTH(F71)-1)/3)+1)*3)+1,1)-1),"-"),"NA") -> 45016 | G70: =IFERROR(IF(G71>0,(DATE(YEAR(G71),((INT((MONTH(G71)-1)/3)+1)*3)+1,1)-1),"-"),"NA") -> 45473 | H70: =IFERROR(IF(H71>0,(DATE(YEAR(H71),((INT((MONTH(H71)-1)/3)+1)*3)+1,1)-1),"-"),"NA") -> 45565 | I70: =IFERROR(IF(I71>0,(DATE(YEAR(I71),((INT((MONTH(I71)-1)/3)+1)*3)+1,1)-1),"-"),"NA") -> 46112 | J70: =IFERROR(IF(J71>0,(DATE(YEAR(J71),((INT((MONTH(J71)-1)/3)+1)*3)+1,1)-1),"-"),"NA") -> 46477 | L70: =IFERROR(IF(L71>0,(DATE(YEAR(L71),((INT((MONTH(L71)-1)/3)+1)*3)+1,1)-1),"-"),"") -> 46477 | O70: =IF(F71<=TODAY(),C70,"0") -> 0 | P70: =IF(F71<=TODAY(),D70,"0") -> 0 | Q70: =IF(F71<=TODAY(),F71,"0") -> 0 | R70: =IF(F71<=TODAY(),F72,0) -> 0 | S70: =IF(G71<=TODAY(),G72,0) -> 0 | T70: =IF(H71<=TODAY(),H72,0) -> 0 | U70: =IF(I71<=TODAY(),I72,0) -> 0 | V70: =IF(J71<=TODAY(),J72,0) -> 0 | W70: =IF(L71<=TODAY(),L72,0) -> 0 | X70: =IF(K71<=TODAY(),K72,"-") -> 0 | Z70: =IF(F71>TODAY(),C70,"0") -> 22 | AA70: =IF(F71>TODAY(),D70,"0") -> Company 22 | AB70: =IF(F71>TODAY(),F71,"0") -> 44967 | AC70: =IF(F71>TODAY(),F72,"0") -> 1250000 | AD70: =IF(G71>TODAY(),G72,"0") -> 112500 | AE70: =IF(H71>TODAY(),H72,"0") -> 937500 | AF70: =IF(I71>TODAY(),I72,"0") -> 750000 | AG70: =IF(J71>TODAY(),J72,"0") -> 0 | AH70: =IF(L71>TODAY(),L72,"0") -> 0
E71: Date | F71: =IF(C70<=$H$3,IF((F68+('Summary and Assumptions'!$K$118*7))>$D$3,(F68+('Summary and Assumptions'!$K$118*7)),($D$3+$H$4)),"") -> 44967 | G71: =IF($C70<=$H$3,IF((F71+('Summary and Assumptions'!$K$119*7))>$D$3,(F71+('Summary and Assumptions'!$K$119*7)),($D$3+$H$4)),"") -> 45422 | H71: =IF($C70<=$H$3,IF((F71+('Summary and Assumptions'!$K$120*7))>$D$3,(F71+('Summary and Assumptions'!$K$120*7)),($D$3+$H$4)),"") -> 45492 | I71: =IF($C70<=$H$3,IF((H71+('Summary and Assumptions'!$K$121*7))>$D$3,(H71+('Summary and Assumptions'!$K$121*7)),($D$3+$H$4)),"") -> 46024 | J71: =IF($C70<=$H$3,IF((I71+('Summary and Assumptions'!$K$122*7))>$D$3,(I71+('Summary and Assumptions'!$K$122*7)),($D$3+$H$4)),"") -> 46472 | L71: =IF($C70<=$H$3,IF((J71+('Summary and Assumptions'!$K$123*7))>$D$3,(J71+('Summary and Assumptions'!$K$123*7)),($D$3+$H$4)),"") -> 46472
E72: Amount | F72: =IF(C70<=$H$3,'Summary and Assumptions'!$D$101,"") -> 1250000 | G72: =IF(C70<=$H$3,F72*'Summary and Assumptions'!$K$111*'Summary and Assumptions'!$K$102,"") -> 112500 | H72: =IF(C70<=$H$3,$F72*'Summary and Assumptions'!$K$112*'Summary and Assumptions'!$K$103,"") -> 937500 | I72: =IF(C70<=$H$3,$F72*'Summary and Assumptions'!$K$113*'Summary and Assumptions'!$K$104,"") -> 750000 | J72: =IF(C70<=$H$3,$F72*'Summary and Assumptions'!$K$114*'Summary and Assumptions'!$K$105,"") -> 0 | K72: =IF(AND(J71<=$D$3,J72>0),$J$6,IF(AND(I71<=$D$3,I72>0),$I$6,IF(AND(H71<=$D$3,H72>0),$H$6,IF(AND(G71<=$D$3,G72>0),$G$6,IF(AND(F71<=$D$3,F72>0),$F$6,"0"))))) -> 0 | L72: =IF(C70<=$H$3,SUM($F72:$I72)*(1+'Summary and Assumptions'!$D$103),"") -> 0
B73: F | C73: =C70+1 -> 23 | D73: =IF(C73<=$H$3,"Company"&" "&C73,"") -> Company 23 | E73: FQ End Date | F73: =IFERROR(IF(F74>0,(DATE(YEAR(F74),((INT((MONTH(F74)-1)/3)+1)*3)+1,1)-1),"-"),"NA") -> 45016 | G73: =IFERROR(IF(G74>0,(DATE(YEAR(G74),((INT((MONTH(G74)-1)/3)+1)*3)+1,1)-1),"-"),"NA") -> 45473 | H73: =IFERROR(IF(H74>0,(DATE(YEAR(H74),((INT((MONTH(H74)-1)/3)+1)*3)+1,1)-1),"-"),"NA") -> 45565 | I73: =IFERROR(IF(I74>0,(DATE(YEAR(I74),((INT((MONTH(I74)-1)/3)+1)*3)+1,1)-1),"-"),"NA") -> 46112 | J73: =IFERROR(IF(J74>0,(DATE(YEAR(J74),((INT((MONTH(J74)-1)/3)+1)*3)+1,1)-1),"-"),"NA") -> 46568 | L73: =IFERROR(IF(L74>0,(DATE(YEAR(L74),((INT((MONTH(L74)-1)/3)+1)*3)+1,1)-1),"-"),"") -> 46568 | O73: =IF(F74<=TODAY(),C73,"0") -> 0 | P73: =IF(F74<=TODAY(),D73,"0") -> 0 | Q73: =IF(F74<=TODAY(),F74,"0") -> 0 | R73: =IF(F74<=TODAY(),F75,0) -> 0 | S73: =IF(G74<=TODAY(),G75,0) -> 0 | T73: =IF(H74<=TODAY(),H75,0) -> 0 | U73: =IF(I74<=TODAY(),I75,0) -> 0 | V73: =IF(J74<=TODAY(),J75,0) -> 0 | W73: =IF(L74<=TODAY(),L75,0) -> 0 | X73: =IF(K74<=TODAY(),K75,"-") -> 0 | Z73: =IF(F74>TODAY(),C73,"0") -> 23 | AA73: =IF(F74>TODAY(),D73,"0") -> Company 23 | AB73: =IF(F74>TODAY(),F74,"0") -> 45002 | AC73: =IF(F74>TODAY(),F75,"0") -> 1250000 | AD73: =IF(G74>TODAY(),G75,"0") -> 112500 | AE73: =IF(H74>TODAY(),H75,"0") -> 937500 | AF73: =IF(I74>TODAY(),I75,"0") -> 750000 | AG73: =IF(J74>TODAY(),J75,"0") -> 0 | AH73: =IF(L74>TODAY(),L75,"0") -> 0
E74: Date | F74: =IF(C73<=$H$3,IF((F71+('Summary and Assumptions'!$K$118*7))>$D$3,(F71+('Summary and Assumptions'!$K$118*7)),($D$3+$H$4)),"") -> 45002 | G74: =IF($C73<=$H$3,IF((F74+('Summary and Assumptions'!$K$119*7))>$D$3,(F74+('Summary and Assumptions'!$K$119*7)),($D$3+$H$4)),"") -> 45457 | H74: =IF($C73<=$H$3,IF((F74+('Summary and Assumptions'!$K$120*7))>$D$3,(F74+('Summary and Assumptions'!$K$120*7)),($D$3+$H$4)),"") -> 45527 | I74: =IF($C73<=$H$3,IF((H74+('Summary and Assumptions'!$K$121*7))>$D$3,(H74+('Summary and Assumptions'!$K$121*7)),($D$3+$H$4)),"") -> 46059 | J74: =IF($C73<=$H$3,IF((I74+('Summary and Assumptions'!$K$122*7))>$D$3,(I74+('Summary and Assumptions'!$K$122*7)),($D$3+$H$4)),"") -> 46507 | L74: =IF($C73<=$H$3,IF((J74+('Summary and Assumptions'!$K$123*7))>$D$3,(J74+('Summary and Assumptions'!$K$123*7)),($D$3+$H$4)),"") -> 46507
E75: Amount | F75: =IF(C73<=$H$3,'Summary and Assumptions'!$D$101,"") -> 1250000 | G75: =IF(C73<=$H$3,F75*'Summary and Assumptions'!$K$111*'Summary and Assumptions'!$K$102,"") -> 112500 | H75: =IF(C73<=$H$3,$F75*'Summary and Assumptions'!$K$112*'Summary and Assumptions'!$K$103,"") -> 937500 | I75: =IF(C73<=$H$3,$F75*'Summary and Assumptions'!$K$113*'Summary and Assumptions'!$K$104,"") -> 750000 | J75: =IF(C73<=$H$3,$F75*'Summary and Assumptions'!$K$114*'Summary and Assumptions'!$K$105,"") -> 0 | K75: =IF(AND(J74<=$D$3,J75>0),$J$6,IF(AND(I74<=$D$3,I75>0),$I$6,IF(AND(H74<=$D$3,H75>0),$H$6,IF(AND(G74<=$D$3,G75>0),$G$6,IF(AND(F74<=$D$3,F75>0),$F$6,"0"))))) -> 0 | L75: =IF(C73<=$H$3,SUM($F75:$I75)*(1+'Summary and Assumptions'!$D$103),"") -> 0
B76: F | C76: =C73+1 -> 24 | D76: =IF(C76<=$H$3,"Company"&" "&C76,"") -> Company 24 | E76: FQ End Date | F76: =IFERROR(IF(F77>0,(DATE(YEAR(F77),((INT((MONTH(F77)-1)/3)+1)*3)+1,1)-1),"-"),"NA") -> 45107 | G76: =IFERROR(IF(G77>0,(DATE(YEAR(G77),((INT((MONTH(G77)-1)/3)+1)*3)+1,1)-1),"-"),"NA") -> 45565 | H76: =IFERROR(IF(H77>0,(DATE(YEAR(H77),((INT((MONTH(H77)-1)/3)+1)*3)+1,1)-1),"-"),"NA") -> 45565 | I76: =IFERROR(IF(I77>0,(DATE(YEAR(I77),((INT((MONTH(I77)-1)/3)+1)*3)+1,1)-1),"-"),"NA") -> 46112 | J76: =IFERROR(IF(J77>0,(DATE(YEAR(J77),((INT((MONTH(J77)-1)/3)+1)*3)+1,1)-1),"-"),"NA") -> 46568 | L76: =IFERROR(IF(L77>0,(DATE(YEAR(L77),((INT((MONTH(L77)-1)/3)+1)*3)+1,1)-1),"-"),"") -> 46568 | O76: =IF(F77<=TODAY(),C76,"0") -> 0 | P76: =IF(F77<=TODAY(),D76,"0") -> 0 | Q76: =IF(F77<=TODAY(),F77,"0") -> 0 | R76: =IF(F77<=TODAY(),F78,0) -> 0 | S76: =IF(G77<=TODAY(),G78,0) -> 0 | T76: =IF(H77<=TODAY(),H78,0) -> 0 | U76: =IF(I77<=TODAY(),I78,0) -> 0 | V76: =IF(J77<=TODAY(),J78,0) -> 0 | W76: =IF(L77<=TODAY(),L78,0) -> 0 | X76: =IF(K77<=TODAY(),K78,"-") -> 0 | Z76: =IF(F77>TODAY(),C76,"0") -> 24 | AA76: =IF(F77>TODAY(),D76,"0") -> Company 24 | AB76: =IF(F77>TODAY(),F77,"0") -> 45037 | AC76: =IF(F77>TODAY(),F78,"0") -> 1250000 | AD76: =IF(G77>TODAY(),G78,"0") -> 112500 | AE76: =IF(H77>TODAY(),H78,"0") -> 937500 | AF76: =IF(I77>TODAY(),I78,"0") -> 750000 | AG76: =IF(J77>TODAY(),J78,"0") -> 0 | AH76: =IF(L77>TODAY(),L78,"0") -> 0
E77: Date | F77: =IF(C76<=$H$3,IF((F74+('Summary and Assumptions'!$K$118*7))>$D$3,(F74+('Summary and Assumptions'!$K$118*7)),($D$3+$H$4)),"") -> 45037 | G77: =IF($C76<=$H$3,IF((F77+('Summary and Assumptions'!$K$119*7))>$D$3,(F77+('Summary and Assumptions'!$K$119*7)),($D$3+$H$4)),"") -> 45492 | H77: =IF($C76<=$H$3,IF((F77+('Summary and Assumptions'!$K$120*7))>$D$3,(F77+('Summary and Assumptions'!$K$120*7)),($D$3+$H$4)),"") -> 45562 | I77: =IF($C76<=$H$3,IF((H77+('Summary and Assumptions'!$K$121*7))>$D$3,(H77+('Summary and Assumptions'!$K$121*7)),($D$3+$H$4)),"") -> 46094 | J77: =IF($C76<=$H$3,IF((I77+('Summary and Assumptions'!$K$122*7))>$D$3,(I77+('Summary and Assumptions'!$K$122*7)),($D$3+$H$4)),"") -> 46542 | L77: =IF($C76<=$H$3,IF((J77+('Summary and Assumptions'!$K$123*7))>$D$3,(J77+('Summary and Assumptions'!$K$123*7)),($D$3+$H$4)),"") -> 46542
E78: Amount | F78: =IF(C76<=$H$3,'Summary and Assumptions'!$D$101,"") -> 1250000 | G78: =IF(C76<=$H$3,F78*'Summary and Assumptions'!$K$111*'Summary and Assumptions'!$K$102,"") -> 112500 | H78: =IF(C76<=$H$3,$F78*'Summary and Assumptions'!$K$112*'Summary and Assumptions'!$K$103,"") -> 937500 | I78: =IF(C76<=$H$3,$F78*'Summary and Assumptions'!$K$113*'Summary and Assumptions'!$K$104,"") -> 750000 | J78: =IF(C76<=$H$3,$F78*'Summary and Assumptions'!$K$114*'Summary and Assumptions'!$K$105,"") -> 0 | K78: =IF(AND(J77<=$D$3,J78>0),$J$6,IF(AND(I77<=$D$3,I78>0),$I$6,IF(AND(H77<=$D$3,H78>0),$H$6,IF(AND(G77<=$D$3,G78>0),$G$6,IF(AND(F77<=$D$3,F78>0),$F$6,"0"))))) -> 0 | L78: =IF(C76<=$H$3,SUM($F78:$I78)*(1+'Summary and Assumptions'!$D$103),"") -> 0
B79: F | C79: =C76+1 -> 25 | D79: =IF(C79<=$H$3,"Company"&" "&C79,"") -> Company 25 | E79: FQ End Date | F79: =IFERROR(IF(F80>0,(DATE(YEAR(F80),((INT((MONTH(F80)-1)/3)+1)*3)+1,1)-1),"-"),"NA") -> 45107 | G79: =IFERROR(IF(G80>0,(DATE(YEAR(G80),((INT((MONTH(G80)-1)/3)+1)*3)+1,1)-1),"-"),"NA") -> 45565 | H79: =IFERROR(IF(H80>0,(DATE(YEAR(H80),((INT((MONTH(H80)-1)/3)+1)*3)+1,1)-1),"-"),"NA") -> 45657 | I79: =IFERROR(IF(I80>0,(DATE(YEAR(I80),((INT((MONTH(I80)-1)/3)+1)*3)+1,1)-1),"-"),"NA") -> 46203 | J79: =IFERROR(IF(J80>0,(DATE(YEAR(J80),((INT((MONTH(J80)-1)/3)+1)*3)+1,1)-1),"-"),"NA") -> 46660 | L79: =IFERROR(IF(L80>0,(DATE(YEAR(L80),((INT((MONTH(L80)-1)/3)+1)*3)+1,1)-1),"-"),"") -> 46660 | O79: =IF(F80<=TODAY(),C79,"0") -> 0 | P79: =IF(F80<=TODAY(),D79,"0") -> 0 | Q79: =IF(F80<=TODAY(),F80,"0") -> 0 | R79: =IF(F80<=TODAY(),F81,0) -> 0 | S79: =IF(G80<=TODAY(),G81,0) -> 0 | T79: =IF(H80<=TODAY(),H81,0) -> 0 | U79: =IF(I80<=TODAY(),I81,0) -> 0 | V79: =IF(J80<=TODAY(),J81,0) -> 0 | W79: =IF(L80<=TODAY(),L81,0) -> 0 | X79: =IF(K80<=TODAY(),K81,"-") -> 0 | Z79: =IF(F80>TODAY(),C79,"0") -> 25 | AA79: =IF(F80>TODAY(),D79,"0") -> Company 25 | AB79: =IF(F80>TODAY(),F80,"0") -> 45072 | AC79: =IF(F80>TODAY(),F81,"0") -> 1250000 | AD79: =IF(G80>TODAY(),G81,"0") -> 112500 | AE79: =IF(H80>TODAY(),H81,"0") -> 937500 | AF79: =IF(I80>TODAY(),I81,"0") -> 750000 | AG79: =IF(J80>TODAY(),J81,"0") -> 0 | AH79: =IF(L80>TODAY(),L81,"0") -> 0
E80: Date | F80: =IF(C79<=$H$3,IF((F77+('Summary and Assumptions'!$K$118*7))>$D$3,(F77+('Summary and Assumptions'!$K$118*7)),($D$3+$H$4)),"") -> 45072 | G80: =IF($C79<=$H$3,IF((F80+('Summary and Assumptions'!$K$119*7))>$D$3,(F80+('Summary and Assumptions'!$K$119*7)),($D$3+$H$4)),"") -> 45527 | H80: =IF($C79<=$H$3,IF((F80+('Summary and Assumptions'!$K$120*7))>$D$3,(F80+('Summary and Assumptions'!$K$120*7)),($D$3+$H$4)),"") -> 45597 | I80: =IF($C79<=$H$3,IF((H80+('Summary and Assumptions'!$K$121*7))>$D$3,(H80+('Summary and Assumptions'!$K$121*7)),($D$3+$H$4)),"") -> 46129 | J80: =IF($C79<=$H$3,IF((I80+('Summary and Assumptions'!$K$122*7))>$D$3,(I80+('Summary and Assumptions'!$K$122*7)),($D$3+$H$4)),"") -> 46577 | L80: =IF($C79<=$H$3,IF((J80+('Summary and Assumptions'!$K$123*7))>$D$3,(J80+('Summary and Assumptions'!$K$123*7)),($D$3+$H$4)),"") -> 46577
E81: Amount | F81: =IF(C79<=$H$3,'Summary and Assumptions'!$D$101,"") -> 1250000 | G81: =IF(C79<=$H$3,F81*'Summary and Assumptions'!$K$111*'Summary and Assumptions'!$K$102,"") -> 112500 | H81: =IF(C79<=$H$3,$F81*'Summary and Assumptions'!$K$112*'Summary and Assumptions'!$K$103,"") -> 937500 | I81: =IF(C79<=$H$3,$F81*'Summary and Assumptions'!$K$113*'Summary and Assumptions'!$K$104,"") -> 750000 | J81: =IF(C79<=$H$3,$F81*'Summary and Assumptions'!$K$114*'Summary and Assumptions'!$K$105,"") -> 0 | K81: =IF(AND(J80<=$D$3,J81>0),$J$6,IF(AND(I80<=$D$3,I81>0),$I$6,IF(AND(H80<=$D$3,H81>0),$H$6,IF(AND(G80<=$D$3,G81>0),$G$6,IF(AND(F80<=$D$3,F81>0),$F$6,"0"))))) -> 0 | L81: =IF(C79<=$H$3,SUM($F81:$I81)*(1+'Summary and Assumptions'!$D$103),"") -> 0
B82: F | C82: =C79+1 -> 26 | D82: =IF(C82<=$H$3,"Company"&" "&C82,"") -> Company 26 | E82: FQ End Date | F82: =IFERROR(IF(F83>0,(DATE(YEAR(F83),((INT((MONTH(F83)-1)/3)+1)*3)+1,1)-1),"-"),"NA") -> 45107 | G82: =IFERROR(IF(G83>0,(DATE(YEAR(G83),((INT((MONTH(G83)-1)/3)+1)*3)+1,1)-1),"-"),"NA") -> 45565 | H82: =IFERROR(IF(H83>0,(DATE(YEAR(H83),((INT((MONTH(H83)-1)/3)+1)*3)+1,1)-1),"-"),"NA") -> 45657 | I82: =IFERROR(IF(I83>0,(DATE(YEAR(I83),((INT((MONTH(I83)-1)/3)+1)*3)+1,1)-1),"-"),"NA") -> 46203 | J82: =IFERROR(IF(J83>0,(DATE(YEAR(J83),((INT((MONTH(J83)-1)/3)+1)*3)+1,1)-1),"-"),"NA") -> 46660 | L82: =IFERROR(IF(L83>0,(DATE(YEAR(L83),((INT((MONTH(L83)-1)/3)+1)*3)+1,1)-1),"-"),"") -> 46660 | O82: =IF(F83<=TODAY(),C82,"0") -> 0 | P82: =IF(F83<=TODAY(),D82,"0") -> 0 | Q82: =IF(F83<=TODAY(),F83,"0") -> 0 | R82: =IF(F83<=TODAY(),F84,0) -> 0 | S82: =IF(G83<=TODAY(),G84,0) -> 0 | T82: =IF(H83<=TODAY(),H84,0) -> 0 | U82: =IF(I83<=TODAY(),I84,0) -> 0 | V82: =IF(J83<=TODAY(),J84,0) -> 0 | W82: =IF(L83<=TODAY(),L84,0) -> 0 | X82: =IF(K83<=TODAY(),K84,"-") -> 0 | Z82: =IF(F83>TODAY(),C82,"0") -> 26 | AA82: =IF(F83>TODAY(),D82,"0") -> Company 26 | AB82: =IF(F83>TODAY(),F83,"0") -> 45107 | AC82: =IF(F83>TODAY(),F84,"0") -> 1250000 | AD82: =IF(G83>TODAY(),G84,"0") -> 112500 | AE82: =IF(H83>TODAY(),H84,"0") -> 937500 | AF82: =IF(I83>TODAY(),I84,"0") -> 750000 | AG82: =IF(J83>TODAY(),J84,"0") -> 0 | AH82: =IF(L83>TODAY(),L84,"0") -> 0
E83: Date | F83: =IF(C82<=$H$3,IF((F80+('Summary and Assumptions'!$K$118*7))>$D$3,(F80+('Summary and Assumptions'!$K$118*7)),($D$3+$H$4)),"") -> 45107 | G83: =IF($C82<=$H$3,IF((F83+('Summary and Assumptions'!$K$119*7))>$D$3,(F83+('Summary and Assumptions'!$K$119*7)),($D$3+$H$4)),"") -> 45562 | H83: =IF($C82<=$H$3,IF((F83+('Summary and Assumptions'!$K$120*7))>$D$3,(F83+('Summary and Assumptions'!$K$120*7)),($D$3+$H$4)),"") -> 45632 | I83: =IF($C82<=$H$3,IF((H83+('Summary and Assumptions'!$K$121*7))>$D$3,(H83+('Summary and Assumptions'!$K$121*7)),($D$3+$H$4)),"") -> 46164 | J83: =IF($C82<=$H$3,IF((I83+('Summary and Assumptions'!$K$122*7))>$D$3,(I83+('Summary and Assumptions'!$K$122*7)),($D$3+$H$4)),"") -> 46612 | L83: =IF($C82<=$H$3,IF((J83+('Summary and Assumptions'!$K$123*7))>$D$3,(J83+('Summary and Assumptions'!$K$123*7)),($D$3+$H$4)),"") -> 46612
E84: Amount | F84: =IF(C82<=$H$3,'Summary and Assumptions'!$D$101,"") -> 1250000 | G84: =IF(C82<=$H$3,F84*'Summary and Assumptions'!$K$111*'Summary and Assumptions'!$K$102,"") -> 112500 | H84: =IF(C82<=$H$3,$F84*'Summary and Assumptions'!$K$112*'Summary and Assumptions'!$K$103,"") -> 937500 | I84: =IF(C82<=$H$3,$F84*'Summary and Assumptions'!$K$113*'Summary and Assumptions'!$K$104,"") -> 750000 | J84: =IF(C82<=$H$3,$F84*'Summary and Assumptions'!$K$114*'Summary and Assumptions'!$K$105,"") -> 0 | K84: =IF(AND(J83<=$D$3,J84>0),$J$6,IF(AND(I83<=$D$3,I84>0),$I$6,IF(AND(H83<=$D$3,H84>0),$H$6,IF(AND(G83<=$D$3,G84>0),$G$6,IF(AND(F83<=$D$3,F84>0),$F$6,"0"))))) -> 0 | L84: =IF(C82<=$H$3,SUM($F84:$I84)*(1+'Summary and Assumptions'!$D$103),"") -> 0
B85: F | C85: =C82+1 -> 27 | D85: =IF(C85<=$H$3,"Company"&" "&C85,"") -> Company 27 | E85: FQ End Date | F85: =IFERROR(IF(F86>0,(DATE(YEAR(F86),((INT((MONTH(F86)-1)/3)+1)*3)+1,1)-1),"-"),"NA") -> 45199 | G85: =IFERROR(IF(G86>0,(DATE(YEAR(G86),((INT((MONTH(G86)-1)/3)+1)*3)+1,1)-1),"-"),"NA") -> 45657 | H85: =IFERROR(IF(H86>0,(DATE(YEAR(H86),((INT((MONTH(H86)-1)/3)+1)*3)+1,1)-1),"-"),"NA") -> 45747 | I85: =IFERROR(IF(I86>0,(DATE(YEAR(I86),((INT((MONTH(I86)-1)/3)+1)*3)+1,1)-1),"-"),"NA") -> 46203 | J85: =IFERROR(IF(J86>0,(DATE(YEAR(J86),((INT((MONTH(J86)-1)/3)+1)*3)+1,1)-1),"-"),"NA") -> 46660 | L85: =IFERROR(IF(L86>0,(DATE(YEAR(L86),((INT((MONTH(L86)-1)/3)+1)*3)+1,1)-1),"-"),"") -> 46660 | O85: =IF(F86<=TODAY(),C85,"0") -> 0 | P85: =IF(F86<=TODAY(),D85,"0") -> 0 | Q85: =IF(F86<=TODAY(),F86,"0") -> 0 | R85: =IF(F86<=TODAY(),F87,0) -> 0 | S85: =IF(G86<=TODAY(),G87,0) -> 0 | T85: =IF(H86<=TODAY(),H87,0) -> 0 | U85: =IF(I86<=TODAY(),I87,0) -> 0 | V85: =IF(J86<=TODAY(),J87,0) -> 0 | W85: =IF(L86<=TODAY(),L87,0) -> 0 | X85: =IF(K86<=TODAY(),K87,"-") -> 0 | Z85: =IF(F86>TODAY(),C85,"0") -> 27 | AA85: =IF(F86>TODAY(),D85,"0") -> Company 27 | AB85: =IF(F86>TODAY(),F86,"0") -> 45142 | AC85: =IF(F86>TODAY(),F87,"0") -> 1250000 | AD85: =IF(G86>TODAY(),G87,"0") -> 112500 | AE85: =IF(H86>TODAY(),H87,"0") -> 937500 | AF85: =IF(I86>TODAY(),I87,"0") -> 750000 | AG85: =IF(J86>TODAY(),J87,"0") -> 0 | AH85: =IF(L86>TODAY(),L87,"0") -> 0
E86: Date | F86: =IF(C85<=$H$3,IF((F83+('Summary and Assumptions'!$K$118*7))>$D$3,(F83+('Summary and Assumptions'!$K$118*7)),($D$3+$H$4)),"") -> 45142 | G86: =IF($C85<=$H$3,IF((F86+('Summary and Assumptions'!$K$119*7))>$D$3,(F86+('Summary and Assumptions'!$K$119*7)),($D$3+$H$4)),"") -> 45597 | H86: =IF($C85<=$H$3,IF((F86+('Summary and Assumptions'!$K$120*7))>$D$3,(F86+('Summary and Assumptions'!$K$120*7)),($D$3+$H$4)),"") -> 45667 | I86: =IF($C85<=$H$3,IF((H86+('Summary and Assumptions'!$K$121*7))>$D$3,(H86+('Summary and Assumptions'!$K$121*7)),($D$3+$H$4)),"") -> 46199 | J86: =IF($C85<=$H$3,IF((I86+('Summary and Assumptions'!$K$122*7))>$D$3,(I86+('Summary and Assumptions'!$K$122*7)),($D$3+$H$4)),"") -> 46647 | L86: =IF($C85<=$H$3,IF((J86+('Summary and Assumptions'!$K$123*7))>$D$3,(J86+('Summary and Assumptions'!$K$123*7)),($D$3+$H$4)),"") -> 46647
E87: Amount | F87: =IF(C85<=$H$3,'Summary and Assumptions'!$D$101,"") -> 1250000 | G87: =IF(C85<=$H$3,F87*'Summary and Assumptions'!$K$111*'Summary and Assumptions'!$K$102,"") -> 112500 | H87: =IF(C85<=$H$3,$F87*'Summary and Assumptions'!$K$112*'Summary and Assumptions'!$K$103,"") -> 937500 | I87: =IF(C85<=$H$3,$F87*'Summary and Assumptions'!$K$113*'Summary and Assumptions'!$K$104,"") -> 750000 | J87: =IF(C85<=$H$3,$F87*'Summary and Assumptions'!$K$114*'Summary and Assumptions'!$K$105,"") -> 0 | K87: =IF(AND(J86<=$D$3,J87>0),$J$6,IF(AND(I86<=$D$3,I87>0),$I$6,IF(AND(H86<=$D$3,H87>0),$H$6,IF(AND(G86<=$D$3,G87>0),$G$6,IF(AND(F86<=$D$3,F87>0),$F$6,"0"))))) -> 0 | L87: =IF(C85<=$H$3,SUM($F87:$I87)*(1+'Summary and Assumptions'!$D$103),"") -> 0
B88: F | C88: =C85+1 -> 28 | D88: =IF(C88<=$H$3,"Company"&" "&C88,"") -> Company 28 | E88: FQ End Date | F88: =IFERROR(IF(F89>0,(DATE(YEAR(F89),((INT((MONTH(F89)-1)/3)+1)*3)+1,1)-1),"-"),"NA") -> 45199 | G88: =IFERROR(IF(G89>0,(DATE(YEAR(G89),((INT((MONTH(G89)-1)/3)+1)*3)+1,1)-1),"-"),"NA") -> 45657 | H88: =IFERROR(IF(H89>0,(DATE(YEAR(H89),((INT((MONTH(H89)-1)/3)+1)*3)+1,1)-1),"-"),"NA") -> 45747 | I88: =IFERROR(IF(I89>0,(DATE(YEAR(I89),((INT((MONTH(I89)-1)/3)+1)*3)+1,1)-1),"-"),"NA") -> 46295 | J88: =IFERROR(IF(J89>0,(DATE(YEAR(J89),((INT((MONTH(J89)-1)/3)+1)*3)+1,1)-1),"-"),"NA") -> 46752 | L88: =IFERROR(IF(L89>0,(DATE(YEAR(L89),((INT((MONTH(L89)-1)/3)+1)*3)+1,1)-1),"-"),"") -> 46752 | O88: =IF(F89<=TODAY(),C88,"0") -> 0 | P88: =IF(F89<=TODAY(),D88,"0") -> 0 | Q88: =IF(F89<=TODAY(),F89,"0") -> 0 | R88: =IF(F89<=TODAY(),F90,0) -> 0 | S88: =IF(G89<=TODAY(),G90,0) -> 0 | T88: =IF(H89<=TODAY(),H90,0) -> 0 | U88: =IF(I89<=TODAY(),I90,0) -> 0 | V88: =IF(J89<=TODAY(),J90,0) -> 0 | W88: =IF(L89<=TODAY(),L90,0) -> 0 | X88: =IF(K89<=TODAY(),K90,"-") -> 0 | Z88: =IF(F89>TODAY(),C88,"0") -> 28 | AA88: =IF(F89>TODAY(),D88,"0") -> Company 28 | AB88: =IF(F89>TODAY(),F89,"0") -> 45177 | AC88: =IF(F89>TODAY(),F90,"0") -> 1250000 | AD88: =IF(G89>TODAY(),G90,"0") -> 112500 | AE88: =IF(H89>TODAY(),H90,"0") -> 937500 | AF88: =IF(I89>TODAY(),I90,"0") -> 750000 | AG88: =IF(J89>TODAY(),J90,"0") -> 0 | AH88: =IF(L89>TODAY(),L90,"0") -> 0
E89: Date | F89: =IF(C88<=$H$3,IF((F86+('Summary and Assumptions'!$K$118*7))>$D$3,(F86+('Summary and Assumptions'!$K$118*7)),($D$3+$H$4)),"") -> 45177 | G89: =IF($C88<=$H$3,IF((F89+('Summary and Assumptions'!$K$119*7))>$D$3,(F89+('Summary and Assumptions'!$K$119*7)),($D$3+$H$4)),"") -> 45632 | H89: =IF($C88<=$H$3,IF((F89+('Summary and Assumptions'!$K$120*7))>$D$3,(F89+('Summary and Assumptions'!$K$120*7)),($D$3+$H$4)),"") -> 45702 | I89: =IF($C88<=$H$3,IF((H89+('Summary and Assumptions'!$K$121*7))>$D$3,(H89+('Summary and Assumptions'!$K$121*7)),($D$3+$H$4)),"") -> 46234 | J89: =IF($C88<=$H$3,IF((I89+('Summary and Assumptions'!$K$122*7))>$D$3,(I89+('Summary and Assumptions'!$K$122*7)),($D$3+$H$4)),"") -> 46682 | L89: =IF($C88<=$H$3,IF((J89+('Summary and Assumptions'!$K$123*7))>$D$3,(J89+('Summary and Assumptions'!$K$123*7)),($D$3+$H$4)),"") -> 46682
E90: Amount | F90: =IF(C88<=$H$3,'Summary and Assumptions'!$D$101,"") -> 1250000 | G90: =IF(C88<=$H$3,F90*'Summary and Assumptions'!$K$111*'Summary and Assumptions'!$K$102,"") -> 112500 | H90: =IF(C88<=$H$3,$F90*'Summary and Assumptions'!$K$112*'Summary and Assumptions'!$K$103,"") -> 937500 | I90: =IF(C88<=$H$3,$F90*'Summary and Assumptions'!$K$113*'Summary and Assumptions'!$K$104,"") -> 750000 | J90: =IF(C88<=$H$3,$F90*'Summary and Assumptions'!$K$114*'Summary and Assumptions'!$K$105,"") -> 0 | K90: =IF(AND(J89<=$D$3,J90>0),$J$6,IF(AND(I89<=$D$3,I90>0),$I$6,IF(AND(H89<=$D$3,H90>0),$H$6,IF(AND(G89<=$D$3,G90>0),$G$6,IF(AND(F89<=$D$3,F90>0),$F$6,"0"))))) -> 0 | L90: =IF(C88<=$H$3,SUM($F90:$I90)*(1+'Summary and Assumptions'!$D$103),"") -> 0
B91: F | C91: =C88+1 -> 29 | D91: =IF(C91<=$H$3,"Company"&" "&C91,"") -> Company 29 | E91: FQ End Date | F91: =IFERROR(IF(F92>0,(DATE(YEAR(F92),((INT((MONTH(F92)-1)/3)+1)*3)+1,1)-1),"-"),"NA") -> 45291 | G91: =IFERROR(IF(G92>0,(DATE(YEAR(G92),((INT((MONTH(G92)-1)/3)+1)*3)+1,1)-1),"-"),"NA") -> 45747 | H91: =IFERROR(IF(H92>0,(DATE(YEAR(H92),((INT((MONTH(H92)-1)/3)+1)*3)+1,1)-1),"-"),"NA") -> 45747 | I91: =IFERROR(IF(I92>0,(DATE(YEAR(I92),((INT((MONTH(I92)-1)/3)+1)*3)+1,1)-1),"-"),"NA") -> 46295 | J91: =IFERROR(IF(J92>0,(DATE(YEAR(J92),((INT((MONTH(J92)-1)/3)+1)*3)+1,1)-1),"-"),"NA") -> 46752 | L91: =IFERROR(IF(L92>0,(DATE(YEAR(L92),((INT((MONTH(L92)-1)/3)+1)*3)+1,1)-1),"-"),"") -> 46752 | O91: =IF(F92<=TODAY(),C91,"0") -> 0 | P91: =IF(F92<=TODAY(),D91,"0") -> 0 | Q91: =IF(F92<=TODAY(),F92,"0") -> 0 | R91: =IF(F92<=TODAY(),F93,0) -> 0 | S91: =IF(G92<=TODAY(),G93,0) -> 0 | T91: =IF(H92<=TODAY(),H93,0) -> 0 | U91: =IF(I92<=TODAY(),I93,0) -> 0 | V91: =IF(J92<=TODAY(),J93,0) -> 0 | W91: =IF(L92<=TODAY(),L93,0) -> 0 | X91: =IF(K92<=TODAY(),K93,"-") -> 0 | Z91: =IF(F92>TODAY(),C91,"0") -> 29 | AA91: =IF(F92>TODAY(),D91,"0") -> Company 29 | AB91: =IF(F92>TODAY(),F92,"0") -> 45212 | AC91: =IF(F92>TODAY(),F93,"0") -> 1250000 | AD91: =IF(G92>TODAY(),G93,"0") -> 112500 | AE91: =IF(H92>TODAY(),H93,"0") -> 937500 | AF91: =IF(I92>TODAY(),I93,"0") -> 750000 | AG91: =IF(J92>TODAY(),J93,"0") -> 0 | AH91: =IF(L92>TODAY(),L93,"0") -> 0
E92: Date | F92: =IF(C91<=$H$3,IF((F89+('Summary and Assumptions'!$K$118*7))>$D$3,(F89+('Summary and Assumptions'!$K$118*7)),($D$3+$H$4)),"") -> 45212 | G92: =IF($C91<=$H$3,IF((F92+('Summary and Assumptions'!$K$119*7))>$D$3,(F92+('Summary and Assumptions'!$K$119*7)),($D$3+$H$4)),"") -> 45667 | H92: =IF($C91<=$H$3,IF((F92+('Summary and Assumptions'!$K$120*7))>$D$3,(F92+('Summary and Assumptions'!$K$120*7)),($D$3+$H$4)),"") -> 45737 | I92: =IF($C91<=$H$3,IF((H92+('Summary and Assumptions'!$K$121*7))>$D$3,(H92+('Summary and Assumptions'!$K$121*7)),($D$3+$H$4)),"") -> 46269 | J92: =IF($C91<=$H$3,IF((I92+('Summary and Assumptions'!$K$122*7))>$D$3,(I92+('Summary and Assumptions'!$K$122*7)),($D$3+$H$4)),"") -> 46717 | L92: =IF($C91<=$H$3,IF((J92+('Summary and Assumptions'!$K$123*7))>$D$3,(J92+('Summary and Assumptions'!$K$123*7)),($D$3+$H$4)),"") -> 46717
E93: Amount | F93: =IF(C91<=$H$3,'Summary and Assumptions'!$D$101,"") -> 1250000 | G93: =IF(C91<=$H$3,F93*'Summary and Assumptions'!$K$111*'Summary and Assumptions'!$K$102,"") -> 112500 | H93: =IF(C91<=$H$3,$F93*'Summary and Assumptions'!$K$112*'Summary and Assumptions'!$K$103,"") -> 937500 | I93: =IF(C91<=$H$3,$F93*'Summary and Assumptions'!$K$113*'Summary and Assumptions'!$K$104,"") -> 750000 | J93: =IF(C91<=$H$3,$F93*'Summary and Assumptions'!$K$114*'Summary and Assumptions'!$K$105,"") -> 0 | K93: =IF(AND(J92<=$D$3,J93>0),$J$6,IF(AND(I92<=$D$3,I93>0),$I$6,IF(AND(H92<=$D$3,H93>0),$H$6,IF(AND(G92<=$D$3,G93>0),$G$6,IF(AND(F92<=$D$3,F93>0),$F$6,"0"))))) -> 0 | L93: =IF(C91<=$H$3,SUM($F93:$I93)*(1+'Summary and Assumptions'!$D$103),"") -> 0
B94: F | C94: =C91+1 -> 30 | D94: =IF(C94<=$H$3,"Company"&" "&C94,"") -> Company 30 | E94: FQ End Date | F94: =IFERROR(IF(F95>0,(DATE(YEAR(F95),((INT((MONTH(F95)-1)/3)+1)*3)+1,1)-1),"-"),"NA") -> 45291 | G94: =IFERROR(IF(G95>0,(DATE(YEAR(G95),((INT((MONTH(G95)-1)/3)+1)*3)+1,1)-1),"-"),"NA") -> 45747 | H94: =IFERROR(IF(H95>0,(DATE(YEAR(H95),((INT((MONTH(H95)-1)/3)+1)*3)+1,1)-1),"-"),"NA") -> 45838 | I94: =IFERROR(IF(I95>0,(DATE(YEAR(I95),((INT((MONTH(I95)-1)/3)+1)*3)+1,1)-1),"-"),"NA") -> 46387 | J94: =IFERROR(IF(J95>0,(DATE(YEAR(J95),((INT((MONTH(J95)-1)/3)+1)*3)+1,1)-1),"-"),"NA") -> 46752 | L94: =IFERROR(IF(L95>0,(DATE(YEAR(L95),((INT((MONTH(L95)-1)/3)+1)*3)+1,1)-1),"-"),"") -> 46752 | O94: =IF(F95<=TODAY(),C94,"0") -> 0 | P94: =IF(F95<=TODAY(),D94,"0") -> 0 | Q94: =IF(F95<=TODAY(),F95,"0") -> 0 | R94: =IF(F95<=TODAY(),F96,0) -> 0 | S94: =IF(G95<=TODAY(),G96,0) -> 0 | T94: =IF(H95<=TODAY(),H96,0) -> 0 | U94: =IF(I95<=TODAY(),I96,0) -> 0 | V94: =IF(J95<=TODAY(),J96,0) -> 0 | W94: =IF(L95<=TODAY(),L96,0) -> 0 | X94: =IF(K95<=TODAY(),K96,"-") -> 0 | Z94: =IF(F95>TODAY(),C94,"0") -> 30 | AA94: =IF(F95>TODAY(),D94,"0") -> Company 30 | AB94: =IF(F95>TODAY(),F95,"0") -> 45247 | AC94: =IF(F95>TODAY(),F96,"0") -> 1250000 | AD94: =IF(G95>TODAY(),G96,"0") -> 112500 | AE94: =IF(H95>TODAY(),H96,"0") -> 937500 | AF94: =IF(I95>TODAY(),I96,"0") -> 750000 | AG94: =IF(J95>TODAY(),J96,"0") -> 0 | AH94: =IF(L95>TODAY(),L96,"0") -> 0
E95: Date | F95: =IF(C94<=$H$3,IF((F92+('Summary and Assumptions'!$K$118*7))>$D$3,(F92+('Summary and Assumptions'!$K$118*7)),($D$3+$H$4)),"") -> 45247 | G95: =IF($C94<=$H$3,IF((F95+('Summary and Assumptions'!$K$119*7))>$D$3,(F95+('Summary and Assumptions'!$K$119*7)),($D$3+$H$4)),"") -> 45702 | H95: =IF($C94<=$H$3,IF((F95+('Summary and Assumptions'!$K$120*7))>$D$3,(F95+('Summary and Assumptions'!$K$120*7)),($D$3+$H$4)),"") -> 45772 | I95: =IF($C94<=$H$3,IF((H95+('Summary and Assumptions'!$K$121*7))>$D$3,(H95+('Summary and Assumptions'!$K$121*7)),($D$3+$H$4)),"") -> 46304 | J95: =IF($C94<=$H$3,IF((I95+('Summary and Assumptions'!$K$122*7))>$D$3,(I95+('Summary and Assumptions'!$K$122*7)),($D$3+$H$4)),"") -> 46752 | L95: =IF($C94<=$H$3,IF((J95+('Summary and Assumptions'!$K$123*7))>$D$3,(J95+('Summary and Assumptions'!$K$123*7)),($D$3+$H$4)),"") -> 46752
E96: Amount | F96: =IF(C94<=$H$3,'Summary and Assumptions'!$D$101,"") -> 1250000 | G96: =IF(C94<=$H$3,F96*'Summary and Assumptions'!$K$111*'Summary and Assumptions'!$K$102,"") -> 112500 | H96: =IF(C94<=$H$3,$F96*'Summary and Assumptions'!$K$112*'Summary and Assumptions'!$K$103,"") -> 937500 | I96: =IF(C94<=$H$3,$F96*'Summary and Assumptions'!$K$113*'Summary and Assumptions'!$K$104,"") -> 750000 | J96: =IF(C94<=$H$3,$F96*'Summary and Assumptions'!$K$114*'Summary and Assumptions'!$K$105,"") -> 0 | K96: =IF(AND(J95<=$D$3,J96>0),$J$6,IF(AND(I95<=$D$3,I96>0),$I$6,IF(AND(H95<=$D$3,H96>0),$H$6,IF(AND(G95<=$D$3,G96>0),$G$6,IF(AND(F95<=$D$3,F96>0),$F$6,"0"))))) -> 0 | L96: =IF(C94<=$H$3,SUM($F96:$I96)*(1+'Summary and Assumptions'!$D$103),"") -> 0
B97: F | C97: =C94+1 -> 31 | D97: =IF(C97<=$H$3,"Company"&" "&C97,"") -> Company 31 | E97: FQ End Date | F97: =IFERROR(IF(F98>0,(DATE(YEAR(F98),((INT((MONTH(F98)-1)/3)+1)*3)+1,1)-1),"-"),"NA") -> 45291 | G97: =IFERROR(IF(G98>0,(DATE(YEAR(G98),((INT((MONTH(G98)-1)/3)+1)*3)+1,1)-1),"-"),"NA") -> 45747 | H97: =IFERROR(IF(H98>0,(DATE(YEAR(H98),((INT((MONTH(H98)-1)/3)+1)*3)+1,1)-1),"-"),"NA") -> 45838 | I97: =IFERROR(IF(I98>0,(DATE(YEAR(I98),((INT((MONTH(I98)-1)/3)+1)*3)+1,1)-1),"-"),"NA") -> 46387 | J97: =IFERROR(IF(J98>0,(DATE(YEAR(J98),((INT((MONTH(J98)-1)/3)+1)*3)+1,1)-1),"-"),"NA") -> 46843 | L97: =IFERROR(IF(L98>0,(DATE(YEAR(L98),((INT((MONTH(L98)-1)/3)+1)*3)+1,1)-1),"-"),"") -> 46843 | O97: =IF(F98<=TODAY(),C97,"0") -> 0 | P97: =IF(F98<=TODAY(),D97,"0") -> 0 | Q97: =IF(F98<=TODAY(),F98,"0") -> 0 | R97: =IF(F98<=TODAY(),F99,0) -> 0 | S97: =IF(G98<=TODAY(),G99,0) -> 0 | T97: =IF(H98<=TODAY(),H99,0) -> 0 | U97: =IF(I98<=TODAY(),I99,0) -> 0 | V97: =IF(J98<=TODAY(),J99,0) -> 0 | W97: =IF(L98<=TODAY(),L99,0) -> 0 | X97: =IF(K98<=TODAY(),K99,"-") -> 0 | Z97: =IF(F98>TODAY(),C97,"0") -> 31 | AA97: =IF(F98>TODAY(),D97,"0") -> Company 31 | AB97: =IF(F98>TODAY(),F98,"0") -> 45282 | AC97: =IF(F98>TODAY(),F99,"0") -> 1250000 | AD97: =IF(G98>TODAY(),G99,"0") -> 112500 | AE97: =IF(H98>TODAY(),H99,"0") -> 937500 | AF97: =IF(I98>TODAY(),I99,"0") -> 750000 | AG97: =IF(J98>TODAY(),J99,"0") -> 0 | AH97: =IF(L98>TODAY(),L99,"0") -> 0
E98: Date | F98: =IF(C97<=$H$3,IF((F95+('Summary and Assumptions'!$K$118*7))>$D$3,(F95+('Summary and Assumptions'!$K$118*7)),($D$3+$H$4)),"") -> 45282 | G98: =IF($C97<=$H$3,IF((F98+('Summary and Assumptions'!$K$119*7))>$D$3,(F98+('Summary and Assumptions'!$K$119*7)),($D$3+$H$4)),"") -> 45737 | H98: =IF($C97<=$H$3,IF((F98+('Summary and Assumptions'!$K$120*7))>$D$3,(F98+('Summary and Assumptions'!$K$120*7)),($D$3+$H$4)),"") -> 45807 | I98: =IF($C97<=$H$3,IF((H98+('Summary and Assumptions'!$K$121*7))>$D$3,(H98+('Summary and Assumptions'!$K$121*7)),($D$3+$H$4)),"") -> 46339 | J98: =IF($C97<=$H$3,IF((I98+('Summary and Assumptions'!$K$122*7))>$D$3,(I98+('Summary and Assumptions'!$K$122*7)),($D$3+$H$4)),"") -> 46787 | L98: =IF($C97<=$H$3,IF((J98+('Summary and Assumptions'!$K$123*7))>$D$3,(J98+('Summary and Assumptions'!$K$123*7)),($D$3+$H$4)),"") -> 46787
E99: Amount | F99: =IF(C97<=$H$3,'Summary and Assumptions'!$D$101,"") -> 1250000 | G99: =IF(C97<=$H$3,F99*'Summary and Assumptions'!$K$111*'Summary and Assumptions'!$K$102,"") -> 112500 | H99: =IF(C97<=$H$3,$F99*'Summary and Assumptions'!$K$112*'Summary and Assumptions'!$K$103,"") -> 937500 | I99: =IF(C97<=$H$3,$F99*'Summary and Assumptions'!$K$113*'Summary and Assumptions'!$K$104,"") -> 750000 | J99: =IF(C97<=$H$3,$F99*'Summary and Assumptions'!$K$114*'Summary and Assumptions'!$K$105,"") -> 0 | K99: =IF(AND(J98<=$D$3,J99>0),$J$6,IF(AND(I98<=$D$3,I99>0),$I$6,IF(AND(H98<=$D$3,H99>0),$H$6,IF(AND(G98<=$D$3,G99>0),$G$6,IF(AND(F98<=$D$3,F99>0),$F$6,"0"))))) -> 0 | L99: =IF(C97<=$H$3,SUM($F99:$I99)*(1+'Summary and Assumptions'!$D$103),"") -> 0
B100: F | C100: =C97+1 -> 32 | D100: =IF(C100<=$H$3,"Company"&" "&C100,"") -> Company 32 | E100: FQ End Date | F100: =IFERROR(IF(F101>0,(DATE(YEAR(F101),((INT((MONTH(F101)-1)/3)+1)*3)+1,1)-1),"-"),"NA") -> 45382 | G100: =IFERROR(IF(G101>0,(DATE(YEAR(G101),((INT((MONTH(G101)-1)/3)+1)*3)+1,1)-1),"-"),"NA") -> 45838 | H100: =IFERROR(IF(H101>0,(DATE(YEAR(H101),((INT((MONTH(H101)-1)/3)+1)*3)+1,1)-1),"-"),"NA") -> 45930 | I100: =IFERROR(IF(I101>0,(DATE(YEAR(I101),((INT((MONTH(I101)-1)/3)+1)*3)+1,1)-1),"-"),"NA") -> 46387 | J100: =IFERROR(IF(J101>0,(DATE(YEAR(J101),((INT((MONTH(J101)-1)/3)+1)*3)+1,1)-1),"-"),"NA") -> 46843 | L100: =IFERROR(IF(L101>0,(DATE(YEAR(L101),((INT((MONTH(L101)-1)/3)+1)*3)+1,1)-1),"-"),"") -> 46843 | O100: =IF(F101<=TODAY(),C100,"0") -> 0 | P100: =IF(F101<=TODAY(),D100,"0") -> 0 | Q100: =IF(F101<=TODAY(),F101,"0") -> 0 | R100: =IF(F101<=TODAY(),F102,0) -> 0 | S100: =IF(G101<=TODAY(),G102,0) -> 0 | T100: =IF(H101<=TODAY(),H102,0) -> 0 | U100: =IF(I101<=TODAY(),I102,0) -> 0 | V100: =IF(J101<=TODAY(),J102,0) -> 0 | W100: =IF(L101<=TODAY(),L102,0) -> 0 | X100: =IF(K101<=TODAY(),K102,"-") -> 0 | Z100: =IF(F101>TODAY(),C100,"0") -> 32 | AA100: =IF(F101>TODAY(),D100,"0") -> Company 32 | AB100: =IF(F101>TODAY(),F101,"0") -> 45317 | AC100: =IF(F101>TODAY(),F102,"0") -> 1250000 | AD100: =IF(G101>TODAY(),G102,"0") -> 112500 | AE100: =IF(H101>TODAY(),H102,"0") -> 937500 | AF100: =IF(I101>TODAY(),I102,"0") -> 750000 | AG100: =IF(J101>TODAY(),J102,"0") -> 0 | AH100: =IF(L101>TODAY(),L102,"0") -> 0
...

Sheet Model
B1: ='Summary and Assumptions'!D9 -> Fund Name
B2: Model
B3: Start | C3: =DATE(YEAR('Summary and Assumptions'!D10),1,1) -> 44197 | G3: ="FY "&YEAR(G4) -> FY 2021 | K3: ="FY "&YEAR(K4) -> FY 2022 | O3: ="FY "&YEAR(O4)&"E" -> FY 2023E | S3: ="FY "&YEAR(S4)&"E" -> FY 2024E | W3: ="FY "&YEAR(W4)&"E" -> FY 2025E | AA3: ="FY "&YEAR(AA4)&"E" -> FY 2026E | AE3: ="FY "&YEAR(AE4)&"E" -> FY 2027E | AI3: ="FY "&YEAR(AI4)&"E" -> FY 2028E | AM3: ="FY "&YEAR(AM4)&"E" -> FY 2029E | AQ3: ="FY "&YEAR(AQ4)&"E" -> FY 2030E | AU3: ="FY "&YEAR(AU4)&"E" -> FY 2031E
B4: Today | C4: ='Summary and Assumptions'!D13 -> 43958 | D4: =DATE(YEAR(C3),((INT((MONTH(C3)-1)/3)+1)*3)+1,1)-1 -> 44286 | E4: =DATE(YEAR(D4),((INT((MONTH(D4+3)-1)/3)+1)*3)+1,1)-1 -> 44377 | F4: =DATE(YEAR(E4),((INT((MONTH(E4+3)-1)/3)+1)*3)+1,1)-1 -> 44469 | G4: =DATE(YEAR(F4),((INT((MONTH(F4+3)-1)/3)+1)*3)+1,1)-1 -> 44561 | H4: =DATE(YEAR(G4+1),((INT((MONTH(G4+3)-1)/3)+1)*3)+1,1)-1 -> 44651 | I4: =DATE(YEAR(H4),((INT((MONTH(H4+3)-1)/3)+1)*3)+1,1)-1 -> 44742 | J4: =DATE(YEAR(I4),((INT((MONTH(I4+3)-1)/3)+1)*3)+1,1)-1 -> 44834 | K4: =DATE(YEAR(J4),((INT((MONTH(J4+3)-1)/3)+1)*3)+1,1)-1 -> 44926 | L4: =DATE(YEAR(K4+1),((INT((MONTH(K4+3)-1)/3)+1)*3)+1,1)-1 -> 45016 | M4: =DATE(YEAR(L4),((INT((MONTH(L4+3)-1)/3)+1)*3)+1,1)-1 -> 45107 | N4: =DATE(YEAR(M4),((INT((MONTH(M4+3)-1)/3)+1)*3)+1,1)-1 -> 45199 | O4: =DATE(YEAR(N4),((INT((MONTH(N4+3)-1)/3)+1)*3)+1,1)-1 -> 45291 | P4: =DATE(YEAR(O4+1),((INT((MONTH(O4+3)-1)/3)+1)*3)+1,1)-1 -> 45382 | Q4: =DATE(YEAR(P4),((INT((MONTH(P4+3)-1)/3)+1)*3)+1,1)-1 -> 45473 | R4: =DATE(YEAR(Q4),((INT((MONTH(Q4+3)-1)/3)+1)*3)+1,1)-1 -> 45565 | S4: =DATE(YEAR(R4),((INT((MONTH(R4+3)-1)/3)+1)*3)+1,1)-1 -> 45657 | T4: =DATE(YEAR(S4+1),((INT((MONTH(S4+3)-1)/3)+1)*3)+1,1)-1 -> 45747 | U4: =DATE(YEAR(T4),((INT((MONTH(T4+3)-1)/3)+1)*3)+1,1)-1 -> 45838 | V4: =DATE(YEAR(U4),((INT((MONTH(U4+3)-1)/3)+1)*3)+1,1)-1 -> 45930 | W4: =DATE(YEAR(V4),((INT((MONTH(V4+3)-1)/3)+1)*3)+1,1)-1 -> 46022 | X4: =DATE(YEAR(W4+1),((INT((MONTH(W4+3)-1)/3)+1)*3)+1,1)-1 -> 46112 | Y4: =DATE(YEAR(X4),((INT((MONTH(X4+3)-1)/3)+1)*3)+1,1)-1 -> 46203 | Z4: =DATE(YEAR(Y4),((INT((MONTH(Y4+3)-1)/3)+1)*3)+1,1)-1 -> 46295 | AA4: =DATE(YEAR(Z4),((INT((MONTH(Z4+3)-1)/3)+1)*3)+1,1)-1 -> 46387 | AB4: =DATE(YEAR(AA4+1),((INT((MONTH(AA4+3)-1)/3)+1)*3)+1,1)-1 -> 46477 | AC4: =DATE(YEAR(AB4),((INT((MONTH(AB4+3)-1)/3)+1)*3)+1,1)-1 -> 46568 | AD4: =DATE(YEAR(AC4),((INT((MONTH(AC4+3)-1)/3)+1)*3)+1,1)-1 -> 46660 | AE4: =DATE(YEAR(AD4),((INT((MONTH(AD4+3)-1)/3)+1)*3)+1,1)-1 -> 46752 | AF4: =DATE(YEAR(AE4+1),((INT((MONTH(AE4+3)-1)/3)+1)*3)+1,1)-1 -> 46843 | AG4: =DATE(YEAR(AF4),((INT((MONTH(AF4+3)-1)/3)+1)*3)+1,1)-1 -> 46934 | AH4: =DATE(YEAR(AG4),((INT((MONTH(AG4+3)-1)/3)+1)*3)+1,1)-1 -> 47026 | AI4: =DATE(YEAR(AH4),((INT((MONTH(AH4+3)-1)/3)+1)*3)+1,1)-1 -> 47118 | AJ4: =DATE(YEAR(AI4+1),((INT((MONTH(AI4+3)-1)/3)+1)*3)+1,1)-1 -> 47208 | AK4: =DATE(YEAR(AJ4),((INT((MONTH(AJ4+3)-1)/3)+1)*3)+1,1)-1 -> 47299 | AL4: =DATE(YEAR(AK4),((INT((MONTH(AK4+3)-1)/3)+1)*3)+1,1)-1 -> 47391 | AM4: =DATE(YEAR(AL4),((INT((MONTH(AL4+3)-1)/3)+1)*3)+1,1)-1 -> 47483 | AN4: =DATE(YEAR(AM4+1),((INT((MONTH(AM4+3)-1)/3)+1)*3)+1,1)-1 -> 47573 | AO4: =DATE(YEAR(AN4),((INT((MONTH(AN4+3)-1)/3)+1)*3)+1,1)-1 -> 47664 | AP4: =DATE(YEAR(AO4),((INT((MONTH(AO4+3)-1)/3)+1)*3)+1,1)-1 -> 47756 | AQ4: =DATE(YEAR(AP4),((INT((MONTH(AP4+3)-1)/3)+1)*3)+1,1)-1 -> 47848 | AR4: =DATE(YEAR(AQ4+1),((INT((MONTH(AQ4+3)-1)/3)+1)*3)+1,1)-1 -> 47938 | AS4: =DATE(YEAR(AR4),((INT((MONTH(AR4+3)-1)/3)+1)*3)+1,1)-1 -> 48029 | AT4: =DATE(YEAR(AS4),((INT((MONTH(AS4+3)-1)/3)+1)*3)+1,1)-1 -> 48121 | AU4: =DATE(YEAR(AT4),((INT((MONTH(AT4+3)-1)/3)+1)*3)+1,1)-1 -> 48213
B5: Fund | C5: ='Summary and Assumptions'!D11 -> 100000000 | D5: Q1 E | E5: Q2 E | F5: Q3 E | G5: Q4 E | H5: Q1 E | I5: Q2 E | J5: Q3 E | K5: Q4 E | L5: Q1 E | M5: Q2 E | N5: Q3 E | O5: Q4 E | P5: Q1 E | Q5: Q2 E | R5: Q3 E | S5: Q4 E | T5: Q1 E | U5: Q2 E | V5: Q3 E | W5: Q4 E | X5: Q1 E | Y5: Q2 E | Z5: Q3 E | AA5: Q4 E | AB5: Q1 E | AC5: Q2 E | AD5: Q3 E | AE5: Q4 E | AF5: Q1 E | AG5: Q2 E | AH5: Q3 E | AI5: Q4 E | AJ5: Q1 E | AK5: Q2 E | AL5: Q3 E | AM5: Q4 E | AN5: Q1 E | AO5: Q2 E | AP5: Q3 E | AQ5: Q4 E | AR5: Q1 E | AS5: Q2 E | AT5: Q3 E | AU5: Q4 E
A6: Cash Flow Model
A8: x | B8: Investments
B9: =IF(Portfolio!C7<>"",Portfolio!C7,"") -> 1 | C9: =IF(Portfolio!D7<>"",Portfolio!D7,"") -> Company 1 | D9: =SUMPRODUCT((Portfolio!$F$7:$J$7=D$4)*(Portfolio!$F$9:$J$9)) -> 1250000 | E9: =SUMPRODUCT((Portfolio!$F$7:$J$7=E$4)*(Portfolio!$F$9:$J$9)) -> 0 | F9: =SUMPRODUCT((Portfolio!$F$7:$J$7=F$4)*(Portfolio!$F$9:$J$9)) -> 0 | G9: =SUMPRODUCT((Portfolio!$F$7:$J$7=G$4)*(Portfolio!$F$9:$J$9)) -> 0 | H9: =SUMPRODUCT((Portfolio!$F$7:$J$7=H$4)*(Portfolio!$F$9:$J$9)) -> 0 | I9: =SUMPRODUCT((Portfolio!$F$7:$J$7=I$4)*(Portfolio!$F$9:$J$9)) -> 112500 | J9: =SUMPRODUCT((Portfolio!$F$7:$J$7=J$4)*(Portfolio!$F$9:$J$9)) -> 937500 | K9: =SUMPRODUCT((Portfolio!$F$7:$J$7=K$4)*(Portfolio!$F$9:$J$9)) -> 0 | ... AU9: =SUMPRODUCT((Portfolio!$F$7:$J$7=AU$4)*(Portfolio!$F$9:$J$9)) -> 0
B10: =IF(Portfolio!C10<>"",Portfolio!C10,"") -> 2 | C10: =IF(Portfolio!D10<>"",Portfolio!D10,"") -> Company 2 | D10: =SUMPRODUCT((Portfolio!$F$10:$J$10=D$4)*(Portfolio!$F$12:$J$12)) -> 1250000 | E10: =SUMPRODUCT((Portfolio!$F$10:$J$10=E$4)*(Portfolio!$F$12:$J$12)) -> 0 | F10: =SUMPRODUCT((Portfolio!$F$10:$J$10=F$4)*(Portfolio!$F$12:$J$12)) -> 0 | G10: =SUMPRODUCT((Portfolio!$F$10:$J$10=G$4)*(Portfolio!$F$12:$J$12)) -> 0 | H10: =SUMPRODUCT((Portfolio!$F$10:$J$10=H$4)*(Portfolio!$F$12:$J$12)) -> 0 | I10: =SUMPRODUCT((Portfolio!$F$10:$J$10=I$4)*(Portfolio!$F$12:$J$12)) -> 112500 | J10: =SUMPRODUCT((Portfolio!$F$10:$J$10=J$4)*(Portfolio!$F$12:$J$12)) -> 937500 | K10: =SUMPRODUCT((Portfolio!$F$10:$J$10=K$4)*(Portfolio!$F$12:$J$12)) -> 0 | ... AU10: =SUMPRODUCT((Portfolio!$F$10:$J$10=AU$4)*(Portfolio!$F$12:$J$12)) -> 0
B11: =IF(Portfolio!C13<>"",Portfolio!C13,"") -> 3 | C11: =IF(Portfolio!D13<>"",Portfolio!D13,"") -> Company 3 | D11: =SUMPRODUCT((Portfolio!$F$13:$J$13=D$4)*(Portfolio!$F$15:$J$15)) -> 0 | E11: =SUMPRODUCT((Portfolio!$F$13:$J$13=E$4)*(Portfolio!$F$15:$J$15)) -> 1250000 | F11: =SUMPRODUCT((Portfolio!$F$13:$J$13=F$4)*(Portfolio!$F$15:$J$15)) -> 0 | G11: =SUMPRODUCT((Portfolio!$F$13:$J$13=G$4)*(Portfolio!$F$15:$J$15)) -> 0 | H11: =SUMPRODUCT((Portfolio!$F$13:$J$13=H$4)*(Portfolio!$F$15:$J$15)) -> 0 | I11: =SUMPRODUCT((Portfolio!$F$13:$J$13=I$4)*(Portfolio!$F$15:$J$15)) -> 0 | J11: =SUMPRODUCT((Portfolio!$F$13:$J$13=J$4)*(Portfolio!$F$15:$J$15)) -> 1050000 | K11: =SUMPRODUCT((Portfolio!$F$13:$J$13=K$4)*(Portfolio!$F$15:$J$15)) -> 0 | ... AU11: =SUMPRODUCT((Portfolio!$F$13:$J$13=AU$4)*(Portfolio!$F$15:$J$15)) -> 0
B12: =IF(Portfolio!C16<>"",Portfolio!C16,"") -> 4 | C12: =IF(Portfolio!D16<>"",Portfolio!D16,"") -> Company 4 | D12: =SUMPRODUCT((Portfolio!$F$16:$J$16=D$4)*(Portfolio!$F$18:$J$18)) -> 0 | E12: =SUMPRODUCT((Portfolio!$F$16:$J$16=E$4)*(Portfolio!$F$18:$J$18)) -> 1250000 | F12: =SUMPRODUCT((Portfolio!$F$16:$J$16=F$4)*(Portfolio!$F$18:$J$18)) -> 0 | G12: =SUMPRODUCT((Portfolio!$F$16:$J$16=G$4)*(Portfolio!$F$18:$J$18)) -> 0 | H12: =SUMPRODUCT((Portfolio!$F$16:$J$16=H$4)*(Portfolio!$F$18:$J$18)) -> 0 | I12: =SUMPRODUCT((Portfolio!$F$16:$J$16=I$4)*(Portfolio!$F$18:$J$18)) -> 0 | J12: =SUMPRODUCT((Portfolio!$F$16:$J$16=J$4)*(Portfolio!$F$18:$J$18)) -> 112500 | K12: =SUMPRODUCT((Portfolio!$F$16:$J$16=K$4)*(Portfolio!$F$18:$J$18)) -> 937500 | ... AU12: =SUMPRODUCT((Portfolio!$F$16:$J$16=AU$4)*(Portfolio!$F$18:$J$18)) -> 0
B13: =IF(Portfolio!C19<>"",Portfolio!C19,"") -> 5 | C13: =IF(Portfolio!D19<>"",Portfolio!D19,"") -> Company 5 | D13: =SUMPRODUCT((Portfolio!$F19:$J19=D$4)*(Portfolio!$F21:$J21)) -> 0 | E13: =SUMPRODUCT((Portfolio!$F19:$J19=E$4)*(Portfolio!$F21:$J21)) -> 1250000 | F13: =SUMPRODUCT((Portfolio!$F19:$J19=F$4)*(Portfolio!$F21:$J21)) -> 0 | G13: =SUMPRODUCT((Portfolio!$F19:$J19=G$4)*(Portfolio!$F21:$J21)) -> 0 | H13: =SUMPRODUCT((Portfolio!$F19:$J19=H$4)*(Portfolio!$F21:$J21)) -> 0 | I13: =SUMPRODUCT((Portfolio!$F19:$J19=I$4)*(Portfolio!$F21:$J21)) -> 0 | J13: =SUMPRODUCT((Portfolio!$F19:$J19=J$4)*(Portfolio!$F21:$J21)) -> 112500 | K13: =SUMPRODUCT((Portfolio!$F19:$J19=K$4)*(Portfolio!$F21:$J21)) -> 937500 | ... AU13: =SUMPRODUCT((Portfolio!$F19:$J19=AU$4)*(Portfolio!$F21:$J21)) -> 0
B14: =IF(Portfolio!C22<>"",Portfolio!C22,"") -> 6 | C14: =IF(Portfolio!D22<>"",Portfolio!D22,"") -> Company 6 | D14: =SUMPRODUCT((Portfolio!$F22:$J22=D$4)*(Portfolio!$F24:$J24)) -> 0 | E14: =SUMPRODUCT((Portfolio!$F22:$J22=E$4)*(Portfolio!$F24:$J24)) -> 0 | F14: =SUMPRODUCT((Portfolio!$F22:$J22=F$4)*(Portfolio!$F24:$J24)) -> 1250000 | G14: =SUMPRODUCT((Portfolio!$F22:$J22=G$4)*(Portfolio!$F24:$J24)) -> 0 | H14: =SUMPRODUCT((Portfolio!$F22:$J22=H$4)*(Portfolio!$F24:$J24)) -> 0 | I14: =SUMPRODUCT((Portfolio!$F22:$J22=I$4)*(Portfolio!$F24:$J24)) -> 0 | J14: =SUMPRODUCT((Portfolio!$F22:$J22=J$4)*(Portfolio!$F24:$J24)) -> 0 | K14: =SUMPRODUCT((Portfolio!$F22:$J22=K$4)*(Portfolio!$F24:$J24)) -> 112500 | ... AU14: =SUMPRODUCT((Portfolio!$F22:$J22=AU$4)*(Portfolio!$F24:$J24)) -> 0
B15: =IF(Portfolio!C25<>"",Portfolio!C25,"") -> 7 | C15: =IF(Portfolio!D25<>"",Portfolio!D25,"") -> Company 7 | D15: =SUMPRODUCT((Portfolio!$F25:$J25=D$4)*(Portfolio!$F27:$J27)) -> 0 | E15: =SUMPRODUCT((Portfolio!$F25:$J25=E$4)*(Portfolio!$F27:$J27)) -> 0 | F15: =SUMPRODUCT((Portfolio!$F25:$J25=F$4)*(Portfolio!$F27:$J27)) -> 1250000 | G15: =SUMPRODUCT((Portfolio!$F25:$J25=G$4)*(Portfolio!$F27:$J27)) -> 0 | H15: =SUMPRODUCT((Portfolio!$F25:$J25=H$4)*(Portfolio!$F27:$J27)) -> 0 | I15: =SUMPRODUCT((Portfolio!$F25:$J25=I$4)*(Portfolio!$F27:$J27)) -> 0 | J15: =SUMPRODUCT((Portfolio!$F25:$J25=J$4)*(Portfolio!$F27:$J27)) -> 0 | K15: =SUMPRODUCT((Portfolio!$F25:$J25=K$4)*(Portfolio!$F27:$J27)) -> 112500 | ... AU15: =SUMPRODUCT((Portfolio!$F25:$J25=AU$4)*(Portfolio!$F27:$J27)) -> 0
B16: =IF(Portfolio!C28<>"",Portfolio!C28,"") -> 8 | C16: =IF(Portfolio!D28<>"",Portfolio!D28,"") -> Company 8 | D16: =SUMPRODUCT((Portfolio!$F28:$J28=D$4)*(Portfolio!$F30:$J30)) -> 0 | E16: =SUMPRODUCT((Portfolio!$F28:$J28=E$4)*(Portfolio!$F30:$J30)) -> 0 | F16: =SUMPRODUCT((Portfolio!$F28:$J28=F$4)*(Portfolio!$F30:$J30)) -> 0 | G16: =SUMPRODUCT((Portfolio!$F28:$J28=G$4)*(Portfolio!$F30:$J30)) -> 1250000 | H16: =SUMPRODUCT((Portfolio!$F28:$J28=H$4)*(Portfolio!$F30:$J30)) -> 0 | I16: =SUMPRODUCT((Portfolio!$F28:$J28=I$4)*(Portfolio!$F30:$J30)) -> 0 | J16: =SUMPRODUCT((Portfolio!$F28:$J28=J$4)*(Portfolio!$F30:$J30)) -> 0 | K16: =SUMPRODUCT((Portfolio!$F28:$J28=K$4)*(Portfolio!$F30:$J30)) -> 0 | ... AU16: =SUMPRODUCT((Portfolio!$F28:$J28=AU$4)*(Portfolio!$F30:$J30)) -> 0
B17: =IF(Portfolio!C31<>"",Portfolio!C31,"") -> 9 | C17: =IF(Portfolio!D31<>"",Portfolio!D31,"") -> Company 9 | D17: =SUMPRODUCT((Portfolio!$F31:$J31=D$4)*(Portfolio!$F33:$J33)) -> 0 | E17: =SUMPRODUCT((Portfolio!$F31:$J31=E$4)*(Portfolio!$F33:$J33)) -> 0 | F17: =SUMPRODUCT((Portfolio!$F31:$J31=F$4)*(Portfolio!$F33:$J33)) -> 0 | G17: =SUMPRODUCT((Portfolio!$F31:$J31=G$4)*(Portfolio!$F33:$J33)) -> 1250000 | H17: =SUMPRODUCT((Portfolio!$F31:$J31=H$4)*(Portfolio!$F33:$J33)) -> 0 | I17: =SUMPRODUCT((Portfolio!$F31:$J31=I$4)*(Portfolio!$F33:$J33)) -> 0 | J17: =SUMPRODUCT((Portfolio!$F31:$J31=J$4)*(Portfolio!$F33:$J33)) -> 0 | K17: =SUMPRODUCT((Portfolio!$F31:$J31=K$4)*(Portfolio!$F33:$J33)) -> 0 | ... AU17: =SUMPRODUCT((Portfolio!$F31:$J31=AU$4)*(Portfolio!$F33:$J33)) -> 0
B18: =IF(Portfolio!C34<>"",Portfolio!C34,"") -> 10 | C18: =IF(Portfolio!D34<>"",Portfolio!D34,"") -> Company 10 | D18: =SUMPRODUCT((Portfolio!$F34:$J34=D$4)*(Portfolio!$F36:$J36)) -> 0 | E18: =SUMPRODUCT((Portfolio!$F34:$J34=E$4)*(Portfolio!$F36:$J36)) -> 0 | F18: =SUMPRODUCT((Portfolio!$F34:$J34=F$4)*(Portfolio!$F36:$J36)) -> 0 | G18: =SUMPRODUCT((Portfolio!$F34:$J34=G$4)*(Portfolio!$F36:$J36)) -> 1250000 | H18: =SUMPRODUCT((Portfolio!$F34:$J34=H$4)*(Portfolio!$F36:$J36)) -> 0 | I18: =SUMPRODUCT((Portfolio!$F34:$J34=I$4)*(Portfolio!$F36:$J36)) -> 0 | J18: =SUMPRODUCT((Portfolio!$F34:$J34=J$4)*(Portfolio!$F36:$J36)) -> 0 | K18: =SUMPRODUCT((Portfolio!$F34:$J34=K$4)*(Portfolio!$F36:$J36)) -> 0 | ... AU18: =SUMPRODUCT((Portfolio!$F34:$J34=AU$4)*(Portfolio!$F36:$J36)) -> 0
B19: =IF(Portfolio!C37<>"",Portfolio!C37,"") -> 11 | C19: =IF(Portfolio!D37<>"",Portfolio!D37,"") -> Company 11 | D19: =SUMPRODUCT((Portfolio!$F37:$J37=D$4)*(Portfolio!$F39:$J39)) -> 0 | E19: =SUMPRODUCT((Portfolio!$F37:$J37=E$4)*(Portfolio!$F39:$J39)) -> 0 | F19: =SUMPRODUCT((Portfolio!$F37:$J37=F$4)*(Portfolio!$F39:$J39)) -> 0 | G19: =SUMPRODUCT((Portfolio!$F37:$J37=G$4)*(Portfolio!$F39:$J39)) -> 0 | H19: =SUMPRODUCT((Portfolio!$F37:$J37=H$4)*(Portfolio!$F39:$J39)) -> 1250000 | I19: =SUMPRODUCT((Portfolio!$F37:$J37=I$4)*(Portfolio!$F39:$J39)) -> 0 | J19: =SUMPRODUCT((Portfolio!$F37:$J37=J$4)*(Portfolio!$F39:$J39)) -> 0 | K19: =SUMPRODUCT((Portfolio!$F37:$J37=K$4)*(Portfolio!$F39:$J39)) -> 0 | ... AU19: =SUMPRODUCT((Portfolio!$F37:$J37=AU$4)*(Portfolio!$F39:$J39)) -> 0
B20: =IF(Portfolio!C40<>"",Portfolio!C40,"") -> 12 | C20: =IF(Portfolio!D40<>"",Portfolio!D40,"") -> Company 12 | D20: =SUMPRODUCT((Portfolio!$F40:$J40=D$4)*(Portfolio!$F42:$J42)) -> 0 | E20: =SUMPRODUCT((Portfolio!$F40:$J40=E$4)*(Portfolio!$F42:$J42)) -> 0 | F20: =SUMPRODUCT((Portfolio!$F40:$J40=F$4)*(Portfolio!$F42:$J42)) -> 0 | G20: =SUMPRODUCT((Portfolio!$F40:$J40=G$4)*(Portfolio!$F42:$J42)) -> 0 | H20: =SUMPRODUCT((Portfolio!$F40:$J40=H$4)*(Portfolio!$F42:$J42)) -> 1250000 | I20: =SUMPRODUCT((Portfolio!$F40:$J40=I$4)*(Portfolio!$F42:$J42)) -> 0 | J20: =SUMPRODUCT((Portfolio!$F40:$J40=J$4)*(Portfolio!$F42:$J42)) -> 0 | K20: =SUMPRODUCT((Portfolio!$F40:$J40=K$4)*(Portfolio!$F42:$J42)) -> 0 | ... AU20: =SUMPRODUCT((Portfolio!$F40:$J40=AU$4)*(Portfolio!$F42:$J42)) -> 0
B21: =IF(Portfolio!C43<>"",Portfolio!C43,"") -> 13 | C21: =IF(Portfolio!D43<>"",Portfolio!D43,"") -> Company 13 | D21: =SUMPRODUCT((Portfolio!$F43:$J43=D$4)*(Portfolio!$F45:$J45)) -> 0 | E21: =SUMPRODUCT((Portfolio!$F43:$J43=E$4)*(Portfolio!$F45:$J45)) -> 0 | F21: =SUMPRODUCT((Portfolio!$F43:$J43=F$4)*(Portfolio!$F45:$J45)) -> 0 | G21: =SUMPRODUCT((Portfolio!$F43:$J43=G$4)*(Portfolio!$F45:$J45)) -> 0 | H21: =SUMPRODUCT((Portfolio!$F43:$J43=H$4)*(Portfolio!$F45:$J45)) -> 0 | I21: =SUMPRODUCT((Portfolio!$F43:$J43=I$4)*(Portfolio!$F45:$J45)) -> 1250000 | J21: =SUMPRODUCT((Portfolio!$F43:$J43=J$4)*(Portfolio!$F45:$J45)) -> 0 | K21: =SUMPRODUCT((Portfolio!$F43:$J43=K$4)*(Portfolio!$F45:$J45)) -> 0 | ... AU21: =SUMPRODUCT((Portfolio!$F43:$J43=AU$4)*(Portfolio!$F45:$J45)) -> 0
B22: =IF(Portfolio!C46<>"",Portfolio!C46,"") -> 14 | C22: =IF(Portfolio!D46<>"",Portfolio!D46,"") -> Company 14 | D22: =SUMPRODUCT((Portfolio!$F46:$J46=D$4)*(Portfolio!$F48:$J48)) -> 0 | E22: =SUMPRODUCT((Portfolio!$F46:$J46=E$4)*(Portfolio!$F48:$J48)) -> 0 | F22: =SUMPRODUCT((Portfolio!$F46:$J46=F$4)*(Portfolio!$F48:$J48)) -> 0 | G22: =SUMPRODUCT((Portfolio!$F46:$J46=G$4)*(Portfolio!$F48:$J48)) -> 0 | H22: =SUMPRODUCT((Portfolio!$F46:$J46=H$4)*(Portfolio!$F48:$J48)) -> 0 | I22: =SUMPRODUCT((Portfolio!$F46:$J46=I$4)*(Portfolio!$F48:$J48)) -> 1250000 | J22: =SUMPRODUCT((Portfolio!$F46:$J46=J$4)*(Portfolio!$F48:$J48)) -> 0 | K22: =SUMPRODUCT((Portfolio!$F46:$J46=K$4)*(Portfolio!$F48:$J48)) -> 0 | ... AU22: =SUMPRODUCT((Portfolio!$F46:$J46=AU$4)*(Portfolio!$F48:$J48)) -> 0
B23: =IF(Portfolio!C49<>"",Portfolio!C49,"") -> 15 | C23: =IF(Portfolio!D49<>"",Portfolio!D49,"") -> Company 15 | D23: =SUMPRODUCT((Portfolio!$F49:$J49=D$4)*(Portfolio!$F51:$J51)) -> 0 | E23: =SUMPRODUCT((Portfolio!$F49:$J49=E$4)*(Portfolio!$F51:$J51)) -> 0 | F23: =SUMPRODUCT((Portfolio!$F49:$J49=F$4)*(Portfolio!$F51:$J51)) -> 0 | G23: =SUMPRODUCT((Portfolio!$F49:$J49=G$4)*(Portfolio!$F51:$J51)) -> 0 | H23: =SUMPRODUCT((Portfolio!$F49:$J49=H$4)*(Portfolio!$F51:$J51)) -> 0 | I23: =SUMPRODUCT((Portfolio!$F49:$J49=I$4)*(Portfolio!$F51:$J51)) -> 1250000 | J23: =SUMPRODUCT((Portfolio!$F49:$J49=J$4)*(Portfolio!$F51:$J51)) -> 0 | K23: =SUMPRODUCT((Portfolio!$F49:$J49=K$4)*(Portfolio!$F51:$J51)) -> 0 | ... AU23: =SUMPRODUCT((Portfolio!$F49:$J49=AU$4)*(Portfolio!$F51:$J51)) -> 0
B24: =IF(Portfolio!C52<>"",Portfolio!C52,"") -> 16 | C24: =IF(Portfolio!D52<>"",Portfolio!D52,"") -> Company 16 | D24: =SUMPRODUCT((Portfolio!$F52:$J52=D$4)*(Portfolio!$F54:$J54)) -> 0 | E24: =SUMPRODUCT((Portfolio!$F52:$J52=E$4)*(Portfolio!$F54:$J54)) -> 0 | F24: =SUMPRODUCT((Portfolio!$F52:$J52=F$4)*(Portfolio!$F54:$J54)) -> 0 | G24: =SUMPRODUCT((Portfolio!$F52:$J52=G$4)*(Portfolio!$F54:$J54)) -> 0 | H24: =SUMPRODUCT((Portfolio!$F52:$J52=H$4)*(Portfolio!$F54:$J54)) -> 0 | I24: =SUMPRODUCT((Portfolio!$F52:$J52=I$4)*(Portfolio!$F54:$J54)) -> 0 | J24: =SUMPRODUCT((Portfolio!$F52:$J52=J$4)*(Portfolio!$F54:$J54)) -> 1250000 | K24: =SUMPRODUCT((Portfolio!$F52:$J52=K$4)*(Portfolio!$F54:$J54)) -> 0 | ... AU24: =SUMPRODUCT((Portfolio!$F52:$J52=AU$4)*(Portfolio!$F54:$J54)) -> 0
B25: =IF(Portfolio!C55<>"",Portfolio!C55,"") -> 17 | C25: =IF(Portfolio!D55<>"",Portfolio!D55,"") -> Company 17 | D25: =SUMPRODUCT((Portfolio!$F55:$J55=D$4)*(Portfolio!$F57:$J57)) -> 0 | E25: =SUMPRODUCT((Portfolio!$F55:$J55=E$4)*(Portfolio!$F57:$J57)) -> 0 | F25: =SUMPRODUCT((Portfolio!$F55:$J55=F$4)*(Portfolio!$F57:$J57)) -> 0 | G25: =SUMPRODUCT((Portfolio!$F55:$J55=G$4)*(Portfolio!$F57:$J57)) -> 0 | H25: =SUMPRODUCT((Portfolio!$F55:$J55=H$4)*(Portfolio!$F57:$J57)) -> 0 | I25: =SUMPRODUCT((Portfolio!$F55:$J55=I$4)*(Portfolio!$F57:$J57)) -> 0 | J25: =SUMPRODUCT((Portfolio!$F55:$J55=J$4)*(Portfolio!$F57:$J57)) -> 1250000 | K25: =SUMPRODUCT((Portfolio!$F55:$J55=K$4)*(Portfolio!$F57:$J57)) -> 0 | ... AU25: =SUMPRODUCT((Portfolio!$F55:$J55=AU$4)*(Portfolio!$F57:$J57)) -> 0
B26: =IF(Portfolio!C58<>"",Portfolio!C58,"") -> 18 | C26: =IF(Portfolio!D58<>"",Portfolio!D58,"") -> Company 18 | D26: =SUMPRODUCT((Portfolio!$F58:$J58=D$4)*(Portfolio!$F60:$J60)) -> 0 | E26: =SUMPRODUCT((Portfolio!$F58:$J58=E$4)*(Portfolio!$F60:$J60)) -> 0 | F26: =SUMPRODUCT((Portfolio!$F58:$J58=F$4)*(Portfolio!$F60:$J60)) -> 0 | G26: =SUMPRODUCT((Portfolio!$F58:$J58=G$4)*(Portfolio!$F60:$J60)) -> 0 | H26: =SUMPRODUCT((Portfolio!$F58:$J58=H$4)*(Portfolio!$F60:$J60)) -> 0 | I26: =SUMPRODUCT((Portfolio!$F58:$J58=I$4)*(Portfolio!$F60:$J60)) -> 0 | J26: =SUMPRODUCT((Portfolio!$F58:$J58=J$4)*(Portfolio!$F60:$J60)) -> 1250000 | K26: =SUMPRODUCT((Portfolio!$F58:$J58=K$4)*(Portfolio!$F60:$J60)) -> 0 | ... AU26: =SUMPRODUCT((Portfolio!$F58:$J58=AU$4)*(Portfolio!$F60:$J60)) -> 0
B27: =IF(Portfolio!C61<>"",Portfolio!C61,"") -> 19 | C27: =IF(Portfolio!D61<>"",Portfolio!D61,"") -> Company 19 | D27: =SUMPRODUCT((Portfolio!$F61:$J61=D$4)*(Portfolio!$F63:$J63)) -> 0 | E27: =SUMPRODUCT((Portfolio!$F61:$J61=E$4)*(Portfolio!$F63:$J63)) -> 0 | F27: =SUMPRODUCT((Portfolio!$F61:$J61=F$4)*(Portfolio!$F63:$J63)) -> 0 | G27: =SUMPRODUCT((Portfolio!$F61:$J61=G$4)*(Portfolio!$F63:$J63)) -> 0 | H27: =SUMPRODUCT((Portfolio!$F61:$J61=H$4)*(Portfolio!$F63:$J63)) -> 0 | I27: =SUMPRODUCT((Portfolio!$F61:$J61=I$4)*(Portfolio!$F63:$J63)) -> 0 | J27: =SUMPRODUCT((Portfolio!$F61:$J61=J$4)*(Portfolio!$F63:$J63)) -> 0 | K27: =SUMPRODUCT((Portfolio!$F61:$J61=K$4)*(Portfolio!$F63:$J63)) -> 1250000 | ... AU27: =SUMPRODUCT((Portfolio!$F61:$J61=AU$4)*(Portfolio!$F63:$J63)) -> 0
B28: =IF(Portfolio!C64<>"",Portfolio!C64,"") -> 20 | C28: =IF(Portfolio!D64<>"",Portfolio!D64,"") -> Company 20 | D28: =SUMPRODUCT((Portfolio!$F64:$J64=D$4)*(Portfolio!$F66:$J66)) -> 0 | E28: =SUMPRODUCT((Portfolio!$F64:$J64=E$4)*(Portfolio!$F66:$J66)) -> 0 | F28: =SUMPRODUCT((Portfolio!$F64:$J64=F$4)*(Portfolio!$F66:$J66)) -> 0 | G28: =SUMPRODUCT((Portfolio!$F64:$J64=G$4)*(Portfolio!$F66:$J66)) -> 0 | H28: =SUMPRODUCT((Portfolio!$F64:$J64=H$4)*(Portfolio!$F66:$J66)) -> 0 | I28: =SUMPRODUCT((Portfolio!$F64:$J64=I$4)*(Portfolio!$F66:$J66)) -> 0 | J28: =SUMPRODUCT((Portfolio!$F64:$J64=J$4)*(Portfolio!$F66:$J66)) -> 0 | K28: =SUMPRODUCT((Portfolio!$F64:$J64=K$4)*(Portfolio!$F66:$J66)) -> 1250000 | ... AU28: =SUMPRODUCT((Portfolio!$F64:$J64=AU$4)*(Portfolio!$F66:$J66)) -> 0
B29: =IF(Portfolio!C67<>"",Portfolio!C67,"") -> 21 | C29: =IF(Portfolio!D67<>"",Portfolio!D67,"") -> Company 21 | D29: =SUMPRODUCT((Portfolio!$F67:$J67=D$4)*(Portfolio!$F69:$J69)) -> 0 | E29: =SUMPRODUCT((Portfolio!$F67:$J67=E$4)*(Portfolio!$F69:$J69)) -> 0 | F29: =SUMPRODUCT((Portfolio!$F67:$J67=F$4)*(Portfolio!$F69:$J69)) -> 0 | G29: =SUMPRODUCT((Portfolio!$F67:$J67=G$4)*(Portfolio!$F69:$J69)) -> 0 | H29: =SUMPRODUCT((Portfolio!$F67:$J67=H$4)*(Portfolio!$F69:$J69)) -> 0 | I29: =SUMPRODUCT((Portfolio!$F67:$J67=I$4)*(Portfolio!$F69:$J69)) -> 0 | J29: =SUMPRODUCT((Portfolio!$F67:$J67=J$4)*(Portfolio!$F69:$J69)) -> 0 | K29: =SUMPRODUCT((Portfolio!$F67:$J67=K$4)*(Portfolio!$F69:$J69)) -> 0 | ... AU29: =SUMPRODUCT((Portfolio!$F67:$J67=AU$4)*(Portfolio!$F69:$J69)) -> 0
B30: =IF(Portfolio!C70<>"",Portfolio!C70,"") -> 22 | C30: =IF(Portfolio!D70<>"",Portfolio!D70,"") -> Company 22 | D30: =SUMPRODUCT((Portfolio!$F70:$J70=D$4)*(Portfolio!$F72:$J72)) -> 0 | E30: =SUMPRODUCT((Portfolio!$F70:$J70=E$4)*(Portfolio!$F72:$J72)) -> 0 | F30: =SUMPRODUCT((Portfolio!$F70:$J70=F$4)*(Portfolio!$F72:$J72)) -> 0 | G30: =SUMPRODUCT((Portfolio!$F70:$J70=G$4)*(Portfolio!$F72:$J72)) -> 0 | H30: =SUMPRODUCT((Portfolio!$F70:$J70=H$4)*(Portfolio!$F72:$J72)) -> 0 | I30: =SUMPRODUCT((Portfolio!$F70:$J70=I$4)*(Portfolio!$F72:$J72)) -> 0 | J30: =SUMPRODUCT((Portfolio!$F70:$J70=J$4)*(Portfolio!$F72:$J72)) -> 0 | K30: =SUMPRODUCT((Portfolio!$F70:$J70=K$4)*(Portfolio!$F72:$J72)) -> 0 | ... AU30: =SUMPRODUCT((Portfolio!$F70:$J70=AU$4)*(Portfolio!$F72:$J72)) -> 0
B31: =IF(Portfolio!C73<>"",Portfolio!C73,"") -> 23 | C31: =IF(Portfolio!D73<>"",Portfolio!D73,"") -> Company 23 | D31: =SUMPRODUCT((Portfolio!$F73:$J73=D$4)*(Portfolio!$F75:$J75)) -> 0 | E31: =SUMPRODUCT((Portfolio!$F73:$J73=E$4)*(Portfolio!$F75:$J75)) -> 0 | F31: =SUMPRODUCT((Portfolio!$F73:$J73=F$4)*(Portfolio!$F75:$J75)) -> 0 | G31: =SUMPRODUCT((Portfolio!$F73:$J73=G$4)*(Portfolio!$F75:$J75)) -> 0 | H31: =SUMPRODUCT((Portfolio!$F73:$J73=H$4)*(Portfolio!$F75:$J75)) -> 0 | I31: =SUMPRODUCT((Portfolio!$F73:$J73=I$4)*(Portfolio!$F75:$J75)) -> 0 | J31: =SUMPRODUCT((Portfolio!$F73:$J73=J$4)*(Portfolio!$F75:$J75)) -> 0 | K31: =SUMPRODUCT((Portfolio!$F73:$J73=K$4)*(Portfolio!$F75:$J75)) -> 0 | ... AU31: =SUMPRODUCT((Portfolio!$F73:$J73=AU$4)*(Portfolio!$F75:$J75)) -> 0
B32: =IF(Portfolio!C76<>"",Portfolio!C76,"") -> 24 | C32: =IF(Portfolio!D76<>"",Portfolio!D76,"") -> Company 24 | D32: =SUMPRODUCT((Portfolio!$F76:$J76=D$4)*(Portfolio!$F78:$J78)) -> 0 | E32: =SUMPRODUCT((Portfolio!$F76:$J76=E$4)*(Portfolio!$F78:$J78)) -> 0 | F32: =SUMPRODUCT((Portfolio!$F76:$J76=F$4)*(Portfolio!$F78:$J78)) -> 0 | G32: =SUMPRODUCT((Portfolio!$F76:$J76=G$4)*(Portfolio!$F78:$J78)) -> 0 | H32: =SUMPRODUCT((Portfolio!$F76:$J76=H$4)*(Portfolio!$F78:$J78)) -> 0 | I32: =SUMPRODUCT((Portfolio!$F76:$J76=I$4)*(Portfolio!$F78:$J78)) -> 0 | J32: =SUMPRODUCT((Portfolio!$F76:$J76=J$4)*(Portfolio!$F78:$J78)) -> 0 | K32: =SUMPRODUCT((Portfolio!$F76:$J76=K$4)*(Portfolio!$F78:$J78)) -> 0 | ... AU32: =SUMPRODUCT((Portfolio!$F76:$J76=AU$4)*(Portfolio!$F78:$J78)) -> 0
B33: =IF(Portfolio!C79<>"",Portfolio!C79,"") -> 25 | C33: =IF(Portfolio!D79<>"",Portfolio!D79,"") -> Company 25 | D33: =SUMPRODUCT((Portfolio!$F79:$J79=D$4)*(Portfolio!$F81:$J81)) -> 0 | E33: =SUMPRODUCT((Portfolio!$F79:$J79=E$4)*(Portfolio!$F81:$J81)) -> 0 | F33: =SUMPRODUCT((Portfolio!$F79:$J79=F$4)*(Portfolio!$F81:$J81)) -> 0 | G33: =SUMPRODUCT((Portfolio!$F79:$J79=G$4)*(Portfolio!$F81:$J81)) -> 0 | H33: =SUMPRODUCT((Portfolio!$F79:$J79=H$4)*(Portfolio!$F81:$J81)) -> 0 | I33: =SUMPRODUCT((Portfolio!$F79:$J79=I$4)*(Portfolio!$F81:$J81)) -> 0 | J33: =SUMPRODUCT((Portfolio!$F79:$J79=J$4)*(Portfolio!$F81:$J81)) -> 0 | K33: =SUMPRODUCT((Portfolio!$F79:$J79=K$4)*(Portfolio!$F81:$J81)) -> 0 | ... AU33: =SUMPRODUCT((Portfolio!$F79:$J79=AU$4)*(Portfolio!$F81:$J81)) -> 0
B34: =IF(Portfolio!C82<>"",Portfolio!C82,"") -> 26 | C34: =IF(Portfolio!D82<>"",Portfolio!D82,"") -> Company 26 | D34: =SUMPRODUCT((Portfolio!$F82:$J82=D$4)*(Portfolio!$F84:$J84)) -> 0 | E34: =SUMPRODUCT((Portfolio!$F82:$J82=E$4)*(Portfolio!$F84:$J84)) -> 0 | F34: =SUMPRODUCT((Portfolio!$F82:$J82=F$4)*(Portfolio!$F84:$J84)) -> 0 | G34: =SUMPRODUCT((Portfolio!$F82:$J82=G$4)*(Portfolio!$F84:$J84)) -> 0 | H34: =SUMPRODUCT((Portfolio!$F82:$J82=H$4)*(Portfolio!$F84:$J84)) -> 0 | I34: =SUMPRODUCT((Portfolio!$F82:$J82=I$4)*(Portfolio!$F84:$J84)) -> 0 | J34: =SUMPRODUCT((Portfolio!$F82:$J82=J$4)*(Portfolio!$F84:$J84)) -> 0 | K34: =SUMPRODUCT((Portfolio!$F82:$J82=K$4)*(Portfolio!$F84:$J84)) -> 0 | ... AU34: =SUMPRODUCT((Portfolio!$F82:$J82=AU$4)*(Portfolio!$F84:$J84)) -> 0
B35: =IF(Portfolio!C85<>"",Portfolio!C85,"") -> 27 | C35: =IF(Portfolio!D85<>"",Portfolio!D85,"") -> Company 27 | D35: =SUMPRODUCT((Portfolio!$F85:$J85=D$4)*(Portfolio!$F87:$J87)) -> 0 | E35: =SUMPRODUCT((Portfolio!$F85:$J85=E$4)*(Portfolio!$F87:$J87)) -> 0 | F35: =SUMPRODUCT((Portfolio!$F85:$J85=F$4)*(Portfolio!$F87:$J87)) -> 0 | G35: =SUMPRODUCT((Portfolio!$F85:$J85=G$4)*(Portfolio!$F87:$J87)) -> 0 | H35: =SUMPRODUCT((Portfolio!$F85:$J85=H$4)*(Portfolio!$F87:$J87)) -> 0 | I35: =SUMPRODUCT((Portfolio!$F85:$J85=I$4)*(Portfolio!$F87:$J87)) -> 0 | J35: =SUMPRODUCT((Portfolio!$F85:$J85=J$4)*(Portfolio!$F87:$J87)) -> 0 | K35: =SUMPRODUCT((Portfolio!$F85:$J85=K$4)*(Portfolio!$F87:$J87)) -> 0 | ... AU35: =SUMPRODUCT((Portfolio!$F85:$J85=AU$4)*(Portfolio!$F87:$J87)) -> 0
B36: =IF(Portfolio!C88<>"",Portfolio!C88,"") -> 28 | C36: =IF(Portfolio!D88<>"",Portfolio!D88,"") -> Company 28 | D36: =SUMPRODUCT((Portfolio!$F88:$J88=D$4)*(Portfolio!$F90:$J90)) -> 0 | E36: =SUMPRODUCT((Portfolio!$F88:$J88=E$4)*(Portfolio!$F90:$J90)) -> 0 | F36: =SUMPRODUCT((Portfolio!$F88:$J88=F$4)*(Portfolio!$F90:$J90)) -> 0 | G36: =SUMPRODUCT((Portfolio!$F88:$J88=G$4)*(Portfolio!$F90:$J90)) -> 0 | H36: =SUMPRODUCT((Portfolio!$F88:$J88=H$4)*(Portfolio!$F90:$J90)) -> 0 | I36: =SUMPRODUCT((Portfolio!$F88:$J88=I$4)*(Portfolio!$F90:$J90)) -> 0 | J36: =SUMPRODUCT((Portfolio!$F88:$J88=J$4)*(Portfolio!$F90:$J90)) -> 0 | K36: =SUMPRODUCT((Portfolio!$F88:$J88=K$4)*(Portfolio!$F90:$J90)) -> 0 | ... AU36: =SUMPRODUCT((Portfolio!$F88:$J88=AU$4)*(Portfolio!$F90:$J90)) -> 0
B37: =IF(Portfolio!C91<>"",Portfolio!C91,"") -> 29 | C37: =IF(Portfolio!D91<>"",Portfolio!D91,"") -> Company 29 | D37: =SUMPRODUCT((Portfolio!$F91:$J91=D$4)*(Portfolio!$F93:$J93)) -> 0 | E37: =SUMPRODUCT((Portfolio!$F91:$J91=E$4)*(Portfolio!$F93:$J93)) -> 0 | F37: =SUMPRODUCT((Portfolio!$F91:$J91=F$4)*(Portfolio!$F93:$J93)) -> 0 | G37: =SUMPRODUCT((Portfolio!$F91:$J91=G$4)*(Portfolio!$F93:$J93)) -> 0 | H37: =SUMPRODUCT((Portfolio!$F91:$J91=H$4)*(Portfolio!$F93:$J93)) -> 0 | I37: =SUMPRODUCT((Portfolio!$F91:$J91=I$4)*(Portfolio!$F93:$J93)) -> 0 | J37: =SUMPRODUCT((Portfolio!$F91:$J91=J$4)*(Portfolio!$F93:$J93)) -> 0 | K37: =SUMPRODUCT((Portfolio!$F91:$J91=K$4)*(Portfolio!$F93:$J93)) -> 0 | ... AU37: =SUMPRODUCT((Portfolio!$F91:$J91=AU$4)*(Portfolio!$F93:$J93)) -> 0
B38: =IF(Portfolio!C94<>"",Portfolio!C94,"") -> 30 | C38: =IF(Portfolio!D94<>"",Portfolio!D94,"") -> Company 30 | D38: =SUMPRODUCT((Portfolio!$F94:$J94=D$4)*(Portfolio!$F96:$J96)) -> 0 | E38: =SUMPRODUCT((Portfolio!$F94:$J94=E$4)*(Portfolio!$F96:$J96)) -> 0 | F38: =SUMPRODUCT((Portfolio!$F94:$J94=F$4)*(Portfolio!$F96:$J96)) -> 0 | G38: =SUMPRODUCT((Portfolio!$F94:$J94=G$4)*(Portfolio!$F96:$J96)) -> 0 | H38: =SUMPRODUCT((Portfolio!$F94:$J94=H$4)*(Portfolio!$F96:$J96)) -> 0 | I38: =SUMPRODUCT((Portfolio!$F94:$J94=I$4)*(Portfolio!$F96:$J96)) -> 0 | J38: =SUMPRODUCT((Portfolio!$F94:$J94=J$4)*(Portfolio!$F96:$J96)) -> 0 | K38: =SUMPRODUCT((Portfolio!$F94:$J94=K$4)*(Portfolio!$F96:$J96)) -> 0 | ... AU38: =SUMPRODUCT((Portfolio!$F94:$J94=AU$4)*(Portfolio!$F96:$J96)) -> 0
B39: =IF(Portfolio!C97<>"",Portfolio!C97,"") -> 31 | C39: =IF(Portfolio!D97<>"",Portfolio!D97,"") -> Company 31 | D39: =SUMPRODUCT((Portfolio!$F97:$J97=D$4)*(Portfolio!$F99:$J99)) -> 0 | E39: =SUMPRODUCT((Portfolio!$F97:$J97=E$4)*(Portfolio!$F99:$J99)) -> 0 | F39: =SUMPRODUCT((Portfolio!$F97:$J97=F$4)*(Portfolio!$F99:$J99)) -> 0 | G39: =SUMPRODUCT((Portfolio!$F97:$J97=G$4)*(Portfolio!$F99:$J99)) -> 0 | H39: =SUMPRODUCT((Portfolio!$F97:$J97=H$4)*(Portfolio!$F99:$J99)) -> 0 | I39: =SUMPRODUCT((Portfolio!$F97:$J97=I$4)*(Portfolio!$F99:$J99)) -> 0 | J39: =SUMPRODUCT((Portfolio!$F97:$J97=J$4)*(Portfolio!$F99:$J99)) -> 0 | K39: =SUMPRODUCT((Portfolio!$F97:$J97=K$4)*(Portfolio!$F99:$J99)) -> 0 | ... AU39: =SUMPRODUCT((Portfolio!$F97:$J97=AU$4)*(Portfolio!$F99:$J99)) -> 0
B40: =IF(Portfolio!C100<>"",Portfolio!C100,"") -> 32 | C40: =IF(Portfolio!D100<>"",Portfolio!D100,"") -> Company 32 | D40: =SUMPRODUCT((Portfolio!$F100:$J100=D$4)*(Portfolio!$F102:$J102)) -> 0 | E40: =SUMPRODUCT((Portfolio!$F100:$J100=E$4)*(Portfolio!$F102:$J102)) -> 0 | F40: =SUMPRODUCT((Portfolio!$F100:$J100=F$4)*(Portfolio!$F102:$J102)) -> 0 | G40: =SUMPRODUCT((Portfolio!$F100:$J100=G$4)*(Portfolio!$F102:$J102)) -> 0 | H40: =SUMPRODUCT((Portfolio!$F100:$J100=H$4)*(Portfolio!$F102:$J102)) -> 0 | I40: =SUMPRODUCT((Portfolio!$F100:$J100=I$4)*(Portfolio!$F102:$J102)) -> 0 | J40: =SUMPRODUCT((Portfolio!$F100:$J100=J$4)*(Portfolio!$F102:$J102)) -> 0 | K40: =SUMPRODUCT((Portfolio!$F100:$J100=K$4)*(Portfolio!$F102:$J102)) -> 0 | ... AU40: =SUMPRODUCT((Portfolio!$F100:$J100=AU$4)*(Portfolio!$F102:$J102)) -> 0
B41: =IF(Portfolio!C103<>"",Portfolio!C103,"") -> 33 | C41: =IF(Portfolio!D103<>"",Portfolio!D103,"") -> Company 33 | D41: =SUMPRODUCT((Portfolio!$F103:$J103=D$4)*(Portfolio!$F105:$J105)) -> 0 | E41: =SUMPRODUCT((Portfolio!$F103:$J103=E$4)*(Portfolio!$F105:$J105)) -> 0 | F41: =SUMPRODUCT((Portfolio!$F103:$J103=F$4)*(Portfolio!$F105:$J105)) -> 0 | G41: =SUMPRODUCT((Portfolio!$F103:$J103=G$4)*(Portfolio!$F105:$J105)) -> 0 | H41: =SUMPRODUCT((Portfolio!$F103:$J103=H$4)*(Portfolio!$F105:$J105)) -> 0 | I41: =SUMPRODUCT((Portfolio!$F103:$J103=I$4)*(Portfolio!$F105:$J105)) -> 0 | J41: =SUMPRODUCT((Portfolio!$F103:$J103=J$4)*(Portfolio!$F105:$J105)) -> 0 | K41: =SUMPRODUCT((Portfolio!$F103:$J103=K$4)*(Portfolio!$F105:$J105)) -> 0 | ... AU41: =SUMPRODUCT((Portfolio!$F103:$J103=AU$4)*(Portfolio!$F105:$J105)) -> 0
B42: =IF(Portfolio!C106<>"",Portfolio!C106,"") -> 34 | C42: =IF(Portfolio!D106<>"",Portfolio!D106,"") -> Company 34 | D42: =SUMPRODUCT((Portfolio!$F106:$J106=D$4)*(Portfolio!$F108:$J108)) -> 0 | E42: =SUMPRODUCT((Portfolio!$F106:$J106=E$4)*(Portfolio!$F108:$J108)) -> 0 | F42: =SUMPRODUCT((Portfolio!$F106:$J106=F$4)*(Portfolio!$F108:$J108)) -> 0 | G42: =SUMPRODUCT((Portfolio!$F106:$J106=G$4)*(Portfolio!$F108:$J108)) -> 0 | H42: =SUMPRODUCT((Portfolio!$F106:$J106=H$4)*(Portfolio!$F108:$J108)) -> 0 | I42: =SUMPRODUCT((Portfolio!$F106:$J106=I$4)*(Portfolio!$F108:$J108)) -> 0 | J42: =SUMPRODUCT((Portfolio!$F106:$J106=J$4)*(Portfolio!$F108:$J108)) -> 0 | K42: =SUMPRODUCT((Portfolio!$F106:$J106=K$4)*(Portfolio!$F108:$J108)) -> 0 | ... AU42: =SUMPRODUCT((Portfolio!$F106:$J106=AU$4)*(Portfolio!$F108:$J108)) -> 0
B43: =IF(Portfolio!C109<>"",Portfolio!C109,"") -> 35 | C43: =IF(Portfolio!D109<>"",Portfolio!D109,"") -> Company 35 | D43: =SUMPRODUCT((Portfolio!$F109:$J109=D$4)*(Portfolio!$F111:$J111)) -> 0 | E43: =SUMPRODUCT((Portfolio!$F109:$J109=E$4)*(Portfolio!$F111:$J111)) -> 0 | F43: =SUMPRODUCT((Portfolio!$F109:$J109=F$4)*(Portfolio!$F111:$J111)) -> 0 | G43: =SUMPRODUCT((Portfolio!$F109:$J109=G$4)*(Portfolio!$F111:$J111)) -> 0 | H43: =SUMPRODUCT((Portfolio!$F109:$J109=H$4)*(Portfolio!$F111:$J111)) -> 0 | I43: =SUMPRODUCT((Portfolio!$F109:$J109=I$4)*(Portfolio!$F111:$J111)) -> 0 | J43: =SUMPRODUCT((Portfolio!$F109:$J109=J$4)*(Portfolio!$F111:$J111)) -> 0 | K43: =SUMPRODUCT((Portfolio!$F109:$J109=K$4)*(Portfolio!$F111:$J111)) -> 0 | ... AU43: =SUMPRODUCT((Portfolio!$F109:$J109=AU$4)*(Portfolio!$F111:$J111)) -> 0
B44: =IF(Portfolio!C112<>"",Portfolio!C112,"") -> 36 | C44: =IF(Portfolio!D112<>"",Portfolio!D112,"") | D44: =SUMPRODUCT((Portfolio!$F112:$J112=D$4)*(Portfolio!$F114:$J114)) -> 0 | E44: =SUMPRODUCT((Portfolio!$F112:$J112=E$4)*(Portfolio!$F114:$J114)) -> 0 | F44: =SUMPRODUCT((Portfolio!$F112:$J112=F$4)*(Portfolio!$F114:$J114)) -> 0 | G44: =SUMPRODUCT((Portfolio!$F112:$J112=G$4)*(Portfolio!$F114:$J114)) -> 0 | H44: =SUMPRODUCT((Portfolio!$F112:$J112=H$4)*(Portfolio!$F114:$J114)) -> 0 | I44: =SUMPRODUCT((Portfolio!$F112:$J112=I$4)*(Portfolio!$F114:$J114)) -> 0 | J44: =SUMPRODUCT((Portfolio!$F112:$J112=J$4)*(Portfolio!$F114:$J114)) -> 0 | K44: =SUMPRODUCT((Portfolio!$F112:$J112=K$4)*(Portfolio!$F114:$J114)) -> 0 | ... AU44: =SUMPRODUCT((Portfolio!$F112:$J112=AU$4)*(Portfolio!$F114:$J114)) -> 0
B45: =IF(Portfolio!C115<>"",Portfolio!C115,"") -> 37 | C45: =IF(Portfolio!D115<>"",Portfolio!D115,"") | D45: =SUMPRODUCT((Portfolio!$F115:$J115=D$4)*(Portfolio!$F117:$J117)) -> 0 | E45: =SUMPRODUCT((Portfolio!$F115:$J115=E$4)*(Portfolio!$F117:$J117)) -> 0 | F45: =SUMPRODUCT((Portfolio!$F115:$J115=F$4)*(Portfolio!$F117:$J117)) -> 0 | G45: =SUMPRODUCT((Portfolio!$F115:$J115=G$4)*(Portfolio!$F117:$J117)) -> 0 | H45: =SUMPRODUCT((Portfolio!$F115:$J115=H$4)*(Portfolio!$F117:$J117)) -> 0 | I45: =SUMPRODUCT((Portfolio!$F115:$J115=I$4)*(Portfolio!$F117:$J117)) -> 0 | J45: =SUMPRODUCT((Portfolio!$F115:$J115=J$4)*(Portfolio!$F117:$J117)) -> 0 | K45: =SUMPRODUCT((Portfolio!$F115:$J115=K$4)*(Portfolio!$F117:$J117)) -> 0 | ... AU45: =SUMPRODUCT((Portfolio!$F115:$J115=AU$4)*(Portfolio!$F117:$J117)) -> 0
B46: =IF(Portfolio!C118<>"",Portfolio!C118,"") -> 38 | C46: =IF(Portfolio!D118<>"",Portfolio!D118,"") | D46: =SUMPRODUCT((Portfolio!$F118:$J118=D$4)*(Portfolio!$F120:$J120)) -> 0 | E46: =SUMPRODUCT((Portfolio!$F118:$J118=E$4)*(Portfolio!$F120:$J120)) -> 0 | F46: =SUMPRODUCT((Portfolio!$F118:$J118=F$4)*(Portfolio!$F120:$J120)) -> 0 | G46: =SUMPRODUCT((Portfolio!$F118:$J118=G$4)*(Portfolio!$F120:$J120)) -> 0 | H46: =SUMPRODUCT((Portfolio!$F118:$J118=H$4)*(Portfolio!$F120:$J120)) -> 0 | I46: =SUMPRODUCT((Portfolio!$F118:$J118=I$4)*(Portfolio!$F120:$J120)) -> 0 | J46: =SUMPRODUCT((Portfolio!$F118:$J118=J$4)*(Portfolio!$F120:$J120)) -> 0 | K46: =SUMPRODUCT((Portfolio!$F118:$J118=K$4)*(Portfolio!$F120:$J120)) -> 0 | ... AU46: =SUMPRODUCT((Portfolio!$F118:$J118=AU$4)*(Portfolio!$F120:$J120)) -> 0
B47: =IF(Portfolio!C121<>"",Portfolio!C121,"") -> 39 | C47: =IF(Portfolio!D121<>"",Portfolio!D121,"") | D47: =SUMPRODUCT((Portfolio!$F121:$J121=D$4)*(Portfolio!$F123:$J123)) -> 0 | E47: =SUMPRODUCT((Portfolio!$F121:$J121=E$4)*(Portfolio!$F123:$J123)) -> 0 | F47: =SUMPRODUCT((Portfolio!$F121:$J121=F$4)*(Portfolio!$F123:$J123)) -> 0 | G47: =SUMPRODUCT((Portfolio!$F121:$J121=G$4)*(Portfolio!$F123:$J123)) -> 0 | H47: =SUMPRODUCT((Portfolio!$F121:$J121=H$4)*(Portfolio!$F123:$J123)) -> 0 | I47: =SUMPRODUCT((Portfolio!$F121:$J121=I$4)*(Portfolio!$F123:$J123)) -> 0 | J47: =SUMPRODUCT((Portfolio!$F121:$J121=J$4)*(Portfolio!$F123:$J123)) -> 0 | K47: =SUMPRODUCT((Portfolio!$F121:$J121=K$4)*(Portfolio!$F123:$J123)) -> 0 | ... AU47: =SUMPRODUCT((Portfolio!$F121:$J121=AU$4)*(Portfolio!$F123:$J123)) -> 0
B48: =IF(Portfolio!C124<>"",Portfolio!C124,"") -> 40 | C48: =IF(Portfolio!D124<>"",Portfolio!D124,"") | D48: =SUMPRODUCT((Portfolio!$F124:$J124=D$4)*(Portfolio!$F126:$J126)) -> 0 | E48: =SUMPRODUCT((Portfolio!$F124:$J124=E$4)*(Portfolio!$F126:$J126)) -> 0 | F48: =SUMPRODUCT((Portfolio!$F124:$J124=F$4)*(Portfolio!$F126:$J126)) -> 0 | G48: =SUMPRODUCT((Portfolio!$F124:$J124=G$4)*(Portfolio!$F126:$J126)) -> 0 | H48: =SUMPRODUCT((Portfolio!$F124:$J124=H$4)*(Portfolio!$F126:$J126)) -> 0 | I48: =SUMPRODUCT((Portfolio!$F124:$J124=I$4)*(Portfolio!$F126:$J126)) -> 0 | J48: =SUMPRODUCT((Portfolio!$F124:$J124=J$4)*(Portfolio!$F126:$J126)) -> 0 | K48: =SUMPRODUCT((Portfolio!$F124:$J124=K$4)*(Portfolio!$F126:$J126)) -> 0 | ... AU48: =SUMPRODUCT((Portfolio!$F124:$J124=AU$4)*(Portfolio!$F126:$J126)) -> 0
B49: =IF(Portfolio!C127<>"",Portfolio!C127,"") -> 41 | C49: =IF(Portfolio!D127<>"",Portfolio!D127,"") | D49: =SUMPRODUCT((Portfolio!$F127:$J127=D$4)*(Portfolio!$F129:$J129)) -> 0 | E49: =SUMPRODUCT((Portfolio!$F127:$J127=E$4)*(Portfolio!$F129:$J129)) -> 0 | F49: =SUMPRODUCT((Portfolio!$F127:$J127=F$4)*(Portfolio!$F129:$J129)) -> 0 | G49: =SUMPRODUCT((Portfolio!$F127:$J127=G$4)*(Portfolio!$F129:$J129)) -> 0 | H49: =SUMPRODUCT((Portfolio!$F127:$J127=H$4)*(Portfolio!$F129:$J129)) -> 0 | I49: =SUMPRODUCT((Portfolio!$F127:$J127=I$4)*(Portfolio!$F129:$J129)) -> 0 | J49: =SUMPRODUCT((Portfolio!$F127:$J127=J$4)*(Portfolio!$F129:$J129)) -> 0 | K49: =SUMPRODUCT((Portfolio!$F127:$J127=K$4)*(Portfolio!$F129:$J129)) -> 0 | ... AU49: =SUMPRODUCT((Portfolio!$F127:$J127=AU$4)*(Portfolio!$F129:$J129)) -> 0
B50: =IF(Portfolio!C130<>"",Portfolio!C130,"") -> 42 | C50: =IF(Portfolio!D130<>"",Portfolio!D130,"") | D50: =SUMPRODUCT((Portfolio!$F130:$J130=D$4)*(Portfolio!$F132:$J132)) -> 0 | E50: =SUMPRODUCT((Portfolio!$F130:$J130=E$4)*(Portfolio!$F132:$J132)) -> 0 | F50: =SUMPRODUCT((Portfolio!$F130:$J130=F$4)*(Portfolio!$F132:$J132)) -> 0 | G50: =SUMPRODUCT((Portfolio!$F130:$J130=G$4)*(Portfolio!$F132:$J132)) -> 0 | H50: =SUMPRODUCT((Portfolio!$F130:$J130=H$4)*(Portfolio!$F132:$J132)) -> 0 | I50: =SUMPRODUCT((Portfolio!$F130:$J130=I$4)*(Portfolio!$F132:$J132)) -> 0 | J50: =SUMPRODUCT((Portfolio!$F130:$J130=J$4)*(Portfolio!$F132:$J132)) -> 0 | K50: =SUMPRODUCT((Portfolio!$F130:$J130=K$4)*(Portfolio!$F132:$J132)) -> 0 | ... AU50: =SUMPRODUCT((Portfolio!$F130:$J130=AU$4)*(Portfolio!$F132:$J132)) -> 0
B51: =IF(Portfolio!C133<>"",Portfolio!C133,"") -> 43 | C51: =IF(Portfolio!D133<>"",Portfolio!D133,"") | D51: =SUMPRODUCT((Portfolio!$F133:$J133=D$4)*(Portfolio!$F135:$J135)) -> 0 | E51: =SUMPRODUCT((Portfolio!$F133:$J133=E$4)*(Portfolio!$F135:$J135)) -> 0 | F51: =SUMPRODUCT((Portfolio!$F133:$J133=F$4)*(Portfolio!$F135:$J135)) -> 0 | G51: =SUMPRODUCT((Portfolio!$F133:$J133=G$4)*(Portfolio!$F135:$J135)) -> 0 | H51: =SUMPRODUCT((Portfolio!$F133:$J133=H$4)*(Portfolio!$F135:$J135)) -> 0 | I51: =SUMPRODUCT((Portfolio!$F133:$J133=I$4)*(Portfolio!$F135:$J135)) -> 0 | J51: =SUMPRODUCT((Portfolio!$F133:$J133=J$4)*(Portfolio!$F135:$J135)) -> 0 | K51: =SUMPRODUCT((Portfolio!$F133:$J133=K$4)*(Portfolio!$F135:$J135)) -> 0 | ... AU51: =SUMPRODUCT((Portfolio!$F133:$J133=AU$4)*(Portfolio!$F135:$J135)) -> 0
B52: =IF(Portfolio!C136<>"",Portfolio!C136,"") -> 44 | C52: =IF(Portfolio!D136<>"",Portfolio!D136,"") | D52: =SUMPRODUCT((Portfolio!$F136:$J136=D$4)*(Portfolio!$F138:$J138)) -> 0 | E52: =SUMPRODUCT((Portfolio!$F136:$J136=E$4)*(Portfolio!$F138:$J138)) -> 0 | F52: =SUMPRODUCT((Portfolio!$F136:$J136=F$4)*(Portfolio!$F138:$J138)) -> 0 | G52: =SUMPRODUCT((Portfolio!$F136:$J136=G$4)*(Portfolio!$F138:$J138)) -> 0 | H52: =SUMPRODUCT((Portfolio!$F136:$J136=H$4)*(Portfolio!$F138:$J138)) -> 0 | I52: =SUMPRODUCT((Portfolio!$F136:$J136=I$4)*(Portfolio!$F138:$J138)) -> 0 | J52: =SUMPRODUCT((Portfolio!$F136:$J136=J$4)*(Portfolio!$F138:$J138)) -> 0 | K52: =SUMPRODUCT((Portfolio!$F136:$J136=K$4)*(Portfolio!$F138:$J138)) -> 0 | ... AU52: =SUMPRODUCT((Portfolio!$F136:$J136=AU$4)*(Portfolio!$F138:$J138)) -> 0
B53: =IF(Portfolio!C139<>"",Portfolio!C139,"") -> 45 | C53: =IF(Portfolio!D139<>"",Portfolio!D139,"") | D53: =SUMPRODUCT((Portfolio!$F139:$J139=D$4)*(Portfolio!$F141:$J141)) -> 0 | E53: =SUMPRODUCT((Portfolio!$F139:$J139=E$4)*(Portfolio!$F141:$J141)) -> 0 | F53: =SUMPRODUCT((Portfolio!$F139:$J139=F$4)*(Portfolio!$F141:$J141)) -> 0 | G53: =SUMPRODUCT((Portfolio!$F139:$J139=G$4)*(Portfolio!$F141:$J141)) -> 0 | H53: =SUMPRODUCT((Portfolio!$F139:$J139=H$4)*(Portfolio!$F141:$J141)) -> 0 | I53: =SUMPRODUCT((Portfolio!$F139:$J139=I$4)*(Portfolio!$F141:$J141)) -> 0 | J53: =SUMPRODUCT((Portfolio!$F139:$J139=J$4)*(Portfolio!$F141:$J141)) -> 0 | K53: =SUMPRODUCT((Portfolio!$F139:$J139=K$4)*(Portfolio!$F141:$J141)) -> 0 | ... AU53: =SUMPRODUCT((Portfolio!$F139:$J139=AU$4)*(Portfolio!$F141:$J141)) -> 0
B54: =IF(Portfolio!C142<>"",Portfolio!C142,"") -> 46 | C54: =IF(Portfolio!D142<>"",Portfolio!D142,"") | D54: =SUMPRODUCT((Portfolio!$F142:$J142=D$4)*(Portfolio!$F144:$J144)) -> 0 | E54: =SUMPRODUCT((Portfolio!$F142:$J142=E$4)*(Portfolio!$F144:$J144)) -> 0 | F54: =SUMPRODUCT((Portfolio!$F142:$J142=F$4)*(Portfolio!$F144:$J144)) -> 0 | G54: =SUMPRODUCT((Portfolio!$F142:$J142=G$4)*(Portfolio!$F144:$J144)) -> 0 | H54: =SUMPRODUCT((Portfolio!$F142:$J142=H$4)*(Portfolio!$F144:$J144)) -> 0 | I54: =SUMPRODUCT((Portfolio!$F142:$J142=I$4)*(Portfolio!$F144:$J144)) -> 0 | J54: =SUMPRODUCT((Portfolio!$F142:$J142=J$4)*(Portfolio!$F144:$J144)) -> 0 | K54: =SUMPRODUCT((Portfolio!$F142:$J142=K$4)*(Portfolio!$F144:$J144)) -> 0 | ... AU54: =SUMPRODUCT((Portfolio!$F142:$J142=AU$4)*(Portfolio!$F144:$J144)) -> 0
B55: =IF(Portfolio!C145<>"",Portfolio!C145,"") -> 47 | C55: =IF(Portfolio!D145<>"",Portfolio!D145,"") | D55: =SUMPRODUCT((Portfolio!$F145:$J145=D$4)*(Portfolio!$F147:$J147)) -> 0 | E55: =SUMPRODUCT((Portfolio!$F145:$J145=E$4)*(Portfolio!$F147:$J147)) -> 0 | F55: =SUMPRODUCT((Portfolio!$F145:$J145=F$4)*(Portfolio!$F147:$J147)) -> 0 | G55: =SUMPRODUCT((Portfolio!$F145:$J145=G$4)*(Portfolio!$F147:$J147)) -> 0 | H55: =SUMPRODUCT((Portfolio!$F145:$J145=H$4)*(Portfolio!$F147:$J147)) -> 0 | I55: =SUMPRODUCT((Portfolio!$F145:$J145=I$4)*(Portfolio!$F147:$J147)) -> 0 | J55: =SUMPRODUCT((Portfolio!$F145:$J145=J$4)*(Portfolio!$F147:$J147)) -> 0 | K55: =SUMPRODUCT((Portfolio!$F145:$J145=K$4)*(Portfolio!$F147:$J147)) -> 0 | ... AU55: =SUMPRODUCT((Portfolio!$F145:$J145=AU$4)*(Portfolio!$F147:$J147)) -> 0
B56: =IF(Portfolio!C148<>"",Portfolio!C148,"") -> 48 | C56: =IF(Portfolio!D148<>"",Portfolio!D148,"") | D56: =SUMPRODUCT((Portfolio!$F148:$J148=D$4)*(Portfolio!$F150:$J150)) -> 0 | E56: =SUMPRODUCT((Portfolio!$F148:$J148=E$4)*(Portfolio!$F150:$J150)) -> 0 | F56: =SUMPRODUCT((Portfolio!$F148:$J148=F$4)*(Portfolio!$F150:$J150)) -> 0 | G56: =SUMPRODUCT((Portfolio!$F148:$J148=G$4)*(Portfolio!$F150:$J150)) -> 0 | H56: =SUMPRODUCT((Portfolio!$F148:$J148=H$4)*(Portfolio!$F150:$J150)) -> 0 | I56: =SUMPRODUCT((Portfolio!$F148:$J148=I$4)*(Portfolio!$F150:$J150)) -> 0 | J56: =SUMPRODUCT((Portfolio!$F148:$J148=J$4)*(Portfolio!$F150:$J150)) -> 0 | K56: =SUMPRODUCT((Portfolio!$F148:$J148=K$4)*(Portfolio!$F150:$J150)) -> 0 | ... AU56: =SUMPRODUCT((Portfolio!$F148:$J148=AU$4)*(Portfolio!$F150:$J150)) -> 0
B57: =IF(Portfolio!C151<>"",Portfolio!C151,"") -> 49 | C57: =IF(Portfolio!D151<>"",Portfolio!D151,"") | D57: =SUMPRODUCT((Portfolio!$F151:$J151=D$4)*(Portfolio!$F153:$J153)) -> 0 | E57: =SUMPRODUCT((Portfolio!$F151:$J151=E$4)*(Portfolio!$F153:$J153)) -> 0 | F57: =SUMPRODUCT((Portfolio!$F151:$J151=F$4)*(Portfolio!$F153:$J153)) -> 0 | G57: =SUMPRODUCT((Portfolio!$F151:$J151=G$4)*(Portfolio!$F153:$J153)) -> 0 | H57: =SUMPRODUCT((Portfolio!$F151:$J151=H$4)*(Portfolio!$F153:$J153)) -> 0 | I57: =SUMPRODUCT((Portfolio!$F151:$J151=I$4)*(Portfolio!$F153:$J153)) -> 0 | J57: =SUMPRODUCT((Portfolio!$F151:$J151=J$4)*(Portfolio!$F153:$J153)) -> 0 | K57: =SUMPRODUCT((Portfolio!$F151:$J151=K$4)*(Portfolio!$F153:$J153)) -> 0 | ... AU57: =SUMPRODUCT((Portfolio!$F151:$J151=AU$4)*(Portfolio!$F153:$J153)) -> 0
B58: =IF(Portfolio!C154<>"",Portfolio!C154,"") -> 50 | C58: =IF(Portfolio!D154<>"",Portfolio!D154,"") | D58: =SUMPRODUCT((Portfolio!$F154:$J154=D$4)*(Portfolio!$F156:$J156)) -> 0 | E58: =SUMPRODUCT((Portfolio!$F154:$J154=E$4)*(Portfolio!$F156:$J156)) -> 0 | F58: =SUMPRODUCT((Portfolio!$F154:$J154=F$4)*(Portfolio!$F156:$J156)) -> 0 | G58: =SUMPRODUCT((Portfolio!$F154:$J154=G$4)*(Portfolio!$F156:$J156)) -> 0 | H58: =SUMPRODUCT((Portfolio!$F154:$J154=H$4)*(Portfolio!$F156:$J156)) -> 0 | I58: =SUMPRODUCT((Portfolio!$F154:$J154=I$4)*(Portfolio!$F156:$J156)) -> 0 | J58: =SUMPRODUCT((Portfolio!$F154:$J154=J$4)*(Portfolio!$F156:$J156)) -> 0 | K58: =SUMPRODUCT((Portfolio!$F154:$J154=K$4)*(Portfolio!$F156:$J156)) -> 0 | ... AU58: =SUMPRODUCT((Portfolio!$F154:$J154=AU$4)*(Portfolio!$F156:$J156)) -> 0
B59: Total Investment Outflows | D59: =SUM(D9:D57) -> 2500000 | E59: =SUM(E9:E58) -> 3750000 | F59: =SUM(F9:F58) -> 2500000 | G59: =SUM(G9:G58) -> 3750000 | H59: =SUM(H9:H58) -> 2500000 | I59: =SUM(I9:I58) -> 3975000 | J59: =SUM(J9:J58) -> 6900000 | K59: =SUM(K9:K58) -> 4600000 | L59: =SUM(L9:L58) -> 6900000 | ... AU59: =SUM(AU9:AU58) -> 0
A61: x | B61: Recycled Returns
B62: =IF(Portfolio!C7<>"",Portfolio!C7,"") -> 1 | C62: =IF(Portfolio!D7<>"",Portfolio!D7,"") -> Company 1 | D62: =SUMPRODUCT((Portfolio!$L7=D$4)*(Portfolio!$L9)) -> 0 | E62: =SUMPRODUCT((Portfolio!$L7=E$4)*(Portfolio!$L9)) -> 0 | F62: =SUMPRODUCT((Portfolio!$L7=F$4)*(Portfolio!$L9)) -> 0 | G62: =SUMPRODUCT((Portfolio!$L7=G$4)*(Portfolio!$L9)) -> 0 | H62: =SUMPRODUCT((Portfolio!$L7=H$4)*(Portfolio!$L9)) -> 0 | I62: =SUMPRODUCT((Portfolio!$L7=I$4)*(Portfolio!$L9)) -> 0 | J62: =SUMPRODUCT((Portfolio!$L7=J$4)*(Portfolio!$L9)) -> 0 | K62: =SUMPRODUCT((Portfolio!$L7=K$4)*(Portfolio!$L9)) -> 0 | ... AU62: =SUMPRODUCT((Portfolio!$L7=AU$4)*(Portfolio!$L9)) -> 0
B63: =IF(Portfolio!C10<>"",Portfolio!C10,"") -> 2 | C63: =IF(Portfolio!D10<>"",Portfolio!D10,"") -> Company 2 | D63: =SUMPRODUCT((Portfolio!$L10=D$4)*(Portfolio!$L12)) -> 0 | E63: =SUMPRODUCT((Portfolio!$L10=E$4)*(Portfolio!$L12)) -> 0 | F63: =SUMPRODUCT((Portfolio!$L10=F$4)*(Portfolio!$L12)) -> 0 | G63: =SUMPRODUCT((Portfolio!$L10=G$4)*(Portfolio!$L12)) -> 0 | H63: =SUMPRODUCT((Portfolio!$L10=H$4)*(Portfolio!$L12)) -> 0 | I63: =SUMPRODUCT((Portfolio!$L10=I$4)*(Portfolio!$L12)) -> 0 | J63: =SUMPRODUCT((Portfolio!$L10=J$4)*(Portfolio!$L12)) -> 0 | K63: =SUMPRODUCT((Portfolio!$L10=K$4)*(Portfolio!$L12)) -> 0 | ... AU63: =SUMPRODUCT((Portfolio!$L10=AU$4)*(Portfolio!$L12)) -> 0
B64: =IF(Portfolio!C13<>"",Portfolio!C13,"") -> 3 | C64: =IF(Portfolio!D13<>"",Portfolio!D13,"") -> Company 3 | D64: =SUMPRODUCT((Portfolio!$L13=D$4)*(Portfolio!$L15)) -> 0 | E64: =SUMPRODUCT((Portfolio!$L13=E$4)*(Portfolio!$L15)) -> 0 | F64: =SUMPRODUCT((Portfolio!$L13=F$4)*(Portfolio!$L15)) -> 0 | G64: =SUMPRODUCT((Portfolio!$L13=G$4)*(Portfolio!$L15)) -> 0 | H64: =SUMPRODUCT((Portfolio!$L13=H$4)*(Portfolio!$L15)) -> 0 | I64: =SUMPRODUCT((Portfolio!$L13=I$4)*(Portfolio!$L15)) -> 0 | J64: =SUMPRODUCT((Portfolio!$L13=J$4)*(Portfolio!$L15)) -> 0 | K64: =SUMPRODUCT((Portfolio!$L13=K$4)*(Portfolio!$L15)) -> 0 | ... AU64: =SUMPRODUCT((Portfolio!$L13=AU$4)*(Portfolio!$L15)) -> 0
B65: =IF(Portfolio!C16<>"",Portfolio!C16,"") -> 4 | C65: =IF(Portfolio!D16<>"",Portfolio!D16,"") -> Company 4 | D65: =SUMPRODUCT((Portfolio!$L16=D$4)*(Portfolio!$L18)) -> 0 | E65: =SUMPRODUCT((Portfolio!$L16=E$4)*(Portfolio!$L18)) -> 0 | F65: =SUMPRODUCT((Portfolio!$L16=F$4)*(Portfolio!$L18)) -> 0 | G65: =SUMPRODUCT((Portfolio!$L16=G$4)*(Portfolio!$L18)) -> 0 | H65: =SUMPRODUCT((Portfolio!$L16=H$4)*(Portfolio!$L18)) -> 0 | I65: =SUMPRODUCT((Portfolio!$L16=I$4)*(Portfolio!$L18)) -> 0 | J65: =SUMPRODUCT((Portfolio!$L16=J$4)*(Portfolio!$L18)) -> 0 | K65: =SUMPRODUCT((Portfolio!$L16=K$4)*(Portfolio!$L18)) -> 0 | ... AU65: =SUMPRODUCT((Portfolio!$L16=AU$4)*(Portfolio!$L18)) -> 0
B66: =IF(Portfolio!C19<>"",Portfolio!C19,"") -> 5 | C66: =IF(Portfolio!D19<>"",Portfolio!D19,"") -> Company 5 | D66: =SUMPRODUCT((Portfolio!$L19=D$4)*(Portfolio!$L21)) -> 0 | E66: =SUMPRODUCT((Portfolio!$L19=E$4)*(Portfolio!$L21)) -> 0 | F66: =SUMPRODUCT((Portfolio!$L19=F$4)*(Portfolio!$L21)) -> 0 | G66: =SUMPRODUCT((Portfolio!$L19=G$4)*(Portfolio!$L21)) -> 0 | H66: =SUMPRODUCT((Portfolio!$L19=H$4)*(Portfolio!$L21)) -> 0 | I66: =SUMPRODUCT((Portfolio!$L19=I$4)*(Portfolio!$L21)) -> 0 | J66: =SUMPRODUCT((Portfolio!$L19=J$4)*(Portfolio!$L21)) -> 0 | K66: =SUMPRODUCT((Portfolio!$L19=K$4)*(Portfolio!$L21)) -> 0 | ... AU66: =SUMPRODUCT((Portfolio!$L19=AU$4)*(Portfolio!$L21)) -> 0
B67: =IF(Portfolio!C22<>"",Portfolio!C22,"") -> 6 | C67: =IF(Portfolio!D22<>"",Portfolio!D22,"") -> Company 6 | D67: =SUMPRODUCT((Portfolio!$L22=D$4)*(Portfolio!$L24)) -> 0 | E67: =SUMPRODUCT((Portfolio!$L22=E$4)*(Portfolio!$L24)) -> 0 | F67: =SUMPRODUCT((Portfolio!$L22=F$4)*(Portfolio!$L24)) -> 0 | G67: =SUMPRODUCT((Portfolio!$L22=G$4)*(Portfolio!$L24)) -> 0 | H67: =SUMPRODUCT((Portfolio!$L22=H$4)*(Portfolio!$L24)) -> 0 | I67: =SUMPRODUCT((Portfolio!$L22=I$4)*(Portfolio!$L24)) -> 0 | J67: =SUMPRODUCT((Portfolio!$L22=J$4)*(Portfolio!$L24)) -> 0 | K67: =SUMPRODUCT((Portfolio!$L22=K$4)*(Portfolio!$L24)) -> 0 | ... AU67: =SUMPRODUCT((Portfolio!$L22=AU$4)*(Portfolio!$L24)) -> 0
B68: =IF(Portfolio!C25<>"",Portfolio!C25,"") -> 7 | C68: =IF(Portfolio!D25<>"",Portfolio!D25,"") -> Company 7 | D68: =SUMPRODUCT((Portfolio!$L25=D$4)*(Portfolio!$L27)) -> 0 | E68: =SUMPRODUCT((Portfolio!$L25=E$4)*(Portfolio!$L27)) -> 0 | F68: =SUMPRODUCT((Portfolio!$L25=F$4)*(Portfolio!$L27)) -> 0 | G68: =SUMPRODUCT((Portfolio!$L25=G$4)*(Portfolio!$L27)) -> 0 | H68: =SUMPRODUCT((Portfolio!$L25=H$4)*(Portfolio!$L27)) -> 0 | I68: =SUMPRODUCT((Portfolio!$L25=I$4)*(Portfolio!$L27)) -> 0 | J68: =SUMPRODUCT((Portfolio!$L25=J$4)*(Portfolio!$L27)) -> 0 | K68: =SUMPRODUCT((Portfolio!$L25=K$4)*(Portfolio!$L27)) -> 0 | ... AU68: =SUMPRODUCT((Portfolio!$L25=AU$4)*(Portfolio!$L27)) -> 0
B69: =IF(Portfolio!C28<>"",Portfolio!C28,"") -> 8 | C69: =IF(Portfolio!D28<>"",Portfolio!D28,"") -> Company 8 | D69: =SUMPRODUCT((Portfolio!$L28=D$4)*(Portfolio!$L30)) -> 0 | E69: =SUMPRODUCT((Portfolio!$L28=E$4)*(Portfolio!$L30)) -> 0 | F69: =SUMPRODUCT((Portfolio!$L28=F$4)*(Portfolio!$L30)) -> 0 | G69: =SUMPRODUCT((Portfolio!$L28=G$4)*(Portfolio!$L30)) -> 0 | H69: =SUMPRODUCT((Portfolio!$L28=H$4)*(Portfolio!$L30)) -> 0 | I69: =SUMPRODUCT((Portfolio!$L28=I$4)*(Portfolio!$L30)) -> 0 | J69: =SUMPRODUCT((Portfolio!$L28=J$4)*(Portfolio!$L30)) -> 0 | K69: =SUMPRODUCT((Portfolio!$L28=K$4)*(Portfolio!$L30)) -> 0 | ... AU69: =SUMPRODUCT((Portfolio!$L28=AU$4)*(Portfolio!$L30)) -> 0
B70: =IF(Portfolio!C31<>"",Portfolio!C31,"") -> 9 | C70: =IF(Portfolio!D31<>"",Portfolio!D31,"") -> Company 9 | D70: =SUMPRODUCT((Portfolio!$L31=D$4)*(Portfolio!$L33)) -> 0 | E70: =SUMPRODUCT((Portfolio!$L31=E$4)*(Portfolio!$L33)) -> 0 | F70: =SUMPRODUCT((Portfolio!$L31=F$4)*(Portfolio!$L33)) -> 0 | G70: =SUMPRODUCT((Portfolio!$L31=G$4)*(Portfolio!$L33)) -> 0 | H70: =SUMPRODUCT((Portfolio!$L31=H$4)*(Portfolio!$L33)) -> 0 | I70: =SUMPRODUCT((Portfolio!$L31=I$4)*(Portfolio!$L33)) -> 0 | J70: =SUMPRODUCT((Portfolio!$L31=J$4)*(Portfolio!$L33)) -> 0 | K70: =SUMPRODUCT((Portfolio!$L31=K$4)*(Portfolio!$L33)) -> 0 | ... AU70: =SUMPRODUCT((Portfolio!$L31=AU$4)*(Portfolio!$L33)) -> 0
B71: =IF(Portfolio!C34<>"",Portfolio!C34,"") -> 10 | C71: =IF(Portfolio!D34<>"",Portfolio!D34,"") -> Company 10 | D71: =SUMPRODUCT((Portfolio!$L34=D$4)*(Portfolio!$L36)) -> 0 | E71: =SUMPRODUCT((Portfolio!$L34=E$4)*(Portfolio!$L36)) -> 0 | F71: =SUMPRODUCT((Portfolio!$L34=F$4)*(Portfolio!$L36)) -> 0 | G71: =SUMPRODUCT((Portfolio!$L34=G$4)*(Portfolio!$L36)) -> 0 | H71: =SUMPRODUCT((Portfolio!$L34=H$4)*(Portfolio!$L36)) -> 0 | I71: =SUMPRODUCT((Portfolio!$L34=I$4)*(Portfolio!$L36)) -> 0 | J71: =SUMPRODUCT((Portfolio!$L34=J$4)*(Portfolio!$L36)) -> 0 | K71: =SUMPRODUCT((Portfolio!$L34=K$4)*(Portfolio!$L36)) -> 0 | ... AU71: =SUMPRODUCT((Portfolio!$L34=AU$4)*(Portfolio!$L36)) -> 0
B72: =IF(Portfolio!C37<>"",Portfolio!C37,"") -> 11 | C72: =IF(Portfolio!D37<>"",Portfolio!D37,"") -> Company 11 | D72: =SUMPRODUCT((Portfolio!$L37=D$4)*(Portfolio!$L39)) -> 0 | E72: =SUMPRODUCT((Portfolio!$L37=E$4)*(Portfolio!$L39)) -> 0 | F72: =SUMPRODUCT((Portfolio!$L37=F$4)*(Portfolio!$L39)) -> 0 | G72: =SUMPRODUCT((Portfolio!$L37=G$4)*(Portfolio!$L39)) -> 0 | H72: =SUMPRODUCT((Portfolio!$L37=H$4)*(Portfolio!$L39)) -> 0 | I72: =SUMPRODUCT((Portfolio!$L37=I$4)*(Portfolio!$L39)) -> 0 | J72: =SUMPRODUCT((Portfolio!$L37=J$4)*(Portfolio!$L39)) -> 0 | K72: =SUMPRODUCT((Portfolio!$L37=K$4)*(Portfolio!$L39)) -> 0 | ... AU72: =SUMPRODUCT((Portfolio!$L37=AU$4)*(Portfolio!$L39)) -> 0
B73: =IF(Portfolio!C40<>"",Portfolio!C40,"") -> 12 | C73: =IF(Portfolio!D40<>"",Portfolio!D40,"") -> Company 12 | D73: =SUMPRODUCT((Portfolio!$L40=D$4)*(Portfolio!$L42)) -> 0 | E73: =SUMPRODUCT((Portfolio!$L40=E$4)*(Portfolio!$L42)) -> 0 | F73: =SUMPRODUCT((Portfolio!$L40=F$4)*(Portfolio!$L42)) -> 0 | G73: =SUMPRODUCT((Portfolio!$L40=G$4)*(Portfolio!$L42)) -> 0 | H73: =SUMPRODUCT((Portfolio!$L40=H$4)*(Portfolio!$L42)) -> 0 | I73: =SUMPRODUCT((Portfolio!$L40=I$4)*(Portfolio!$L42)) -> 0 | J73: =SUMPRODUCT((Portfolio!$L40=J$4)*(Portfolio!$L42)) -> 0 | K73: =SUMPRODUCT((Portfolio!$L40=K$4)*(Portfolio!$L42)) -> 0 | ... AU73: =SUMPRODUCT((Portfolio!$L40=AU$4)*(Portfolio!$L42)) -> 0
B74: =IF(Portfolio!C43<>"",Portfolio!C43,"") -> 13 | C74: =IF(Portfolio!D43<>"",Portfolio!D43,"") -> Company 13 | D74: =SUMPRODUCT((Portfolio!$L43=D$4)*(Portfolio!$L45)) -> 0 | E74: =SUMPRODUCT((Portfolio!$L43=E$4)*(Portfolio!$L45)) -> 0 | F74: =SUMPRODUCT((Portfolio!$L43=F$4)*(Portfolio!$L45)) -> 0 | G74: =SUMPRODUCT((Portfolio!$L43=G$4)*(Portfolio!$L45)) -> 0 | H74: =SUMPRODUCT((Portfolio!$L43=H$4)*(Portfolio!$L45)) -> 0 | I74: =SUMPRODUCT((Portfolio!$L43=I$4)*(Portfolio!$L45)) -> 0 | J74: =SUMPRODUCT((Portfolio!$L43=J$4)*(Portfolio!$L45)) -> 0 | K74: =SUMPRODUCT((Portfolio!$L43=K$4)*(Portfolio!$L45)) -> 0 | ... AU74: =SUMPRODUCT((Portfolio!$L43=AU$4)*(Portfolio!$L45)) -> 0
B75: =IF(Portfolio!C46<>"",Portfolio!C46,"") -> 14 | C75: =IF(Portfolio!D46<>"",Portfolio!D46,"") -> Company 14 | D75: =SUMPRODUCT((Portfolio!$L46=D$4)*(Portfolio!$L48)) -> 0 | E75: =SUMPRODUCT((Portfolio!$L46=E$4)*(Portfolio!$L48)) -> 0 | F75: =SUMPRODUCT((Portfolio!$L46=F$4)*(Portfolio!$L48)) -> 0 | G75: =SUMPRODUCT((Portfolio!$L46=G$4)*(Portfolio!$L48)) -> 0 | H75: =SUMPRODUCT((Portfolio!$L46=H$4)*(Portfolio!$L48)) -> 0 | I75: =SUMPRODUCT((Portfolio!$L46=I$4)*(Portfolio!$L48)) -> 0 | J75: =SUMPRODUCT((Portfolio!$L46=J$4)*(Portfolio!$L48)) -> 0 | K75: =SUMPRODUCT((Portfolio!$L46=K$4)*(Portfolio!$L48)) -> 0 | ... AU75: =SUMPRODUCT((Portfolio!$L46=AU$4)*(Portfolio!$L48)) -> 0
B76: =IF(Portfolio!C49<>"",Portfolio!C49,"") -> 15 | C76: =IF(Portfolio!D49<>"",Portfolio!D49,"") -> Company 15 | D76: =SUMPRODUCT((Portfolio!$L49=D$4)*(Portfolio!$L51)) -> 0 | E76: =SUMPRODUCT((Portfolio!$L49=E$4)*(Portfolio!$L51)) -> 0 | F76: =SUMPRODUCT((Portfolio!$L49=F$4)*(Portfolio!$L51)) -> 0 | G76: =SUMPRODUCT((Portfolio!$L49=G$4)*(Portfolio!$L51)) -> 0 | H76: =SUMPRODUCT((Portfolio!$L49=H$4)*(Portfolio!$L51)) -> 0 | I76: =SUMPRODUCT((Portfolio!$L49=I$4)*(Portfolio!$L51)) -> 0 | J76: =SUMPRODUCT((Portfolio!$L49=J$4)*(Portfolio!$L51)) -> 0 | K76: =SUMPRODUCT((Portfolio!$L49=K$4)*(Portfolio!$L51)) -> 0 | ... AU76: =SUMPRODUCT((Portfolio!$L49=AU$4)*(Portfolio!$L51)) -> 0
B77: =IF(Portfolio!C52<>"",Portfolio!C52,"") -> 16 | C77: =IF(Portfolio!D52<>"",Portfolio!D52,"") -> Company 16 | D77: =SUMPRODUCT((Portfolio!$L52=D$4)*(Portfolio!$L54)) -> 0 | E77: =SUMPRODUCT((Portfolio!$L52=E$4)*(Portfolio!$L54)) -> 0 | F77: =SUMPRODUCT((Portfolio!$L52=F$4)*(Portfolio!$L54)) -> 0 | G77: =SUMPRODUCT((Portfolio!$L52=G$4)*(Portfolio!$L54)) -> 0 | H77: =SUMPRODUCT((Portfolio!$L52=H$4)*(Portfolio!$L54)) -> 0 | I77: =SUMPRODUCT((Portfolio!$L52=I$4)*(Portfolio!$L54)) -> 0 | J77: =SUMPRODUCT((Portfolio!$L52=J$4)*(Portfolio!$L54)) -> 0 | K77: =SUMPRODUCT((Portfolio!$L52=K$4)*(Portfolio!$L54)) -> 0 | ... AU77: =SUMPRODUCT((Portfolio!$L52=AU$4)*(Portfolio!$L54)) -> 0
B78: =IF(Portfolio!C55<>"",Portfolio!C55,"") -> 17 | C78: =IF(Portfolio!D55<>"",Portfolio!D55,"") -> Company 17 | D78: =SUMPRODUCT((Portfolio!$L55=D$4)*(Portfolio!$L57)) -> 0 | E78: =SUMPRODUCT((Portfolio!$L55=E$4)*(Portfolio!$L57)) -> 0 | F78: =SUMPRODUCT((Portfolio!$L55=F$4)*(Portfolio!$L57)) -> 0 | G78: =SUMPRODUCT((Portfolio!$L55=G$4)*(Portfolio!$L57)) -> 0 | H78: =SUMPRODUCT((Portfolio!$L55=H$4)*(Portfolio!$L57)) -> 0 | I78: =SUMPRODUCT((Portfolio!$L55=I$4)*(Portfolio!$L57)) -> 0 | J78: =SUMPRODUCT((Portfolio!$L55=J$4)*(Portfolio!$L57)) -> 0 | K78: =SUMPRODUCT((Portfolio!$L55=K$4)*(Portfolio!$L57)) -> 0 | ... AU78: =SUMPRODUCT((Portfolio!$L55=AU$4)*(Portfolio!$L57)) -> 0
B79: =IF(Portfolio!C58<>"",Portfolio!C58,"") -> 18 | C79: =IF(Portfolio!D58<>"",Portfolio!D58,"") -> Company 18 | D79: =SUMPRODUCT((Portfolio!$L58=D$4)*(Portfolio!$L60)) -> 0 | E79: =SUMPRODUCT((Portfolio!$L58=E$4)*(Portfolio!$L60)) -> 0 | F79: =SUMPRODUCT((Portfolio!$L58=F$4)*(Portfolio!$L60)) -> 0 | G79: =SUMPRODUCT((Portfolio!$L58=G$4)*(Portfolio!$L60)) -> 0 | H79: =SUMPRODUCT((Portfolio!$L58=H$4)*(Portfolio!$L60)) -> 0 | I79: =SUMPRODUCT((Portfolio!$L58=I$4)*(Portfolio!$L60)) -> 0 | J79: =SUMPRODUCT((Portfolio!$L58=J$4)*(Portfolio!$L60)) -> 0 | K79: =SUMPRODUCT((Portfolio!$L58=K$4)*(Portfolio!$L60)) -> 0 | ... AU79: =SUMPRODUCT((Portfolio!$L58=AU$4)*(Portfolio!$L60)) -> 0
B80: =IF(Portfolio!C61<>"",Portfolio!C61,"") -> 19 | C80: =IF(Portfolio!D61<>"",Portfolio!D61,"") -> Company 19 | D80: =SUMPRODUCT((Portfolio!$L61=D$4)*(Portfolio!$L63)) -> 0 | E80: =SUMPRODUCT((Portfolio!$L61=E$4)*(Portfolio!$L63)) -> 0 | F80: =SUMPRODUCT((Portfolio!$L61=F$4)*(Portfolio!$L63)) -> 0 | G80: =SUMPRODUCT((Portfolio!$L61=G$4)*(Portfolio!$L63)) -> 0 | H80: =SUMPRODUCT((Portfolio!$L61=H$4)*(Portfolio!$L63)) -> 0 | I80: =SUMPRODUCT((Portfolio!$L61=I$4)*(Portfolio!$L63)) -> 0 | J80: =SUMPRODUCT((Portfolio!$L61=J$4)*(Portfolio!$L63)) -> 0 | K80: =SUMPRODUCT((Portfolio!$L61=K$4)*(Portfolio!$L63)) -> 0 | ... AU80: =SUMPRODUCT((Portfolio!$L61=AU$4)*(Portfolio!$L63)) -> 0
B81: =IF(Portfolio!C64<>"",Portfolio!C64,"") -> 20 | C81: =IF(Portfolio!D64<>"",Portfolio!D64,"") -> Company 20 | D81: =SUMPRODUCT((Portfolio!$L64=D$4)*(Portfolio!$L66)) -> 0 | E81: =SUMPRODUCT((Portfolio!$L64=E$4)*(Portfolio!$L66)) -> 0 | F81: =SUMPRODUCT((Portfolio!$L64=F$4)*(Portfolio!$L66)) -> 0 | G81: =SUMPRODUCT((Portfolio!$L64=G$4)*(Portfolio!$L66)) -> 0 | H81: =SUMPRODUCT((Portfolio!$L64=H$4)*(Portfolio!$L66)) -> 0 | I81: =SUMPRODUCT((Portfolio!$L64=I$4)*(Portfolio!$L66)) -> 0 | J81: =SUMPRODUCT((Portfolio!$L64=J$4)*(Portfolio!$L66)) -> 0 | K81: =SUMPRODUCT((Portfolio!$L64=K$4)*(Portfolio!$L66)) -> 0 | ... AU81: =SUMPRODUCT((Portfolio!$L64=AU$4)*(Portfolio!$L66)) -> 0
B82: =IF(Portfolio!C67<>"",Portfolio!C67,"") -> 21 | C82: =IF(Portfolio!D67<>"",Portfolio!D67,"") -> Company 21 | D82: =SUMPRODUCT((Portfolio!$L67=D$4)*(Portfolio!$L69)) -> 0 | E82: =SUMPRODUCT((Portfolio!$L67=E$4)*(Portfolio!$L69)) -> 0 | F82: =SUMPRODUCT((Portfolio!$L67=F$4)*(Portfolio!$L69)) -> 0 | G82: =SUMPRODUCT((Portfolio!$L67=G$4)*(Portfolio!$L69)) -> 0 | H82: =SUMPRODUCT((Portfolio!$L67=H$4)*(Portfolio!$L69)) -> 0 | I82: =SUMPRODUCT((Portfolio!$L67=I$4)*(Portfolio!$L69)) -> 0 | J82: =SUMPRODUCT((Portfolio!$L67=J$4)*(Portfolio!$L69)) -> 0 | K82: =SUMPRODUCT((Portfolio!$L67=K$4)*(Portfolio!$L69)) -> 0 | ... AU82: =SUMPRODUCT((Portfolio!$L67=AU$4)*(Portfolio!$L69)) -> 0
B83: =IF(Portfolio!C70<>"",Portfolio!C70,"") -> 22 | C83: =IF(Portfolio!D70<>"",Portfolio!D70,"") -> Company 22 | D83: =SUMPRODUCT((Portfolio!$L70=D$4)*(Portfolio!$L72)) -> 0 | E83: =SUMPRODUCT((Portfolio!$L70=E$4)*(Portfolio!$L72)) -> 0 | F83: =SUMPRODUCT((Portfolio!$L70=F$4)*(Portfolio!$L72)) -> 0 | G83: =SUMPRODUCT((Portfolio!$L70=G$4)*(Portfolio!$L72)) -> 0 | H83: =SUMPRODUCT((Portfolio!$L70=H$4)*(Portfolio!$L72)) -> 0 | I83: =SUMPRODUCT((Portfolio!$L70=I$4)*(Portfolio!$L72)) -> 0 | J83: =SUMPRODUCT((Portfolio!$L70=J$4)*(Portfolio!$L72)) -> 0 | K83: =SUMPRODUCT((Portfolio!$L70=K$4)*(Portfolio!$L72)) -> 0 | ... AU83: =SUMPRODUCT((Portfolio!$L70=AU$4)*(Portfolio!$L72)) -> 0
B84: =IF(Portfolio!C73<>"",Portfolio!C73,"") -> 23 | C84: =IF(Portfolio!D73<>"",Portfolio!D73,"") -> Company 23 | D84: =SUMPRODUCT((Portfolio!$L73=D$4)*(Portfolio!$L75)) -> 0 | E84: =SUMPRODUCT((Portfolio!$L73=E$4)*(Portfolio!$L75)) -> 0 | F84: =SUMPRODUCT((Portfolio!$L73=F$4)*(Portfolio!$L75)) -> 0 | G84: =SUMPRODUCT((Portfolio!$L73=G$4)*(Portfolio!$L75)) -> 0 | H84: =SUMPRODUCT((Portfolio!$L73=H$4)*(Portfolio!$L75)) -> 0 | I84: =SUMPRODUCT((Portfolio!$L73=I$4)*(Portfolio!$L75)) -> 0 | J84: =SUMPRODUCT((Portfolio!$L73=J$4)*(Portfolio!$L75)) -> 0 | K84: =SUMPRODUCT((Portfolio!$L73=K$4)*(Portfolio!$L75)) -> 0 | ... AU84: =SUMPRODUCT((Portfolio!$L73=AU$4)*(Portfolio!$L75)) -> 0
B85: =IF(Portfolio!C76<>"",Portfolio!C76,"") -> 24 | C85: =IF(Portfolio!D76<>"",Portfolio!D76,"") -> Company 24 | D85: =SUMPRODUCT((Portfolio!$L76=D$4)*(Portfolio!$L78)) -> 0 | E85: =SUMPRODUCT((Portfolio!$L76=E$4)*(Portfolio!$L78)) -> 0 | F85: =SUMPRODUCT((Portfolio!$L76=F$4)*(Portfolio!$L78)) -> 0 | G85: =SUMPRODUCT((Portfolio!$L76=G$4)*(Portfolio!$L78)) -> 0 | H85: =SUMPRODUCT((Portfolio!$L76=H$4)*(Portfolio!$L78)) -> 0 | I85: =SUMPRODUCT((Portfolio!$L76=I$4)*(Portfolio!$L78)) -> 0 | J85: =SUMPRODUCT((Portfolio!$L76=J$4)*(Portfolio!$L78)) -> 0 | K85: =SUMPRODUCT((Portfolio!$L76=K$4)*(Portfolio!$L78)) -> 0 | ... AU85: =SUMPRODUCT((Portfolio!$L76=AU$4)*(Portfolio!$L78)) -> 0
B86: =IF(Portfolio!C79<>"",Portfolio!C79,"") -> 25 | C86: =IF(Portfolio!D79<>"",Portfolio!D79,"") -> Company 25 | D86: =SUMPRODUCT((Portfolio!$L79=D$4)*(Portfolio!$L81)) -> 0 | E86: =SUMPRODUCT((Portfolio!$L79=E$4)*(Portfolio!$L81)) -> 0 | F86: =SUMPRODUCT((Portfolio!$L79=F$4)*(Portfolio!$L81)) -> 0 | G86: =SUMPRODUCT((Portfolio!$L79=G$4)*(Portfolio!$L81)) -> 0 | H86: =SUMPRODUCT((Portfolio!$L79=H$4)*(Portfolio!$L81)) -> 0 | I86: =SUMPRODUCT((Portfolio!$L79=I$4)*(Portfolio!$L81)) -> 0 | J86: =SUMPRODUCT((Portfolio!$L79=J$4)*(Portfolio!$L81)) -> 0 | K86: =SUMPRODUCT((Portfolio!$L79=K$4)*(Portfolio!$L81)) -> 0 | ... AU86: =SUMPRODUCT((Portfolio!$L79=AU$4)*(Portfolio!$L81)) -> 0
B87: =IF(Portfolio!C82<>"",Portfolio!C82,"") -> 26 | C87: =IF(Portfolio!D82<>"",Portfolio!D82,"") -> Company 26 | D87: =SUMPRODUCT((Portfolio!$L82=D$4)*(Portfolio!$L84)) -> 0 | E87: =SUMPRODUCT((Portfolio!$L82=E$4)*(Portfolio!$L84)) -> 0 | F87: =SUMPRODUCT((Portfolio!$L82=F$4)*(Portfolio!$L84)) -> 0 | G87: =SUMPRODUCT((Portfolio!$L82=G$4)*(Portfolio!$L84)) -> 0 | H87: =SUMPRODUCT((Portfolio!$L82=H$4)*(Portfolio!$L84)) -> 0 | I87: =SUMPRODUCT((Portfolio!$L82=I$4)*(Portfolio!$L84)) -> 0 | J87: =SUMPRODUCT((Portfolio!$L82=J$4)*(Portfolio!$L84)) -> 0 | K87: =SUMPRODUCT((Portfolio!$L82=K$4)*(Portfolio!$L84)) -> 0 | ... AU87: =SUMPRODUCT((Portfolio!$L82=AU$4)*(Portfolio!$L84)) -> 0
B88: =IF(Portfolio!C85<>"",Portfolio!C85,"") -> 27 | C88: =IF(Portfolio!D85<>"",Portfolio!D85,"") -> Company 27 | D88: =SUMPRODUCT((Portfolio!$L85=D$4)*(Portfolio!$L87)) -> 0 | E88: =SUMPRODUCT((Portfolio!$L85=E$4)*(Portfolio!$L87)) -> 0 | F88: =SUMPRODUCT((Portfolio!$L85=F$4)*(Portfolio!$L87)) -> 0 | G88: =SUMPRODUCT((Portfolio!$L85=G$4)*(Portfolio!$L87)) -> 0 | H88: =SUMPRODUCT((Portfolio!$L85=H$4)*(Portfolio!$L87)) -> 0 | I88: =SUMPRODUCT((Portfolio!$L85=I$4)*(Portfolio!$L87)) -> 0 | J88: =SUMPRODUCT((Portfolio!$L85=J$4)*(Portfolio!$L87)) -> 0 | K88: =SUMPRODUCT((Portfolio!$L85=K$4)*(Portfolio!$L87)) -> 0 | ... AU88: =SUMPRODUCT((Portfolio!$L85=AU$4)*(Portfolio!$L87)) -> 0
B89: =IF(Portfolio!C88<>"",Portfolio!C88,"") -> 28 | C89: =IF(Portfolio!D88<>"",Portfolio!D88,"") -> Company 28 | D89: =SUMPRODUCT((Portfolio!$L88=D$4)*(Portfolio!$L90)) -> 0 | E89: =SUMPRODUCT((Portfolio!$L88=E$4)*(Portfolio!$L90)) -> 0 | F89: =SUMPRODUCT((Portfolio!$L88=F$4)*(Portfolio!$L90)) -> 0 | G89: =SUMPRODUCT((Portfolio!$L88=G$4)*(Portfolio!$L90)) -> 0 | H89: =SUMPRODUCT((Portfolio!$L88=H$4)*(Portfolio!$L90)) -> 0 | I89: =SUMPRODUCT((Portfolio!$L88=I$4)*(Portfolio!$L90)) -> 0 | J89: =SUMPRODUCT((Portfolio!$L88=J$4)*(Portfolio!$L90)) -> 0 | K89: =SUMPRODUCT((Portfolio!$L88=K$4)*(Portfolio!$L90)) -> 0 | ... AU89: =SUMPRODUCT((Portfolio!$L88=AU$4)*(Portfolio!$L90)) -> 0
B90: =IF(Portfolio!C91<>"",Portfolio!C91,"") -> 29 | C90: =IF(Portfolio!D91<>"",Portfolio!D91,"") -> Company 29 | D90: =SUMPRODUCT((Portfolio!$L91=D$4)*(Portfolio!$L93)) -> 0 | E90: =SUMPRODUCT((Portfolio!$L91=E$4)*(Portfolio!$L93)) -> 0 | F90: =SUMPRODUCT((Portfolio!$L91=F$4)*(Portfolio!$L93)) -> 0 | G90: =SUMPRODUCT((Portfolio!$L91=G$4)*(Portfolio!$L93)) -> 0 | H90: =SUMPRODUCT((Portfolio!$L91=H$4)*(Portfolio!$L93)) -> 0 | I90: =SUMPRODUCT((Portfolio!$L91=I$4)*(Portfolio!$L93)) -> 0 | J90: =SUMPRODUCT((Portfolio!$L91=J$4)*(Portfolio!$L93)) -> 0 | K90: =SUMPRODUCT((Portfolio!$L91=K$4)*(Portfolio!$L93)) -> 0 | ... AU90: =SUMPRODUCT((Portfolio!$L91=AU$4)*(Portfolio!$L93)) -> 0
B91: =IF(Portfolio!C94<>"",Portfolio!C94,"") -> 30 | C91: =IF(Portfolio!D94<>"",Portfolio!D94,"") -> Company 30 | D91: =SUMPRODUCT((Portfolio!$L94=D$4)*(Portfolio!$L96)) -> 0 | E91: =SUMPRODUCT((Portfolio!$L94=E$4)*(Portfolio!$L96)) -> 0 | F91: =SUMPRODUCT((Portfolio!$L94=F$4)*(Portfolio!$L96)) -> 0 | G91: =SUMPRODUCT((Portfolio!$L94=G$4)*(Portfolio!$L96)) -> 0 | H91: =SUMPRODUCT((Portfolio!$L94=H$4)*(Portfolio!$L96)) -> 0 | I91: =SUMPRODUCT((Portfolio!$L94=I$4)*(Portfolio!$L96)) -> 0 | J91: =SUMPRODUCT((Portfolio!$L94=J$4)*(Portfolio!$L96)) -> 0 | K91: =SUMPRODUCT((Portfolio!$L94=K$4)*(Portfolio!$L96)) -> 0 | ... AU91: =SUMPRODUCT((Portfolio!$L94=AU$4)*(Portfolio!$L96)) -> 0
B92: =IF(Portfolio!C97<>"",Portfolio!C97,"") -> 31 | C92: =IF(Portfolio!D97<>"",Portfolio!D97,"") -> Company 31 | D92: =SUMPRODUCT((Portfolio!$L97=D$4)*(Portfolio!$L99)) -> 0 | E92: =SUMPRODUCT((Portfolio!$L97=E$4)*(Portfolio!$L99)) -> 0 | F92: =SUMPRODUCT((Portfolio!$L97=F$4)*(Portfolio!$L99)) -> 0 | G92: =SUMPRODUCT((Portfolio!$L97=G$4)*(Portfolio!$L99)) -> 0 | H92: =SUMPRODUCT((Portfolio!$L97=H$4)*(Portfolio!$L99)) -> 0 | I92: =SUMPRODUCT((Portfolio!$L97=I$4)*(Portfolio!$L99)) -> 0 | J92: =SUMPRODUCT((Portfolio!$L97=J$4)*(Portfolio!$L99)) -> 0 | K92: =SUMPRODUCT((Portfolio!$L97=K$4)*(Portfolio!$L99)) -> 0 | ... AU92: =SUMPRODUCT((Portfolio!$L97=AU$4)*(Portfolio!$L99)) -> 0
B93: =IF(Portfolio!C100<>"",Portfolio!C100,"") -> 32 | C93: =IF(Portfolio!D100<>"",Portfolio!D100,"") -> Company 32 | D93: =SUMPRODUCT((Portfolio!$L100=D$4)*(Portfolio!$L102)) -> 0 | E93: =SUMPRODUCT((Portfolio!$L100=E$4)*(Portfolio!$L102)) -> 0 | F93: =SUMPRODUCT((Portfolio!$L100=F$4)*(Portfolio!$L102)) -> 0 | G93: =SUMPRODUCT((Portfolio!$L100=G$4)*(Portfolio!$L102)) -> 0 | H93: =SUMPRODUCT((Portfolio!$L100=H$4)*(Portfolio!$L102)) -> 0 | I93: =SUMPRODUCT((Portfolio!$L100=I$4)*(Portfolio!$L102)) -> 0 | J93: =SUMPRODUCT((Portfolio!$L100=J$4)*(Portfolio!$L102)) -> 0 | K93: =SUMPRODUCT((Portfolio!$L100=K$4)*(Portfolio!$L102)) -> 0 | ... AU93: =SUMPRODUCT((Portfolio!$L100=AU$4)*(Portfolio!$L102)) -> 0
B94: =IF(Portfolio!C103<>"",Portfolio!C103,"") -> 33 | C94: =IF(Portfolio!D103<>"",Portfolio!D103,"") -> Company 33 | D94: =SUMPRODUCT((Portfolio!$L103=D$4)*(Portfolio!$L105)) -> 0 | E94: =SUMPRODUCT((Portfolio!$L103=E$4)*(Portfolio!$L105)) -> 0 | F94: =SUMPRODUCT((Portfolio!$L103=F$4)*(Portfolio!$L105)) -> 0 | G94: =SUMPRODUCT((Portfolio!$L103=G$4)*(Portfolio!$L105)) -> 0 | H94: =SUMPRODUCT((Portfolio!$L103=H$4)*(Portfolio!$L105)) -> 0 | I94: =SUMPRODUCT((Portfolio!$L103=I$4)*(Portfolio!$L105)) -> 0 | J94: =SUMPRODUCT((Portfolio!$L103=J$4)*(Portfolio!$L105)) -> 0 | K94: =SUMPRODUCT((Portfolio!$L103=K$4)*(Portfolio!$L105)) -> 0 | ... AU94: =SUMPRODUCT((Portfolio!$L103=AU$4)*(Portfolio!$L105)) -> 0
B95: =IF(Portfolio!C106<>"",Portfolio!C106,"") -> 34 | C95: =IF(Portfolio!D106<>"",Portfolio!D106,"") -> Company 34 | D95: =SUMPRODUCT((Portfolio!$L106=D$4)*(Portfolio!$L108)) -> 0 | E95: =SUMPRODUCT((Portfolio!$L106=E$4)*(Portfolio!$L108)) -> 0 | F95: =SUMPRODUCT((Portfolio!$L106=F$4)*(Portfolio!$L108)) -> 0 | G95: =SUMPRODUCT((Portfolio!$L106=G$4)*(Portfolio!$L108)) -> 0 | H95: =SUMPRODUCT((Portfolio!$L106=H$4)*(Portfolio!$L108)) -> 0 | I95: =SUMPRODUCT((Portfolio!$L106=I$4)*(Portfolio!$L108)) -> 0 | J95: =SUMPRODUCT((Portfolio!$L106=J$4)*(Portfolio!$L108)) -> 0 | K95: =SUMPRODUCT((Portfolio!$L106=K$4)*(Portfolio!$L108)) -> 0 | ... AU95: =SUMPRODUCT((Portfolio!$L106=AU$4)*(Portfolio!$L108)) -> 0
B96: =IF(Portfolio!C109<>"",Portfolio!C109,"") -> 35 | C96: =IF(Portfolio!D109<>"",Portfolio!D109,"") -> Company 35 | D96: =SUMPRODUCT((Portfolio!$L109=D$4)*(Portfolio!$L111)) -> 0 | E96: =SUMPRODUCT((Portfolio!$L109=E$4)*(Portfolio!$L111)) -> 0 | F96: =SUMPRODUCT((Portfolio!$L109=F$4)*(Portfolio!$L111)) -> 0 | G96: =SUMPRODUCT((Portfolio!$L109=G$4)*(Portfolio!$L111)) -> 0 | H96: =SUMPRODUCT((Portfolio!$L109=H$4)*(Portfolio!$L111)) -> 0 | I96: =SUMPRODUCT((Portfolio!$L109=I$4)*(Portfolio!$L111)) -> 0 | J96: =SUMPRODUCT((Portfolio!$L109=J$4)*(Portfolio!$L111)) -> 0 | K96: =SUMPRODUCT((Portfolio!$L109=K$4)*(Portfolio!$L111)) -> 0 | ... AU96: =SUMPRODUCT((Portfolio!$L109=AU$4)*(Portfolio!$L111)) -> 0
B97: =IF(Portfolio!C112<>"",Portfolio!C112,"") -> 36 | C97: =IF(Portfolio!D112<>"",Portfolio!D112,"") | D97: =SUMPRODUCT((Portfolio!$L112=D$4)*(Portfolio!$L114)) -> 0 | E97: =SUMPRODUCT((Portfolio!$L112=E$4)*(Portfolio!$L114)) -> 0 | F97: =SUMPRODUCT((Portfolio!$L112=F$4)*(Portfolio!$L114)) -> 0 | G97: =SUMPRODUCT((Portfolio!$L112=G$4)*(Portfolio!$L114)) -> 0 | H97: =SUMPRODUCT((Portfolio!$L112=H$4)*(Portfolio!$L114)) -> 0 | I97: =SUMPRODUCT((Portfolio!$L112=I$4)*(Portfolio!$L114)) -> 0 | J97: =SUMPRODUCT((Portfolio!$L112=J$4)*(Portfolio!$L114)) -> 0 | K97: =SUMPRODUCT((Portfolio!$L112=K$4)*(Portfolio!$L114)) -> 0 | ... AU97: =SUMPRODUCT((Portfolio!$L112=AU$4)*(Portfolio!$L114)) -> 0
B98: =IF(Portfolio!C115<>"",Portfolio!C115,"") -> 37 | C98: =IF(Portfolio!D115<>"",Portfolio!D115,"") | D98: =SUMPRODUCT((Portfolio!$L115=D$4)*(Portfolio!$L117)) -> 0 | E98: =SUMPRODUCT((Portfolio!$L115=E$4)*(Portfolio!$L117)) -> 0 | F98: =SUMPRODUCT((Portfolio!$L115=F$4)*(Portfolio!$L117)) -> 0 | G98: =SUMPRODUCT((Portfolio!$L115=G$4)*(Portfolio!$L117)) -> 0 | H98: =SUMPRODUCT((Portfolio!$L115=H$4)*(Portfolio!$L117)) -> 0 | I98: =SUMPRODUCT((Portfolio!$L115=I$4)*(Portfolio!$L117)) -> 0 | J98: =SUMPRODUCT((Portfolio!$L115=J$4)*(Portfolio!$L117)) -> 0 | K98: =SUMPRODUCT((Portfolio!$L115=K$4)*(Portfolio!$L117)) -> 0 | ... AU98: =SUMPRODUCT((Portfolio!$L115=AU$4)*(Portfolio!$L117)) -> 0
B99: =IF(Portfolio!C118<>"",Portfolio!C118,"") -> 38 | C99: =IF(Portfolio!D118<>"",Portfolio!D118,"") | D99: =SUMPRODUCT((Portfolio!$L118=D$4)*(Portfolio!$L120)) -> 0 | E99: =SUMPRODUCT((Portfolio!$L118=E$4)*(Portfolio!$L120)) -> 0 | F99: =SUMPRODUCT((Portfolio!$L118=F$4)*(Portfolio!$L120)) -> 0 | G99: =SUMPRODUCT((Portfolio!$L118=G$4)*(Portfolio!$L120)) -> 0 | H99: =SUMPRODUCT((Portfolio!$L118=H$4)*(Portfolio!$L120)) -> 0 | I99: =SUMPRODUCT((Portfolio!$L118=I$4)*(Portfolio!$L120)) -> 0 | J99: =SUMPRODUCT((Portfolio!$L118=J$4)*(Portfolio!$L120)) -> 0 | K99: =SUMPRODUCT((Portfolio!$L118=K$4)*(Portfolio!$L120)) -> 0 | ... AU99: =SUMPRODUCT((Portfolio!$L118=AU$4)*(Portfolio!$L120)) -> 0
B100: =IF(Portfolio!C121<>"",Portfolio!C121,"") -> 39 | C100: =IF(Portfolio!D121<>"",Portfolio!D121,"") | D100: =SUMPRODUCT((Portfolio!$L121=D$4)*(Portfolio!$L123)) -> 0 | E100: =SUMPRODUCT((Portfolio!$L121=E$4)*(Portfolio!$L123)) -> 0 | F100: =SUMPRODUCT((Portfolio!$L121=F$4)*(Portfolio!$L123)) -> 0 | G100: =SUMPRODUCT((Portfolio!$L121=G$4)*(Portfolio!$L123)) -> 0 | H100: =SUMPRODUCT((Portfolio!$L121=H$4)*(Portfolio!$L123)) -> 0 | I100: =SUMPRODUCT((Portfolio!$L121=I$4)*(Portfolio!$L123)) -> 0 | J100: =SUMPRODUCT((Portfolio!$L121=J$4)*(Portfolio!$L123)) -> 0 | K100: =SUMPRODUCT((Portfolio!$L121=K$4)*(Portfolio!$L123)) -> 0 | ... AU100: =SUMPRODUCT((Portfolio!$L121=AU$4)*(Portfolio!$L123)) -> 0
B101: =IF(Portfolio!C124<>"",Portfolio!C124,"") -> 40 | C101: =IF(Portfolio!D124<>"",Portfolio!D124,"") | D101: =SUMPRODUCT((Portfolio!$L124=D$4)*(Portfolio!$L126)) -> 0 | E101: =SUMPRODUCT((Portfolio!$L124=E$4)*(Portfolio!$L126)) -> 0 | F101: =SUMPRODUCT((Portfolio!$L124=F$4)*(Portfolio!$L126)) -> 0 | G101: =SUMPRODUCT((Portfolio!$L124=G$4)*(Portfolio!$L126)) -> 0 | H101: =SUMPRODUCT((Portfolio!$L124=H$4)*(Portfolio!$L126)) -> 0 | I101: =SUMPRODUCT((Portfolio!$L124=I$4)*(Portfolio!$L126)) -> 0 | J101: =SUMPRODUCT((Portfolio!$L124=J$4)*(Portfolio!$L126)) -> 0 | K101: =SUMPRODUCT((Portfolio!$L124=K$4)*(Portfolio!$L126)) -> 0 | ... AU101: =SUMPRODUCT((Portfolio!$L124=AU$4)*(Portfolio!$L126)) -> 0
B102: =IF(Portfolio!C127<>"",Portfolio!C127,"") -> 41 | C102: =IF(Portfolio!D127<>"",Portfolio!D127,"") | D102: =SUMPRODUCT((Portfolio!$L127=D$4)*(Portfolio!$L129)) -> 0 | E102: =SUMPRODUCT((Portfolio!$L127=E$4)*(Portfolio!$L129)) -> 0 | F102: =SUMPRODUCT((Portfolio!$L127=F$4)*(Portfolio!$L129)) -> 0 | G102: =SUMPRODUCT((Portfolio!$L127=G$4)*(Portfolio!$L129)) -> 0 | H102: =SUMPRODUCT((Portfolio!$L127=H$4)*(Portfolio!$L129)) -> 0 | I102: =SUMPRODUCT((Portfolio!$L127=I$4)*(Portfolio!$L129)) -> 0 | J102: =SUMPRODUCT((Portfolio!$L127=J$4)*(Portfolio!$L129)) -> 0 | K102: =SUMPRODUCT((Portfolio!$L127=K$4)*(Portfolio!$L129)) -> 0 | ... AU102: =SUMPRODUCT((Portfolio!$L127=AU$4)*(Portfolio!$L129)) -> 0
...
